Classfile /home/krzysiek/workspace/scala-bcode-cutter/talk_n_blog/nested/target/scala-2.12/classes/NestedObject.class
  Last modified Nov 23, 2017; size 1589 bytes
  MD5 checksum a4e0404f202a371d1696752092eab059
  Compiled from "Nested.scala"
public class NestedObject
  minor version: 0
  major version: 52
  flags: ACC_PUBLIC, ACC_SUPER
Constant pool:
   #1 = Utf8               NestedObject
   #2 = Class              #1             // NestedObject
   #3 = Utf8               java/lang/Object
   #4 = Class              #3             // java/lang/Object
   #5 = Utf8               Nested.scala
   #6 = Utf8               Lscala/reflect/ScalaSignature;
   #7 = Utf8               bytes
   #8 = Utf8               2A!\taa*Z:uK|%M[3di*\t1!A=K6H/ MA\t)i)1oY1mC&1:L(+4\t5A\rqJg.;?)yC\t\"\n\t!B8viHC !\t)BD5AqC1)ByI|w \nmAA)sK,g-=\t11:j]T!a\t\nA\"a\n\rB!aA%oi
   #9 = Utf8               NestedObject$inner$3$
  #10 = Class              #9             // NestedObject$inner$3$
  #11 = Utf8               inner$3$
  #12 = Utf8               outer
  #13 = Utf8               (I)Ljava/lang/String;
  #14 = Utf8               a
  #15 = Utf8               scala/runtime/LazyRef
  #16 = Class              #15            // scala/runtime/LazyRef
  #17 = Utf8               <init>
  #18 = Utf8               ()V
  #19 = NameAndType        #17:#18        // "<init>":()V
  #20 = Methodref          #16.#19        // scala/runtime/LazyRef."<init>":()V
  #21 = Utf8               inner$2
  #22 = Utf8               (Lscala/runtime/LazyRef;)LNestedObject$inner$3$;
  #23 = NameAndType        #21:#22        // inner$2:(Lscala/runtime/LazyRef;)LNestedObject$inner$3$;
  #24 = Methodref          #2.#23         // NestedObject.inner$2:(Lscala/runtime/LazyRef;)LNestedObject$inner$3$;
  #25 = Utf8               toString
  #26 = Utf8               ()Ljava/lang/String;
  #27 = NameAndType        #25:#26        // toString:()Ljava/lang/String;
  #28 = Methodref          #10.#27        // NestedObject$inner$3$.toString:()Ljava/lang/String;
  #29 = Utf8               inner$module
  #30 = Utf8               Lscala/runtime/LazyRef;
  #31 = Utf8               this
  #32 = Utf8               LNestedObject;
  #33 = Utf8               I
  #34 = Utf8               inner$lzycompute$1
  #35 = Utf8               inner$module$1
  #36 = Utf8               initialized
  #37 = Utf8               ()Z
  #38 = NameAndType        #36:#37        // initialized:()Z
  #39 = Methodref          #16.#38        // scala/runtime/LazyRef.initialized:()Z
  #40 = Utf8               value
  #41 = Utf8               ()Ljava/lang/Object;
  #42 = NameAndType        #40:#41        // value:()Ljava/lang/Object;
  #43 = Methodref          #16.#42        // scala/runtime/LazyRef.value:()Ljava/lang/Object;
  #44 = Utf8               (LNestedObject;)V
  #45 = NameAndType        #17:#44        // "<init>":(LNestedObject;)V
  #46 = Methodref          #10.#45        // NestedObject$inner$3$."<init>":(LNestedObject;)V
  #47 = Utf8               initialize
  #48 = Utf8               (Ljava/lang/Object;)Ljava/lang/Object;
  #49 = NameAndType        #47:#48        // initialize:(Ljava/lang/Object;)Ljava/lang/Object;
  #50 = Methodref          #16.#49        // scala/runtime/LazyRef.initialize:(Ljava/lang/Object;)Ljava/lang/Object;
  #51 = Utf8               java/lang/Throwable
  #52 = Class              #51            // java/lang/Throwable
  #53 = NameAndType        #34:#22        // inner$lzycompute$1:(Lscala/runtime/LazyRef;)LNestedObject$inner$3$;
  #54 = Methodref          #2.#53         // NestedObject.inner$lzycompute$1:(Lscala/runtime/LazyRef;)LNestedObject$inner$3$;
  #55 = Methodref          #4.#19         // java/lang/Object."<init>":()V
  #56 = Utf8               Code
  #57 = Utf8               LocalVariableTable
  #58 = Utf8               LineNumberTable
  #59 = Utf8               MethodParameters
  #60 = Utf8               StackMapTable
  #61 = Utf8               SourceFile
  #62 = Utf8               InnerClasses
  #63 = Utf8               RuntimeVisibleAnnotations
  #64 = Utf8               ScalaInlineInfo
  #65 = Utf8               ScalaSig
{
  public java.lang.String outer(int);
    descriptor: (I)Ljava/lang/String;
    flags: ACC_PUBLIC
    Code:
      stack=2, locals=3, args_size=2
         0: new           #16                 // class scala/runtime/LazyRef
         3: dup
         4: invokespecial #20                 // Method scala/runtime/LazyRef."<init>":()V
         7: astore_2
         8: aload_0
         9: aload_2
        10: invokespecial #24                 // Method inner$2:(Lscala/runtime/LazyRef;)LNestedObject$inner$3$;
        13: invokevirtual #28                 // Method NestedObject$inner$3$.toString:()Ljava/lang/String;
        16: areturn
      LocalVariableTable:
        Start  Length  Slot  Name   Signature
            7       9     2 inner$module   Lscala/runtime/LazyRef;
            0      17     0  this   LNestedObject;
            0      17     1     a   I
      LineNumberTable:
        line 10: 0
        line 11: 8
    MethodParameters:
      Name                           Flags
      a                              final

  private static final NestedObject$inner$3$ inner$lzycompute$1(scala.runtime.LazyRef);
    descriptor: (Lscala/runtime/LazyRef;)LNestedObject$inner$3$;
    flags: ACC_PRIVATE, ACC_STATIC, ACC_FINAL, ACC_SYNTHETIC
    Code:
      stack=4, locals=3, args_size=1
         0: aload_0
         1: dup
         2: astore_1
         3: monitorenter
         4: aload_0
         5: invokevirtual #39                 // Method scala/runtime/LazyRef.initialized:()Z
         8: ifeq          21
        11: aload_0
        12: invokevirtual #43                 // Method scala/runtime/LazyRef.value:()Ljava/lang/Object;
        15: checkcast     #10                 // class NestedObject$inner$3$
        18: goto          36
        21: aload_0
        22: new           #10                 // class NestedObject$inner$3$
        25: dup
        26: aconst_null
        27: invokespecial #46                 // Method NestedObject$inner$3$."<init>":(LNestedObject;)V
        30: invokevirtual #50                 // Method scala/runtime/LazyRef.initialize:(Ljava/lang/Object;)Ljava/lang/Object;
        33: checkcast     #10                 // class NestedObject$inner$3$
        36: astore_2
        37: aload_1
        38: monitorexit
        39: aload_2
        40: goto          46
        43: aload_1
        44: monitorexit
        45: athrow
        46: areturn
      Exception table:
         from    to  target type
             4    37    43   any
      LocalVariableTable:
        Start  Length  Slot  Name   Signature
            0      47     0 inner$module$1   Lscala/runtime/LazyRef;
      LineNumberTable:
        line 10: 0
      StackMapTable: number_of_entries = 4
        frame_type = 252 /* append */
          offset_delta = 21
          locals = [ class scala/runtime/LazyRef ]
        frame_type = 78 /* same_locals_1_stack_item */
          stack = [ class NestedObject$inner$3$ ]
        frame_type = 70 /* same_locals_1_stack_item */
          stack = [ class java/lang/Throwable ]
        frame_type = 255 /* full_frame */
          offset_delta = 2
          locals = [ class scala/runtime/LazyRef, class scala/runtime/LazyRef, class NestedObject$inner$3$ ]
          stack = [ class NestedObject$inner$3$ ]
    MethodParameters:
      Name                           Flags
      inner$module$1                 final

  private final NestedObject$inner$3$ inner$2(scala.runtime.LazyRef);
    descriptor: (Lscala/runtime/LazyRef;)LNestedObject$inner$3$;
    flags: ACC_PRIVATE, ACC_FINAL
    Code:
      stack=1, locals=2, args_size=2
         0: aload_1
         1: invokevirtual #39                 // Method scala/runtime/LazyRef.initialized:()Z
         4: ifeq          17
         7: aload_1
         8: invokevirtual #43                 // Method scala/runtime/LazyRef.value:()Ljava/lang/Object;
        11: checkcast     #10                 // class NestedObject$inner$3$
        14: goto          21
        17: aload_1
        18: invokestatic  #54                 // Method inner$lzycompute$1:(Lscala/runtime/LazyRef;)LNestedObject$inner$3$;
        21: areturn
      LocalVariableTable:
        Start  Length  Slot  Name   Signature
            0      22     0  this   LNestedObject;
            0      22     1 inner$module$1   Lscala/runtime/LazyRef;
      LineNumberTable:
        line 10: 0
      StackMapTable: number_of_entries = 2
        frame_type = 17 /* same */
        frame_type = 67 /* same_locals_1_stack_item */
          stack = [ class NestedObject$inner$3$ ]
    MethodParameters:
      Name                           Flags
      inner$module$1                 final

  public NestedObject();
    descriptor: ()V
    flags: ACC_PUBLIC
    Code:
      stack=1, locals=1, args_size=1
         0: aload_0
         1: invokespecial #55                 // Method java/lang/Object."<init>":()V
         4: return
      LocalVariableTable:
        Start  Length  Slot  Name   Signature
            0       5     0  this   LNestedObject;
      LineNumberTable:
        line 13: 0
        line 8: 4
}
SourceFile: "Nested.scala"
InnerClasses:
     public #11= #10; //inner$3$=class NestedObject$inner$3$
RuntimeVisibleAnnotations:
  0: #6(#7=s#8)
Error: unknown attribute
  ScalaInlineInfo: length = 0x18
   01 00 00 04 00 11 00 12 00 00 15 00 16 01 00 22
   00 16 01 00 0C 00 0D 00
Error: unknown attribute
  ScalaSig: length = 0x3
   05 00 00
