Compiled from "PatMatSkillTrees.scala"
public final class rpg.patmat.SlowPathMatSkillTrees$$anon$2 extends rpg.SkillTreeRepr<rpg.patmat.DexTree> {
  private final rpg.PlayerTraits traits$2;

  public int totalCost();
    Code:
       0: getstatic     #21                 // Field rpg/patmat/Node$.MODULE$:Lrpg/patmat/Node$;
       3: aload_0
       4: invokevirtual #25                 // Method tree:()Ljava/lang/Object;
       7: checkcast     #27                 // class rpg/patmat/Node
      10: aload_0
      11: getfield      #29                 // Field traits$2:Lrpg/PlayerTraits;
      14: invokevirtual #33                 // Method rpg/patmat/Node$.slowTotalSkill:(Lrpg/patmat/Node;Lrpg/PlayerTraits;)I
      17: ireturn

  public rpg.patmat.SlowPathMatSkillTrees$$anon$2(rpg.patmat.SlowPathMatSkillTrees, rpg.PlayerTraits);
    Code:
       0: aload_0
       1: aload_2
       2: putfield      #29                 // Field traits$2:Lrpg/PlayerTraits;
       5: aload_0
       6: aload_1
       7: invokevirtual #42                 // Method rpg/patmat/SlowPathMatSkillTrees.mkTree:()Lrpg/patmat/DexTree;
      10: invokespecial #45                 // Method rpg/SkillTreeRepr."<init>":(Ljava/lang/Object;)V
      13: return
}
