Classfile /home/krzysiek/workspace/scala-bcode-cutter/pref/target/scala-2.12/classes/rpg/patmat/PatMatSkillTrees.class
  Last modified Apr 8, 2018; size 1411 bytes
  MD5 checksum b18befeb0a76febda3000d738249b7f9
  Compiled from "PatMatSkillTrees.scala"
public class rpg.patmat.PatMatSkillTrees extends rpg.SkillTrees implements rpg.patmat.TreeProvider
  minor version: 0
  major version: 52
  flags: ACC_PUBLIC, ACC_SUPER
Constant pool:
   #1 = Utf8               rpg/patmat/PatMatSkillTrees
   #2 = Class              #1             // rpg/patmat/PatMatSkillTrees
   #3 = Utf8               rpg/SkillTrees
   #4 = Class              #3             // rpg/SkillTrees
   #5 = Utf8               rpg/patmat/TreeProvider
   #6 = Class              #5             // rpg/patmat/TreeProvider
   #7 = Utf8               PatMatSkillTrees.scala
   #8 = Utf8               Lscala/reflect/ScalaSignature;
   #9 = Utf8               bytes
  #10 = Utf8               92A!\t+;NCR6.7m)J,Wm\ta]1u[$(\"AIxmAA\n5\tA!\t\tQ1k[5mYRX-Z:5qQ\"\n=!+sK&o<jI\"B\t\tAj]&$hF!\tiCc#AbeDWM]=Ue,GCA*a\tARE\n3mI!AM[7Ue,'+9s!\taRy!!Ay\"aA0%cEE\n\tCjA\tG)1oY1mC&QE\t>$.8h!\t\ts%)E\tI\=\t)\"A\rQ-;t!\tIA&.\t\ta\1zKJ$&/Y5ug
  #11 = Utf8               rpg/patmat/PatMatSkillTrees$$anon$1
  #12 = Class              #11            // rpg/patmat/PatMatSkillTrees$$anon$1
  #13 = Utf8               mkTree
  #14 = Utf8               ()Lrpg/patmat/DexTree;
  #15 = Utf8               mkTree$
  #16 = Utf8               (Lrpg/patmat/TreeProvider;)Lrpg/patmat/DexTree;
  #17 = NameAndType        #15:#16        // mkTree$:(Lrpg/patmat/TreeProvider;)Lrpg/patmat/DexTree;
  #18 = InterfaceMethodref #6.#17         // rpg/patmat/TreeProvider.mkTree$:(Lrpg/patmat/TreeProvider;)Lrpg/patmat/DexTree;
  #19 = Utf8               this
  #20 = Utf8               Lrpg/patmat/PatMatSkillTrees;
  #21 = Utf8               archeryTree
  #22 = Utf8               (Lrpg/PlayerTraits;)Lrpg/SkillTreeRepr;
  #23 = Utf8               traits
  #24 = Utf8               <init>
  #25 = Utf8               (Lrpg/patmat/PatMatSkillTrees;Lrpg/PlayerTraits;)V
  #26 = NameAndType        #24:#25        // "<init>":(Lrpg/patmat/PatMatSkillTrees;Lrpg/PlayerTraits;)V
  #27 = Methodref          #12.#26        // rpg/patmat/PatMatSkillTrees$$anon$1."<init>":(Lrpg/patmat/PatMatSkillTrees;Lrpg/PlayerTraits;)V
  #28 = Utf8               Lrpg/PlayerTraits;
  #29 = Utf8               ()V
  #30 = NameAndType        #24:#29        // "<init>":()V
  #31 = Methodref          #4.#30         // rpg/SkillTrees."<init>":()V
  #32 = Utf8               $init$
  #33 = Utf8               (Lrpg/patmat/TreeProvider;)V
  #34 = NameAndType        #32:#33        // $init$:(Lrpg/patmat/TreeProvider;)V
  #35 = InterfaceMethodref #6.#34         // rpg/patmat/TreeProvider.$init$:(Lrpg/patmat/TreeProvider;)V
  #36 = Utf8               Code
  #37 = Utf8               LocalVariableTable
  #38 = Utf8               LineNumberTable
  #39 = Utf8               Signature
  #40 = Utf8               (Lrpg/PlayerTraits;)Lrpg/SkillTreeRepr<*>;
  #41 = Utf8               MethodParameters
  #42 = Utf8               SourceFile
  #43 = Utf8               InnerClasses
  #44 = Utf8               RuntimeVisibleAnnotations
  #45 = Utf8               ScalaInlineInfo
  #46 = Utf8               ScalaSig
{
  public rpg.patmat.DexTree mkTree();
    descriptor: ()Lrpg/patmat/DexTree;
    flags: ACC_PUBLIC
    Code:
      stack=1, locals=1, args_size=1
         0: aload_0
         1: invokestatic  #18                 // InterfaceMethod rpg/patmat/TreeProvider.mkTree$:(Lrpg/patmat/TreeProvider;)Lrpg/patmat/DexTree;
         4: areturn
      LocalVariableTable:
        Start  Length  Slot  Name   Signature
            0       5     0  this   Lrpg/patmat/PatMatSkillTrees;
      LineNumberTable:
        line 95: 0

  public rpg.SkillTreeRepr<?> archeryTree(rpg.PlayerTraits);
    descriptor: (Lrpg/PlayerTraits;)Lrpg/SkillTreeRepr;
    flags: ACC_PUBLIC
    Code:
      stack=4, locals=2, args_size=2
         0: new           #12                 // class rpg/patmat/PatMatSkillTrees$$anon$1
         3: dup
         4: aload_0
         5: aload_1
         6: invokespecial #27                 // Method rpg/patmat/PatMatSkillTrees$$anon$1."<init>":(Lrpg/patmat/PatMatSkillTrees;Lrpg/PlayerTraits;)V
         9: areturn
      LocalVariableTable:
        Start  Length  Slot  Name   Signature
            0      10     0  this   Lrpg/patmat/PatMatSkillTrees;
            0      10     1 traits   Lrpg/PlayerTraits;
      LineNumberTable:
        line 97: 0
    Signature: #40                          // (Lrpg/PlayerTraits;)Lrpg/SkillTreeRepr<*>;
    MethodParameters:
      Name                           Flags
      traits                         final

  public rpg.patmat.PatMatSkillTrees();
    descriptor: ()V
    flags: ACC_PUBLIC
    Code:
      stack=1, locals=1, args_size=1
         0: aload_0
         1: invokespecial #31                 // Method rpg/SkillTrees."<init>":()V
         4: aload_0
         5: invokestatic  #35                 // InterfaceMethod rpg/patmat/TreeProvider.$init$:(Lrpg/patmat/TreeProvider;)V
         8: return
      LocalVariableTable:
        Start  Length  Slot  Name   Signature
            0       9     0  this   Lrpg/patmat/PatMatSkillTrees;
      LineNumberTable:
        line 95: 0
}
SourceFile: "PatMatSkillTrees.scala"
InnerClasses:
     public final #12; //class rpg/patmat/PatMatSkillTrees$$anon$1
RuntimeVisibleAnnotations:
  0: #8(#9=s#10)
Error: unknown attribute
  ScalaInlineInfo: length = 0x13
   01 00 00 03 00 18 00 1D 00 00 15 00 16 00 00 0D
   00 0E 00
Error: unknown attribute
  ScalaSig: length = 0x3
   05 00 00
