Compiled from "TypeclassSkillTrees.scala"
public final class rpg.typeclass.naive.Node$$anon$8 implements rpg.typeclass.naive.Node$Summer<rpg.typeclass.naive.StrTree<L, R>> {
  private final rpg.typeclass.naive.Node$Summer evidence$6$1;

  private final rpg.typeclass.naive.Node$Summer evidence$7$1;

  public int sumExp(rpg.typeclass.naive.StrTree<L, R>, rpg.PlayerTraits);
    Code:
       0: getstatic     #29                 // Field scala/Predef$.MODULE$:Lscala/Predef$;
       3: aload_0
       4: getfield      #31                 // Field evidence$6$1:Lrpg/typeclass/naive/Node$Summer;
       7: invokevirtual #35                 // Method scala/Predef$.implicitly:(Ljava/lang/Object;)Ljava/lang/Object;
      10: checkcast     #7                  // class rpg/typeclass/naive/Node$Summer
      13: aload_1
      14: invokevirtual #41                 // Method rpg/typeclass/naive/StrTree.left:()Ljava/lang/Object;
      17: aload_2
      18: invokeinterface #44,  3           // InterfaceMethod rpg/typeclass/naive/Node$Summer.sumExp:(Ljava/lang/Object;Lrpg/PlayerTraits;)I
      23: getstatic     #29                 // Field scala/Predef$.MODULE$:Lscala/Predef$;
      26: aload_0
      27: getfield      #46                 // Field evidence$7$1:Lrpg/typeclass/naive/Node$Summer;
      30: invokevirtual #35                 // Method scala/Predef$.implicitly:(Ljava/lang/Object;)Ljava/lang/Object;
      33: checkcast     #7                  // class rpg/typeclass/naive/Node$Summer
      36: aload_1
      37: invokevirtual #49                 // Method rpg/typeclass/naive/StrTree.right:()Ljava/lang/Object;
      40: aload_2
      41: invokeinterface #44,  3           // InterfaceMethod rpg/typeclass/naive/Node$Summer.sumExp:(Ljava/lang/Object;Lrpg/PlayerTraits;)I
      46: iadd
      47: aload_2
      48: invokevirtual #55                 // Method rpg/PlayerTraits.strCost:()I
      51: iadd
      52: ireturn

  public int sumExp(java.lang.Object, rpg.PlayerTraits);
    Code:
       0: aload_0
       1: aload_1
       2: checkcast     #37                 // class rpg/typeclass/naive/StrTree
       5: aload_2
       6: invokevirtual #61                 // Method sumExp:(Lrpg/typeclass/naive/StrTree;Lrpg/PlayerTraits;)I
       9: ireturn

  public rpg.typeclass.naive.Node$$anon$8(rpg.typeclass.naive.Node$Summer, rpg.typeclass.naive.Node$Summer);
    Code:
       0: aload_0
       1: aload_1
       2: putfield      #31                 // Field evidence$6$1:Lrpg/typeclass/naive/Node$Summer;
       5: aload_0
       6: aload_2
       7: putfield      #46                 // Field evidence$7$1:Lrpg/typeclass/naive/Node$Summer;
      10: aload_0
      11: invokespecial #67                 // Method java/lang/Object."<init>":()V
      14: return
}
