Classfile /home/krzysiek/workspace/scala-bcode-cutter/pref/target/scala-2.12/classes/rpg/ooo/StrStep.class
  Last modified Apr 8, 2018; size 4515 bytes
  MD5 checksum 1df3519f7eb225b9af8049cf064b1c16
  Compiled from "OOOSkillTrees.scala"
public class rpg.ooo.StrStep implements rpg.ooo.Node,scala.Product,scala.Serializable
  minor version: 0
  major version: 52
  flags: ACC_PUBLIC, ACC_SUPER
Constant pool:
    #1 = Utf8               rpg/ooo/StrStep
    #2 = Class              #1            // rpg/ooo/StrStep
    #3 = Utf8               java/lang/Object
    #4 = Class              #3            // java/lang/Object
    #5 = Utf8               rpg/ooo/Node
    #6 = Class              #5            // rpg/ooo/Node
    #7 = Utf8               scala/Product
    #8 = Class              #7            // scala/Product
    #9 = Utf8               scala/Serializable
   #10 = Class              #9            // scala/Serializable
   #11 = Utf8               OOOSkillTrees.scala
   #12 = Utf8               Lscala/reflect/ScalaSignature;
   #13 = Utf8               bytes
   #14 = Utf8               }aBqa;s'R,O\tqn\8\t1A9hR%U\"!)QaCgG.Y)a!8z%4CABA\tquZ3%B&o3vGR\"!\n]Q!D*fe&G.>bE2,C\r+IQ|W#\tq!#Q\n9\t1^8!q\" aN\5u}Q%\t\tAQ!GA9AQa\tB\nAaY8tiRQ\tJ!a\n%sGC*E!&ueLGo\tW1jB[A7bsHK]1jiNDqa'd_BLHC2Ib%AA9Aqa\rA'd_BLHZ3gCVdGJUR#A,]\"OeR!AOUt7\r[3dW$'B)\tgN\8uCRLwN\}e#8dQ7.3WCJLM\2f!!ABQ:pIVG:fM&DX#\"\rCU\"#37b]TaRU4-J\t\n11:j]DqaA*qe>$Wo;Be&$0F&q!!A=a:pIVG/7f[tGQ'B\"U%*1!8z!V*!AA\n121!!AB]q:pIVG/;fe$xN]1B)iS!a\r|G\3di&|g.^5\nA\n^3sCR|'C`I1\rg.R9vC2$\"!3%BA2un7fC:Dq0CgII4!7[\"pI$!\nS\t\t\"k!!xn;sS:<G#\"\t1!C![1Q-];bYN$\"!8\tQ[!a!9OAA\taB*ueN#X\r\tI4q!#1oEsiVB!=A5\taOx9!/8uS6,BA=wE\t%m;sC$h)8di&|g.\r=I$\tac\"9N]A\nRb@s%\ti`CBH.A\"B\r~q\"CAeIQA)h.9qYf$B!!A!\"a\r\tiAB$n8\tE1AAa=%a!IQ:%qCeGMU3t_24X\rA1)a\nuAIPE*,7\r
   #15 = Utf8               to
   #16 = Utf8               Lrpg/ooo/Node;
   #17 = Utf8               unapply
   #18 = Utf8               (Lrpg/ooo/StrStep;)Lscala/Option;
   #19 = Utf8               rpg/ooo/StrStep$
   #20 = Class              #19           // rpg/ooo/StrStep$
   #21 = Utf8               MODULE$
   #22 = Utf8               Lrpg/ooo/StrStep$;
   #23 = NameAndType        #21:#22       // MODULE$:Lrpg/ooo/StrStep$;
   #24 = Fieldref           #20.#23       // rpg/ooo/StrStep$.MODULE$:Lrpg/ooo/StrStep$;
   #25 = NameAndType        #17:#18       // unapply:(Lrpg/ooo/StrStep;)Lscala/Option;
   #26 = Methodref          #20.#25       // rpg/ooo/StrStep$.unapply:(Lrpg/ooo/StrStep;)Lscala/Option;
   #27 = Utf8               apply
   #28 = Utf8               (Lrpg/ooo/Node;)Lrpg/ooo/StrStep;
   #29 = NameAndType        #27:#28       // apply:(Lrpg/ooo/Node;)Lrpg/ooo/StrStep;
   #30 = Methodref          #20.#29       // rpg/ooo/StrStep$.apply:(Lrpg/ooo/Node;)Lrpg/ooo/StrStep;
   #31 = Utf8               andThen
   #32 = Utf8               (Lscala/Function1;)Lscala/Function1;
   #33 = NameAndType        #31:#32       // andThen:(Lscala/Function1;)Lscala/Function1;
   #34 = Methodref          #20.#33       // rpg/ooo/StrStep$.andThen:(Lscala/Function1;)Lscala/Function1;
   #35 = Utf8               compose
   #36 = NameAndType        #35:#32       // compose:(Lscala/Function1;)Lscala/Function1;
   #37 = Methodref          #20.#36       // rpg/ooo/StrStep$.compose:(Lscala/Function1;)Lscala/Function1;
   #38 = Utf8               ()Lrpg/ooo/Node;
   #39 = NameAndType        #15:#16       // to:Lrpg/ooo/Node;
   #40 = Fieldref           #2.#39        // rpg/ooo/StrStep.to:Lrpg/ooo/Node;
   #41 = Utf8               this
   #42 = Utf8               Lrpg/ooo/StrStep;
   #43 = Utf8               cost
   #44 = Utf8               (Lrpg/PlayerTraits;)I
   #45 = Utf8               traits
   #46 = NameAndType        #15:#38       // to:()Lrpg/ooo/Node;
   #47 = Methodref          #2.#46        // rpg/ooo/StrStep.to:()Lrpg/ooo/Node;
   #48 = NameAndType        #43:#44       // cost:(Lrpg/PlayerTraits;)I
   #49 = InterfaceMethodref #6.#48        // rpg/ooo/Node.cost:(Lrpg/PlayerTraits;)I
   #50 = Utf8               rpg/PlayerTraits
   #51 = Class              #50           // rpg/PlayerTraits
   #52 = Utf8               strCost
   #53 = Utf8               ()I
   #54 = NameAndType        #52:#53       // strCost:()I
   #55 = Methodref          #51.#54       // rpg/PlayerTraits.strCost:()I
   #56 = Utf8               Lrpg/PlayerTraits;
   #57 = Utf8               copy
   #58 = Utf8               <init>
   #59 = Utf8               (Lrpg/ooo/Node;)V
   #60 = NameAndType        #58:#59       // "<init>":(Lrpg/ooo/Node;)V
   #61 = Methodref          #2.#60        // rpg/ooo/StrStep."<init>":(Lrpg/ooo/Node;)V
   #62 = Utf8               copy$default$1
   #63 = Utf8               productPrefix
   #64 = Utf8               ()Ljava/lang/String;
   #65 = Utf8               StrStep
   #66 = String             #65           // StrStep
   #67 = Utf8               productArity
   #68 = Utf8               productElement
   #69 = Utf8               (I)Ljava/lang/Object;
   #70 = Utf8               x$1
   #71 = Utf8               java/lang/IndexOutOfBoundsException
   #72 = Class              #71           // java/lang/IndexOutOfBoundsException
   #73 = Utf8               scala/runtime/BoxesRunTime
   #74 = Class              #73           // scala/runtime/BoxesRunTime
   #75 = Utf8               boxToInteger
   #76 = Utf8               (I)Ljava/lang/Integer;
   #77 = NameAndType        #75:#76       // boxToInteger:(I)Ljava/lang/Integer;
   #78 = Methodref          #74.#77       // scala/runtime/BoxesRunTime.boxToInteger:(I)Ljava/lang/Integer;
   #79 = Utf8               toString
   #80 = NameAndType        #79:#64       // toString:()Ljava/lang/String;
   #81 = Methodref          #4.#80        // java/lang/Object.toString:()Ljava/lang/String;
   #82 = Utf8               (Ljava/lang/String;)V
   #83 = NameAndType        #58:#82       // "<init>":(Ljava/lang/String;)V
   #84 = Methodref          #72.#83       // java/lang/IndexOutOfBoundsException."<init>":(Ljava/lang/String;)V
   #85 = Utf8               I
   #86 = Utf8               productIterator
   #87 = Utf8               ()Lscala/collection/Iterator;
   #88 = Utf8               scala/runtime/ScalaRunTime$
   #89 = Class              #88           // scala/runtime/ScalaRunTime$
   #90 = Utf8               Lscala/runtime/ScalaRunTime$;
   #91 = NameAndType        #21:#90       // MODULE$:Lscala/runtime/ScalaRunTime$;
   #92 = Fieldref           #89.#91       // scala/runtime/ScalaRunTime$.MODULE$:Lscala/runtime/ScalaRunTime$;
   #93 = Utf8               typedProductIterator
   #94 = Utf8               (Lscala/Product;)Lscala/collection/Iterator;
   #95 = NameAndType        #93:#94       // typedProductIterator:(Lscala/Product;)Lscala/collection/Iterator;
   #96 = Methodref          #89.#95       // scala/runtime/ScalaRunTime$.typedProductIterator:(Lscala/Product;)Lscala/collection/Iterator;
   #97 = Utf8               canEqual
   #98 = Utf8               (Ljava/lang/Object;)Z
   #99 = Utf8               Ljava/lang/Object;
  #100 = Utf8               hashCode
  #101 = Utf8               _hashCode
  #102 = Utf8               (Lscala/Product;)I
  #103 = NameAndType        #101:#102     // _hashCode:(Lscala/Product;)I
  #104 = Methodref          #89.#103      // scala/runtime/ScalaRunTime$._hashCode:(Lscala/Product;)I
  #105 = Utf8               _toString
  #106 = Utf8               (Lscala/Product;)Ljava/lang/String;
  #107 = NameAndType        #105:#106     // _toString:(Lscala/Product;)Ljava/lang/String;
  #108 = Methodref          #89.#107      // scala/runtime/ScalaRunTime$._toString:(Lscala/Product;)Ljava/lang/String;
  #109 = Utf8               equals
  #110 = NameAndType        #109:#98      // equals:(Ljava/lang/Object;)Z
  #111 = Methodref          #4.#110       // java/lang/Object.equals:(Ljava/lang/Object;)Z
  #112 = NameAndType        #97:#98       // canEqual:(Ljava/lang/Object;)Z
  #113 = Methodref          #2.#112       // rpg/ooo/StrStep.canEqual:(Ljava/lang/Object;)Z
  #114 = Utf8               ()V
  #115 = NameAndType        #58:#114      // "<init>":()V
  #116 = Methodref          #4.#115       // java/lang/Object."<init>":()V
  #117 = Utf8               $init$
  #118 = Utf8               (Lscala/Product;)V
  #119 = NameAndType        #117:#118     // $init$:(Lscala/Product;)V
  #120 = InterfaceMethodref #8.#119       // scala/Product.$init$:(Lscala/Product;)V
  #121 = Utf8               Code
  #122 = Utf8               Signature
  #123 = Utf8               (Lrpg/ooo/StrStep;)Lscala/Option<Lrpg/ooo/Node;>;
  #124 = Utf8               <A:Ljava/lang/Object;>(Lscala/Function1<Lrpg/ooo/StrStep;TA;>;)Lscala/Function1<Lrpg/ooo/Node;TA;>;
  #125 = Utf8               <A:Ljava/lang/Object;>(Lscala/Function1<TA;Lrpg/ooo/Node;>;)Lscala/Function1<TA;Lrpg/ooo/StrStep;>;
  #126 = Utf8               LocalVariableTable
  #127 = Utf8               LineNumberTable
  #128 = Utf8               MethodParameters
  #129 = Utf8               StackMapTable
  #130 = Utf8               ()Lscala/collection/Iterator<Ljava/lang/Object;>;
  #131 = Utf8               SourceFile
  #132 = Utf8               RuntimeVisibleAnnotations
  #133 = Utf8               ScalaInlineInfo
  #134 = Utf8               ScalaSig
{
  private final rpg.ooo.Node to;
    descriptor: Lrpg/ooo/Node;
    flags: ACC_PRIVATE, ACC_FINAL

  public static scala.Option<rpg.ooo.Node> unapply(rpg.ooo.StrStep);
    descriptor: (Lrpg/ooo/StrStep;)Lscala/Option;
    flags: ACC_PUBLIC, ACC_STATIC
    Code:
      stack=2, locals=1, args_size=1
         0: getstatic     #24                 // Field rpg/ooo/StrStep$.MODULE$:Lrpg/ooo/StrStep$;
         3: aload_0
         4: invokevirtual #26                 // Method rpg/ooo/StrStep$.unapply:(Lrpg/ooo/StrStep;)Lscala/Option;
         7: areturn
    Signature: #123                         // (Lrpg/ooo/StrStep;)Lscala/Option<Lrpg/ooo/Node;>;

  public static rpg.ooo.StrStep apply(rpg.ooo.Node);
    descriptor: (Lrpg/ooo/Node;)Lrpg/ooo/StrStep;
    flags: ACC_PUBLIC, ACC_STATIC
    Code:
      stack=2, locals=1, args_size=1
         0: getstatic     #24                 // Field rpg/ooo/StrStep$.MODULE$:Lrpg/ooo/StrStep$;
         3: aload_0
         4: invokevirtual #30                 // Method rpg/ooo/StrStep$.apply:(Lrpg/ooo/Node;)Lrpg/ooo/StrStep;
         7: areturn

  public static <A extends java.lang.Object> scala.Function1<rpg.ooo.Node, A> andThen(scala.Function1<rpg.ooo.StrStep, A>);
    descriptor: (Lscala/Function1;)Lscala/Function1;
    flags: ACC_PUBLIC, ACC_STATIC
    Code:
      stack=2, locals=1, args_size=1
         0: getstatic     #24                 // Field rpg/ooo/StrStep$.MODULE$:Lrpg/ooo/StrStep$;
         3: aload_0
         4: invokevirtual #34                 // Method rpg/ooo/StrStep$.andThen:(Lscala/Function1;)Lscala/Function1;
         7: areturn
    Signature: #124                         // <A:Ljava/lang/Object;>(Lscala/Function1<Lrpg/ooo/StrStep;TA;>;)Lscala/Function1<Lrpg/ooo/Node;TA;>;

  public static <A extends java.lang.Object> scala.Function1<A, rpg.ooo.StrStep> compose(scala.Function1<A, rpg.ooo.Node>);
    descriptor: (Lscala/Function1;)Lscala/Function1;
    flags: ACC_PUBLIC, ACC_STATIC
    Code:
      stack=2, locals=1, args_size=1
         0: getstatic     #24                 // Field rpg/ooo/StrStep$.MODULE$:Lrpg/ooo/StrStep$;
         3: aload_0
         4: invokevirtual #37                 // Method rpg/ooo/StrStep$.compose:(Lscala/Function1;)Lscala/Function1;
         7: areturn
    Signature: #125                         // <A:Ljava/lang/Object;>(Lscala/Function1<TA;Lrpg/ooo/Node;>;)Lscala/Function1<TA;Lrpg/ooo/StrStep;>;

  public rpg.ooo.Node to();
    descriptor: ()Lrpg/ooo/Node;
    flags: ACC_PUBLIC
    Code:
      stack=1, locals=1, args_size=1
         0: aload_0
         1: getfield      #40                 // Field to:Lrpg/ooo/Node;
         4: areturn
      LocalVariableTable:
        Start  Length  Slot  Name   Signature
            0       5     0  this   Lrpg/ooo/StrStep;
      LineNumberTable:
        line 27: 0

  public int cost(rpg.PlayerTraits);
    descriptor: (Lrpg/PlayerTraits;)I
    flags: ACC_PUBLIC
    Code:
      stack=2, locals=2, args_size=2
         0: aload_0
         1: invokevirtual #47                 // Method to:()Lrpg/ooo/Node;
         4: aload_1
         5: invokeinterface #49,  2           // InterfaceMethod rpg/ooo/Node.cost:(Lrpg/PlayerTraits;)I
        10: aload_1
        11: invokevirtual #55                 // Method rpg/PlayerTraits.strCost:()I
        14: iadd
        15: ireturn
      LocalVariableTable:
        Start  Length  Slot  Name   Signature
            0      16     0  this   Lrpg/ooo/StrStep;
            0      16     1 traits   Lrpg/PlayerTraits;
      LineNumberTable:
        line 28: 0
    MethodParameters:
      Name                           Flags
      traits                         final

  public rpg.ooo.StrStep copy(rpg.ooo.Node);
    descriptor: (Lrpg/ooo/Node;)Lrpg/ooo/StrStep;
    flags: ACC_PUBLIC
    Code:
      stack=3, locals=2, args_size=2
         0: new           #2                  // class rpg/ooo/StrStep
         3: dup
         4: aload_1
         5: invokespecial #61                 // Method "<init>":(Lrpg/ooo/Node;)V
         8: areturn
      LocalVariableTable:
        Start  Length  Slot  Name   Signature
            0       9     0  this   Lrpg/ooo/StrStep;
            0       9     1    to   Lrpg/ooo/Node;
      LineNumberTable:
        line 27: 0
    MethodParameters:
      Name                           Flags
      to                             final

  public rpg.ooo.Node copy$default$1();
    descriptor: ()Lrpg/ooo/Node;
    flags: ACC_PUBLIC
    Code:
      stack=1, locals=1, args_size=1
         0: aload_0
         1: invokevirtual #47                 // Method to:()Lrpg/ooo/Node;
         4: areturn
      LocalVariableTable:
        Start  Length  Slot  Name   Signature
            0       5     0  this   Lrpg/ooo/StrStep;
      LineNumberTable:
        line 27: 0

  public java.lang.String productPrefix();
    descriptor: ()Ljava/lang/String;
    flags: ACC_PUBLIC
    Code:
      stack=1, locals=1, args_size=1
         0: ldc           #66                 // String StrStep
         2: areturn
      LocalVariableTable:
        Start  Length  Slot  Name   Signature
            0       3     0  this   Lrpg/ooo/StrStep;
      LineNumberTable:
        line 27: 0

  public int productArity();
    descriptor: ()I
    flags: ACC_PUBLIC
    Code:
      stack=1, locals=1, args_size=1
         0: iconst_1
         1: ireturn
      LocalVariableTable:
        Start  Length  Slot  Name   Signature
            0       2     0  this   Lrpg/ooo/StrStep;
      LineNumberTable:
        line 27: 0

  public java.lang.Object productElement(int);
    descriptor: (I)Ljava/lang/Object;
    flags: ACC_PUBLIC
    Code:
      stack=3, locals=3, args_size=2
         0: iload_1
         1: istore_2
         2: iload_2
         3: tableswitch   { // 0 to 0
                       0: 20
                 default: 27
            }
        20: aload_0
        21: invokevirtual #47                 // Method to:()Lrpg/ooo/Node;
        24: goto          42
        27: new           #72                 // class java/lang/IndexOutOfBoundsException
        30: dup
        31: iload_1
        32: invokestatic  #78                 // Method scala/runtime/BoxesRunTime.boxToInteger:(I)Ljava/lang/Integer;
        35: invokevirtual #81                 // Method java/lang/Object.toString:()Ljava/lang/String;
        38: invokespecial #84                 // Method java/lang/IndexOutOfBoundsException."<init>":(Ljava/lang/String;)V
        41: athrow
        42: areturn
      LocalVariableTable:
        Start  Length  Slot  Name   Signature
            0      43     0  this   Lrpg/ooo/StrStep;
            0      43     1   x$1   I
      LineNumberTable:
        line 27: 0
      StackMapTable: number_of_entries = 3
        frame_type = 252 /* append */
          offset_delta = 20
          locals = [ int ]
        frame_type = 6 /* same */
        frame_type = 78 /* same_locals_1_stack_item */
          stack = [ class rpg/ooo/Node ]
    MethodParameters:
      Name                           Flags
      x$1                            final

  public scala.collection.Iterator<java.lang.Object> productIterator();
    descriptor: ()Lscala/collection/Iterator;
    flags: ACC_PUBLIC
    Code:
      stack=2, locals=1, args_size=1
         0: getstatic     #92                 // Field scala/runtime/ScalaRunTime$.MODULE$:Lscala/runtime/ScalaRunTime$;
         3: aload_0
         4: invokevirtual #96                 // Method scala/runtime/ScalaRunTime$.typedProductIterator:(Lscala/Product;)Lscala/collection/Iterator;
         7: areturn
      LocalVariableTable:
        Start  Length  Slot  Name   Signature
            0       8     0  this   Lrpg/ooo/StrStep;
      LineNumberTable:
        line 27: 0
    Signature: #130                         // ()Lscala/collection/Iterator<Ljava/lang/Object;>;

  public boolean canEqual(java.lang.Object);
    descriptor: (Ljava/lang/Object;)Z
    flags: ACC_PUBLIC
    Code:
      stack=1, locals=2, args_size=2
         0: aload_1
         1: instanceof    #2                  // class rpg/ooo/StrStep
         4: ireturn
      LocalVariableTable:
        Start  Length  Slot  Name   Signature
            0       5     0  this   Lrpg/ooo/StrStep;
            0       5     1   x$1   Ljava/lang/Object;
      LineNumberTable:
        line 27: 0
    MethodParameters:
      Name                           Flags
      x$1                            final

  public int hashCode();
    descriptor: ()I
    flags: ACC_PUBLIC
    Code:
      stack=2, locals=1, args_size=1
         0: getstatic     #92                 // Field scala/runtime/ScalaRunTime$.MODULE$:Lscala/runtime/ScalaRunTime$;
         3: aload_0
         4: invokevirtual #104                // Method scala/runtime/ScalaRunTime$._hashCode:(Lscala/Product;)I
         7: ireturn
      LocalVariableTable:
        Start  Length  Slot  Name   Signature
            0       8     0  this   Lrpg/ooo/StrStep;
      LineNumberTable:
        line 27: 0

  public java.lang.String toString();
    descriptor: ()Ljava/lang/String;
    flags: ACC_PUBLIC
    Code:
      stack=2, locals=1, args_size=1
         0: getstatic     #92                 // Field scala/runtime/ScalaRunTime$.MODULE$:Lscala/runtime/ScalaRunTime$;
         3: aload_0
         4: invokevirtual #108                // Method scala/runtime/ScalaRunTime$._toString:(Lscala/Product;)Ljava/lang/String;
         7: areturn
      LocalVariableTable:
        Start  Length  Slot  Name   Signature
            0       8     0  this   Lrpg/ooo/StrStep;
      LineNumberTable:
        line 27: 0

  public boolean equals(java.lang.Object);
    descriptor: (Ljava/lang/Object;)Z
    flags: ACC_PUBLIC
    Code:
      stack=2, locals=6, args_size=2
         0: aload_0
         1: aload_1
         2: if_acmpeq     86
         5: aload_1
         6: astore_3
         7: aload_3
         8: instanceof    #2                  // class rpg/ooo/StrStep
        11: ifeq          19
        14: iconst_1
        15: istore_2
        16: goto          27
        19: goto          22
        22: iconst_0
        23: istore_2
        24: goto          27
        27: iload_2
        28: ifeq          90
        31: aload_1
        32: checkcast     #2                  // class rpg/ooo/StrStep
        35: astore        4
        37: aload_0
        38: invokevirtual #47                 // Method to:()Lrpg/ooo/Node;
        41: aload         4
        43: invokevirtual #47                 // Method to:()Lrpg/ooo/Node;
        46: astore        5
        48: dup
        49: ifnonnull     61
        52: pop
        53: aload         5
        55: ifnull        69
        58: goto          82
        61: aload         5
        63: invokevirtual #111                // Method java/lang/Object.equals:(Ljava/lang/Object;)Z
        66: ifeq          82
        69: aload         4
        71: aload_0
        72: invokevirtual #113                // Method canEqual:(Ljava/lang/Object;)Z
        75: ifeq          82
        78: iconst_1
        79: goto          83
        82: iconst_0
        83: ifeq          90
        86: iconst_1
        87: goto          91
        90: iconst_0
        91: ireturn
      LocalVariableTable:
        Start  Length  Slot  Name   Signature
            0      92     0  this   Lrpg/ooo/StrStep;
            0      92     1   x$1   Ljava/lang/Object;
      LineNumberTable:
        line 27: 0
      StackMapTable: number_of_entries = 10
        frame_type = 253 /* append */
          offset_delta = 19
          locals = [ top, class java/lang/Object ]
        frame_type = 2 /* same */
        frame_type = 255 /* full_frame */
          offset_delta = 4
          locals = [ class rpg/ooo/StrStep, class java/lang/Object, int, class java/lang/Object ]
          stack = []
        frame_type = 255 /* full_frame */
          offset_delta = 33
          locals = [ class rpg/ooo/StrStep, class java/lang/Object, int, class java/lang/Object, class rpg/ooo/StrStep, class rpg/ooo/Node ]
          stack = [ class rpg/ooo/Node ]
        frame_type = 7 /* same */
        frame_type = 12 /* same */
        frame_type = 64 /* same_locals_1_stack_item */
          stack = [ int ]
        frame_type = 255 /* full_frame */
          offset_delta = 2
          locals = [ class rpg/ooo/StrStep, class java/lang/Object ]
          stack = []
        frame_type = 253 /* append */
          offset_delta = 3
          locals = [ int, class java/lang/Object ]
        frame_type = 255 /* full_frame */
          offset_delta = 0
          locals = [ class rpg/ooo/StrStep, class java/lang/Object ]
          stack = [ int ]
    MethodParameters:
      Name                           Flags
      x$1                            final

  public rpg.ooo.StrStep(rpg.ooo.Node);
    descriptor: (Lrpg/ooo/Node;)V
    flags: ACC_PUBLIC
    Code:
      stack=2, locals=2, args_size=2
         0: aload_0
         1: aload_1
         2: putfield      #40                 // Field to:Lrpg/ooo/Node;
         5: aload_0
         6: invokespecial #116                // Method java/lang/Object."<init>":()V
         9: aload_0
        10: invokestatic  #120                // InterfaceMethod scala/Product.$init$:(Lscala/Product;)V
        13: return
      LocalVariableTable:
        Start  Length  Slot  Name   Signature
            0      14     0  this   Lrpg/ooo/StrStep;
            0      14     1    to   Lrpg/ooo/Node;
      LineNumberTable:
        line 27: 0
    MethodParameters:
      Name                           Flags
      to                             final
}
SourceFile: "OOOSkillTrees.scala"
RuntimeVisibleAnnotations:
  0: #12(#13=s#14)
Error: unknown attribute
  ScalaInlineInfo: length = 0x45
   01 00 00 0D 00 3A 00 3B 00 00 61 00 62 00 00 3E
   00 26 00 00 39 00 1C 00 00 2B 00 2C 00 00 6D 00
   62 00 00 64 00 35 00 00 43 00 35 00 00 44 00 45
   00 00 56 00 57 00 00 3F 00 40 00 00 0F 00 26 00
   00 4F 00 40 00
Error: unknown attribute
  ScalaSig: length = 0x3
   05 00 00
