Classfile /home/krzysiek/workspace/scala-bcode-cutter/pref/target/scala-2.12/classes/rpg/typeclass/naive/WisStep.class
  Last modified Apr 8, 2018; size 4369 bytes
  MD5 checksum 6b8b2e1d319c00888124c5c48b8499f9
  Compiled from "TypeclassSkillTrees.scala"
public class rpg.typeclass.naive.WisStep<N extends java.lang.Object> extends java.lang.Object implements rpg.typeclass.naive.Node, scala.Product, scala.Serializable
  minor version: 0
  major version: 52
  flags: ACC_PUBLIC, ACC_SUPER
Constant pool:
    #1 = Utf8               rpg/typeclass/naive/WisStep
    #2 = Class              #1            // rpg/typeclass/naive/WisStep
    #3 = Utf8               <N:Ljava/lang/Object;>Ljava/lang/Object;Lrpg/typeclass/naive/Node;Lscala/Product;Lscala/Serializable;
    #4 = Utf8               java/lang/Object
    #5 = Class              #4            // java/lang/Object
    #6 = Utf8               rpg/typeclass/naive/Node
    #7 = Class              #6            // rpg/typeclass/naive/Node
    #8 = Utf8               scala/Product
    #9 = Class              #8            // scala/Product
   #10 = Utf8               scala/Serializable
   #11 = Class              #10           // scala/Serializable
   #12 = Utf8               TypeclassSkillTrees.scala
   #13 = Utf8               Lscala/reflect/ScalaSignature;
   #14 = Utf8               bytes
   #15 = Utf8               MbB&qaV5t'R,O\t)a.Y5wK*QAB\nifXm7bgNTaBeB<7ARA+a\"D5QADgG.Y!5a!8z%4C\nBquZ311BA&o3vGR\"D\r\nii!D*fe&G.>bE2,+IAQ|W#}CC\rA\tF1E\n\tJ!!J9{G[5oOBAbJQ51!8z!QA!E!qa;pA!)AC[1A(8jiz\"\"ALIaCWaC2I\t\r|/_gY\"\"NIQ m)\rbE!9A\rI)bB#%\tAOG>\n3fM,H2+\tYd)F=U\tqRhK?!\tyD)DA\t\t%)Av]DWmY6fI*1)DC:tw^1uS>tBA#AE)hn5fG.,GMV1sSt7-Ca\rA\t\t\t\"J5(o3vGR&/4jqV\t!\nL!6\tAJN!A.8hy6bmL!!'\rM#(/8h!!AQA:pIVG/:jif,!\tYK!aV%sGCZI.AxZ;dicW-\3oiRae9b\t1V\rAH%\r=\t\t\"`=(o3vGRLE/:bi>X#1$g%Dc\tW\"d_2dWm;j_:L!!2%#XM]1u_JDqa.dC:,/^1m)\tIG\rU&1.>|G.Z1oaf-!AABqAs.iCND7i3f))bB9%\tE]\ti>FO]5oOR\t!\nCuII;\rX/7t)\tIgC]g\ta!Es9q+[:TiC\n{\r\t!!!A\tm2A_a#\"~)IbB9{%)E\nQ!CA\tQ!9qYf,B!!Q!qAA!!!}\tYB\"\n!\n#Q!CA'\tq!8baBd0}ABACRDA\r;I1!ay^5p]Bq$a\r\nyA1#)\t#aQEq\n;A\"!{%I!aI,\r*fg>dg/[2aSA\r\t\t\nTWm;
   #16 = Utf8               to
   #17 = Utf8               Ljava/lang/Object;
   #18 = Utf8               TN;
   #19 = Utf8               unapply
   #20 = Utf8               (Lrpg/typeclass/naive/WisStep;)Lscala/Option;
   #21 = Utf8               rpg/typeclass/naive/WisStep$
   #22 = Class              #21           // rpg/typeclass/naive/WisStep$
   #23 = Utf8               MODULE$
   #24 = Utf8               Lrpg/typeclass/naive/WisStep$;
   #25 = NameAndType        #23:#24       // MODULE$:Lrpg/typeclass/naive/WisStep$;
   #26 = Fieldref           #22.#25       // rpg/typeclass/naive/WisStep$.MODULE$:Lrpg/typeclass/naive/WisStep$;
   #27 = NameAndType        #19:#20       // unapply:(Lrpg/typeclass/naive/WisStep;)Lscala/Option;
   #28 = Methodref          #22.#27       // rpg/typeclass/naive/WisStep$.unapply:(Lrpg/typeclass/naive/WisStep;)Lscala/Option;
   #29 = Utf8               apply
   #30 = Utf8               (Ljava/lang/Object;)Lrpg/typeclass/naive/WisStep;
   #31 = NameAndType        #29:#30       // apply:(Ljava/lang/Object;)Lrpg/typeclass/naive/WisStep;
   #32 = Methodref          #22.#31       // rpg/typeclass/naive/WisStep$.apply:(Ljava/lang/Object;)Lrpg/typeclass/naive/WisStep;
   #33 = Utf8               ()Ljava/lang/Object;
   #34 = NameAndType        #16:#17       // to:Ljava/lang/Object;
   #35 = Fieldref           #2.#34        // rpg/typeclass/naive/WisStep.to:Ljava/lang/Object;
   #36 = Utf8               this
   #37 = Utf8               Lrpg/typeclass/naive/WisStep;
   #38 = Utf8               copy
   #39 = Utf8               <init>
   #40 = Utf8               (Ljava/lang/Object;)V
   #41 = NameAndType        #39:#40       // "<init>":(Ljava/lang/Object;)V
   #42 = Methodref          #2.#41        // rpg/typeclass/naive/WisStep."<init>":(Ljava/lang/Object;)V
   #43 = Utf8               copy$default$1
   #44 = NameAndType        #16:#33       // to:()Ljava/lang/Object;
   #45 = Methodref          #2.#44        // rpg/typeclass/naive/WisStep.to:()Ljava/lang/Object;
   #46 = Utf8               productPrefix
   #47 = Utf8               ()Ljava/lang/String;
   #48 = Utf8               WisStep
   #49 = String             #48           // WisStep
   #50 = Utf8               productArity
   #51 = Utf8               ()I
   #52 = Utf8               productElement
   #53 = Utf8               (I)Ljava/lang/Object;
   #54 = Utf8               x$1
   #55 = Utf8               java/lang/IndexOutOfBoundsException
   #56 = Class              #55           // java/lang/IndexOutOfBoundsException
   #57 = Utf8               scala/runtime/BoxesRunTime
   #58 = Class              #57           // scala/runtime/BoxesRunTime
   #59 = Utf8               boxToInteger
   #60 = Utf8               (I)Ljava/lang/Integer;
   #61 = NameAndType        #59:#60       // boxToInteger:(I)Ljava/lang/Integer;
   #62 = Methodref          #58.#61       // scala/runtime/BoxesRunTime.boxToInteger:(I)Ljava/lang/Integer;
   #63 = Utf8               toString
   #64 = NameAndType        #63:#47       // toString:()Ljava/lang/String;
   #65 = Methodref          #5.#64        // java/lang/Object.toString:()Ljava/lang/String;
   #66 = Utf8               (Ljava/lang/String;)V
   #67 = NameAndType        #39:#66       // "<init>":(Ljava/lang/String;)V
   #68 = Methodref          #56.#67       // java/lang/IndexOutOfBoundsException."<init>":(Ljava/lang/String;)V
   #69 = Utf8               I
   #70 = Utf8               productIterator
   #71 = Utf8               ()Lscala/collection/Iterator;
   #72 = Utf8               scala/runtime/ScalaRunTime$
   #73 = Class              #72           // scala/runtime/ScalaRunTime$
   #74 = Utf8               Lscala/runtime/ScalaRunTime$;
   #75 = NameAndType        #23:#74       // MODULE$:Lscala/runtime/ScalaRunTime$;
   #76 = Fieldref           #73.#75       // scala/runtime/ScalaRunTime$.MODULE$:Lscala/runtime/ScalaRunTime$;
   #77 = Utf8               typedProductIterator
   #78 = Utf8               (Lscala/Product;)Lscala/collection/Iterator;
   #79 = NameAndType        #77:#78       // typedProductIterator:(Lscala/Product;)Lscala/collection/Iterator;
   #80 = Methodref          #73.#79       // scala/runtime/ScalaRunTime$.typedProductIterator:(Lscala/Product;)Lscala/collection/Iterator;
   #81 = Utf8               canEqual
   #82 = Utf8               (Ljava/lang/Object;)Z
   #83 = Utf8               hashCode
   #84 = Utf8               _hashCode
   #85 = Utf8               (Lscala/Product;)I
   #86 = NameAndType        #84:#85       // _hashCode:(Lscala/Product;)I
   #87 = Methodref          #73.#86       // scala/runtime/ScalaRunTime$._hashCode:(Lscala/Product;)I
   #88 = Utf8               _toString
   #89 = Utf8               (Lscala/Product;)Ljava/lang/String;
   #90 = NameAndType        #88:#89       // _toString:(Lscala/Product;)Ljava/lang/String;
   #91 = Methodref          #73.#90       // scala/runtime/ScalaRunTime$._toString:(Lscala/Product;)Ljava/lang/String;
   #92 = Utf8               equals
   #93 = Utf8               (Ljava/lang/Object;Ljava/lang/Object;)Z
   #94 = NameAndType        #92:#93       // equals:(Ljava/lang/Object;Ljava/lang/Object;)Z
   #95 = Methodref          #58.#94       // scala/runtime/BoxesRunTime.equals:(Ljava/lang/Object;Ljava/lang/Object;)Z
   #96 = NameAndType        #81:#82       // canEqual:(Ljava/lang/Object;)Z
   #97 = Methodref          #2.#96        // rpg/typeclass/naive/WisStep.canEqual:(Ljava/lang/Object;)Z
   #98 = Utf8               ()V
   #99 = NameAndType        #39:#98       // "<init>":()V
  #100 = Methodref          #5.#99        // java/lang/Object."<init>":()V
  #101 = Utf8               $init$
  #102 = Utf8               (Lscala/Product;)V
  #103 = NameAndType        #101:#102     // $init$:(Lscala/Product;)V
  #104 = InterfaceMethodref #9.#103       // scala/Product.$init$:(Lscala/Product;)V
  #105 = Utf8               Signature
  #106 = Utf8               Code
  #107 = Utf8               <N:Ljava/lang/Object;>(Lrpg/typeclass/naive/WisStep<TN;>;)Lscala/Option<TN;>;
  #108 = Utf8               <N:Ljava/lang/Object;>(TN;)Lrpg/typeclass/naive/WisStep<TN;>;
  #109 = Utf8               LocalVariableTable
  #110 = Utf8               LineNumberTable
  #111 = Utf8               ()TN;
  #112 = Utf8               MethodParameters
  #113 = Utf8               <N:Ljava/lang/Object;>()TN;
  #114 = Utf8               StackMapTable
  #115 = Utf8               ()Lscala/collection/Iterator<Ljava/lang/Object;>;
  #116 = Utf8               (TN;)V
  #117 = Utf8               SourceFile
  #118 = Utf8               RuntimeVisibleAnnotations
  #119 = Utf8               ScalaInlineInfo
  #120 = Utf8               ScalaSig
{
  private final N to;
    descriptor: Ljava/lang/Object;
    flags: ACC_PRIVATE, ACC_FINAL
    Signature: #18                          // TN;

  public static <N extends java.lang.Object> scala.Option<N> unapply(rpg.typeclass.naive.WisStep<N>);
    descriptor: (Lrpg/typeclass/naive/WisStep;)Lscala/Option;
    flags: ACC_PUBLIC, ACC_STATIC
    Code:
      stack=2, locals=1, args_size=1
         0: getstatic     #26                 // Field rpg/typeclass/naive/WisStep$.MODULE$:Lrpg/typeclass/naive/WisStep$;
         3: aload_0
         4: invokevirtual #28                 // Method rpg/typeclass/naive/WisStep$.unapply:(Lrpg/typeclass/naive/WisStep;)Lscala/Option;
         7: areturn
    Signature: #107                         // <N:Ljava/lang/Object;>(Lrpg/typeclass/naive/WisStep<TN;>;)Lscala/Option<TN;>;

  public static <N extends java.lang.Object> rpg.typeclass.naive.WisStep<N> apply(N);
    descriptor: (Ljava/lang/Object;)Lrpg/typeclass/naive/WisStep;
    flags: ACC_PUBLIC, ACC_STATIC
    Code:
      stack=2, locals=1, args_size=1
         0: getstatic     #26                 // Field rpg/typeclass/naive/WisStep$.MODULE$:Lrpg/typeclass/naive/WisStep$;
         3: aload_0
         4: invokevirtual #32                 // Method rpg/typeclass/naive/WisStep$.apply:(Ljava/lang/Object;)Lrpg/typeclass/naive/WisStep;
         7: areturn
    Signature: #108                         // <N:Ljava/lang/Object;>(TN;)Lrpg/typeclass/naive/WisStep<TN;>;

  public N to();
    descriptor: ()Ljava/lang/Object;
    flags: ACC_PUBLIC
    Code:
      stack=1, locals=1, args_size=1
         0: aload_0
         1: getfield      #35                 // Field to:Ljava/lang/Object;
         4: areturn
      LocalVariableTable:
        Start  Length  Slot  Name   Signature
            0       5     0  this   Lrpg/typeclass/naive/WisStep;
      LineNumberTable:
        line 19: 0
    Signature: #111                         // ()TN;

  public <N extends java.lang.Object> rpg.typeclass.naive.WisStep<N> copy(N);
    descriptor: (Ljava/lang/Object;)Lrpg/typeclass/naive/WisStep;
    flags: ACC_PUBLIC
    Code:
      stack=3, locals=2, args_size=2
         0: new           #2                  // class rpg/typeclass/naive/WisStep
         3: dup
         4: aload_1
         5: invokespecial #42                 // Method "<init>":(Ljava/lang/Object;)V
         8: areturn
      LocalVariableTable:
        Start  Length  Slot  Name   Signature
            0       9     0  this   Lrpg/typeclass/naive/WisStep;
            0       9     1    to   Ljava/lang/Object;
      LineNumberTable:
        line 19: 0
    Signature: #108                         // <N:Ljava/lang/Object;>(TN;)Lrpg/typeclass/naive/WisStep<TN;>;
    MethodParameters:
      Name                           Flags
      to                             final

  public <N extends java.lang.Object> N copy$default$1();
    descriptor: ()Ljava/lang/Object;
    flags: ACC_PUBLIC
    Code:
      stack=1, locals=1, args_size=1
         0: aload_0
         1: invokevirtual #45                 // Method to:()Ljava/lang/Object;
         4: areturn
      LocalVariableTable:
        Start  Length  Slot  Name   Signature
            0       5     0  this   Lrpg/typeclass/naive/WisStep;
      LineNumberTable:
        line 19: 0
    Signature: #113                         // <N:Ljava/lang/Object;>()TN;

  public java.lang.String productPrefix();
    descriptor: ()Ljava/lang/String;
    flags: ACC_PUBLIC
    Code:
      stack=1, locals=1, args_size=1
         0: ldc           #49                 // String WisStep
         2: areturn
      LocalVariableTable:
        Start  Length  Slot  Name   Signature
            0       3     0  this   Lrpg/typeclass/naive/WisStep;
      LineNumberTable:
        line 19: 0

  public int productArity();
    descriptor: ()I
    flags: ACC_PUBLIC
    Code:
      stack=1, locals=1, args_size=1
         0: iconst_1
         1: ireturn
      LocalVariableTable:
        Start  Length  Slot  Name   Signature
            0       2     0  this   Lrpg/typeclass/naive/WisStep;
      LineNumberTable:
        line 19: 0

  public java.lang.Object productElement(int);
    descriptor: (I)Ljava/lang/Object;
    flags: ACC_PUBLIC
    Code:
      stack=3, locals=3, args_size=2
         0: iload_1
         1: istore_2
         2: iload_2
         3: tableswitch   { // 0 to 0
                       0: 20
                 default: 27
            }
        20: aload_0
        21: invokevirtual #45                 // Method to:()Ljava/lang/Object;
        24: goto          42
        27: new           #56                 // class java/lang/IndexOutOfBoundsException
        30: dup
        31: iload_1
        32: invokestatic  #62                 // Method scala/runtime/BoxesRunTime.boxToInteger:(I)Ljava/lang/Integer;
        35: invokevirtual #65                 // Method java/lang/Object.toString:()Ljava/lang/String;
        38: invokespecial #68                 // Method java/lang/IndexOutOfBoundsException."<init>":(Ljava/lang/String;)V
        41: athrow
        42: areturn
      LocalVariableTable:
        Start  Length  Slot  Name   Signature
            0      43     0  this   Lrpg/typeclass/naive/WisStep;
            0      43     1   x$1   I
      LineNumberTable:
        line 19: 0
      StackMapTable: number_of_entries = 3
        frame_type = 252 /* append */
          offset_delta = 20
          locals = [ int ]
        frame_type = 6 /* same */
        frame_type = 78 /* same_locals_1_stack_item */
          stack = [ class java/lang/Object ]
    MethodParameters:
      Name                           Flags
      x$1                            final

  public scala.collection.Iterator<java.lang.Object> productIterator();
    descriptor: ()Lscala/collection/Iterator;
    flags: ACC_PUBLIC
    Code:
      stack=2, locals=1, args_size=1
         0: getstatic     #76                 // Field scala/runtime/ScalaRunTime$.MODULE$:Lscala/runtime/ScalaRunTime$;
         3: aload_0
         4: invokevirtual #80                 // Method scala/runtime/ScalaRunTime$.typedProductIterator:(Lscala/Product;)Lscala/collection/Iterator;
         7: areturn
      LocalVariableTable:
        Start  Length  Slot  Name   Signature
            0       8     0  this   Lrpg/typeclass/naive/WisStep;
      LineNumberTable:
        line 19: 0
    Signature: #115                         // ()Lscala/collection/Iterator<Ljava/lang/Object;>;

  public boolean canEqual(java.lang.Object);
    descriptor: (Ljava/lang/Object;)Z
    flags: ACC_PUBLIC
    Code:
      stack=1, locals=2, args_size=2
         0: aload_1
         1: instanceof    #2                  // class rpg/typeclass/naive/WisStep
         4: ireturn
      LocalVariableTable:
        Start  Length  Slot  Name   Signature
            0       5     0  this   Lrpg/typeclass/naive/WisStep;
            0       5     1   x$1   Ljava/lang/Object;
      LineNumberTable:
        line 19: 0
    MethodParameters:
      Name                           Flags
      x$1                            final

  public int hashCode();
    descriptor: ()I
    flags: ACC_PUBLIC
    Code:
      stack=2, locals=1, args_size=1
         0: getstatic     #76                 // Field scala/runtime/ScalaRunTime$.MODULE$:Lscala/runtime/ScalaRunTime$;
         3: aload_0
         4: invokevirtual #87                 // Method scala/runtime/ScalaRunTime$._hashCode:(Lscala/Product;)I
         7: ireturn
      LocalVariableTable:
        Start  Length  Slot  Name   Signature
            0       8     0  this   Lrpg/typeclass/naive/WisStep;
      LineNumberTable:
        line 19: 0

  public java.lang.String toString();
    descriptor: ()Ljava/lang/String;
    flags: ACC_PUBLIC
    Code:
      stack=2, locals=1, args_size=1
         0: getstatic     #76                 // Field scala/runtime/ScalaRunTime$.MODULE$:Lscala/runtime/ScalaRunTime$;
         3: aload_0
         4: invokevirtual #91                 // Method scala/runtime/ScalaRunTime$._toString:(Lscala/Product;)Ljava/lang/String;
         7: areturn
      LocalVariableTable:
        Start  Length  Slot  Name   Signature
            0       8     0  this   Lrpg/typeclass/naive/WisStep;
      LineNumberTable:
        line 19: 0

  public boolean equals(java.lang.Object);
    descriptor: (Ljava/lang/Object;)Z
    flags: ACC_PUBLIC
    Code:
      stack=2, locals=5, args_size=2
         0: aload_0
         1: aload_1
         2: if_acmpeq     69
         5: aload_1
         6: astore_3
         7: aload_3
         8: instanceof    #2                  // class rpg/typeclass/naive/WisStep
        11: ifeq          19
        14: iconst_1
        15: istore_2
        16: goto          27
        19: goto          22
        22: iconst_0
        23: istore_2
        24: goto          27
        27: iload_2
        28: ifeq          73
        31: aload_1
        32: checkcast     #2                  // class rpg/typeclass/naive/WisStep
        35: astore        4
        37: aload_0
        38: invokevirtual #45                 // Method to:()Ljava/lang/Object;
        41: aload         4
        43: invokevirtual #45                 // Method to:()Ljava/lang/Object;
        46: invokestatic  #95                 // Method scala/runtime/BoxesRunTime.equals:(Ljava/lang/Object;Ljava/lang/Object;)Z
        49: ifeq          65
        52: aload         4
        54: aload_0
        55: invokevirtual #97                 // Method canEqual:(Ljava/lang/Object;)Z
        58: ifeq          65
        61: iconst_1
        62: goto          66
        65: iconst_0
        66: ifeq          73
        69: iconst_1
        70: goto          74
        73: iconst_0
        74: ireturn
      LocalVariableTable:
        Start  Length  Slot  Name   Signature
            0      75     0  this   Lrpg/typeclass/naive/WisStep;
            0      75     1   x$1   Ljava/lang/Object;
      LineNumberTable:
        line 19: 0
      StackMapTable: number_of_entries = 8
        frame_type = 253 /* append */
          offset_delta = 19
          locals = [ top, class java/lang/Object ]
        frame_type = 2 /* same */
        frame_type = 255 /* full_frame */
          offset_delta = 4
          locals = [ class rpg/typeclass/naive/WisStep, class java/lang/Object, int, class java/lang/Object ]
          stack = []
        frame_type = 252 /* append */
          offset_delta = 37
          locals = [ class rpg/typeclass/naive/WisStep ]
        frame_type = 64 /* same_locals_1_stack_item */
          stack = [ int ]
        frame_type = 248 /* chop */
          offset_delta = 2
        frame_type = 253 /* append */
          offset_delta = 3
          locals = [ int, class java/lang/Object ]
        frame_type = 255 /* full_frame */
          offset_delta = 0
          locals = [ class rpg/typeclass/naive/WisStep, class java/lang/Object ]
          stack = [ int ]
    MethodParameters:
      Name                           Flags
      x$1                            final

  public rpg.typeclass.naive.WisStep(N);
    descriptor: (Ljava/lang/Object;)V
    flags: ACC_PUBLIC
    Code:
      stack=2, locals=2, args_size=2
         0: aload_0
         1: aload_1
         2: putfield      #35                 // Field to:Ljava/lang/Object;
         5: aload_0
         6: invokespecial #100                // Method java/lang/Object."<init>":()V
         9: aload_0
        10: invokestatic  #104                // InterfaceMethod scala/Product.$init$:(Lscala/Product;)V
        13: return
      LocalVariableTable:
        Start  Length  Slot  Name   Signature
            0      14     0  this   Lrpg/typeclass/naive/WisStep;
            0      14     1    to   Ljava/lang/Object;
      LineNumberTable:
        line 19: 0
    Signature: #116                         // (TN;)V
    MethodParameters:
      Name                           Flags
      to                             final
}
Signature: #3                           // <N:Ljava/lang/Object;>Ljava/lang/Object;Lrpg/typeclass/naive/Node;Lscala/Product;Lscala/Serializable;
SourceFile: "TypeclassSkillTrees.scala"
RuntimeVisibleAnnotations:
  0: #13(#14=s#15)
Error: unknown attribute
  ScalaInlineInfo: length = 0x40
   01 00 00 0C 00 27 00 28 00 00 51 00 52 00 00 2B
   00 21 00 00 26 00 1E 00 00 5C 00 52 00 00 53 00
   33 00 00 32 00 33 00 00 34 00 35 00 00 46 00 47
   00 00 2E 00 2F 00 00 10 00 21 00 00 3F 00 2F 00

Error: unknown attribute
  ScalaSig: length = 0x3
   05 00 00
