Classfile /home/krzysiek/workspace/scala-bcode-cutter/pref/target/scala-2.12/classes/rpg/cake/CakeSkillTrees.class
  Last modified Apr 8, 2018; size 2208 bytes
  MD5 checksum 78085d3bfacde8f816a8f9fcb1634924
  Compiled from "CakeSkillTrees.scala"
public class rpg.cake.CakeSkillTrees extends rpg.SkillTrees
  minor version: 0
  major version: 52
  flags: ACC_PUBLIC, ACC_SUPER
Constant pool:
    #1 = Utf8               rpg/cake/CakeSkillTrees
    #2 = Class              #1            // rpg/cake/CakeSkillTrees
    #3 = Utf8               rpg/SkillTrees
    #4 = Class              #3            // rpg/SkillTrees
    #5 = Utf8               CakeSkillTrees.scala
    #6 = Utf8               Lscala/reflect/ScalaSignature;
    #7 = Utf8               bytes
    #8 = Utf8               -2A!\tq1)Y6f'.LG+sK(BAm[3\t1A9h\"%QQ\"\n-!!AC*lS2dGK]3fg\")QC1A(8jiz\"a\t!iA%!\teECJ.:z)J,W\rMAQC\tYABA56.7m)J,WMU3qeBD\t%Y#!AADA`IE\n\"!Hy\tS\"A\nQa]2bYL!AI9{G[5oOBaJK}1!8z91)!(/Y5ugB\"KUA7bsHK]1jiN
    #9 = Utf8               rpg/cake/CakeSkillTrees$$anon$1
   #10 = Class              #9            // rpg/cake/CakeSkillTrees$$anon$1
   #11 = Utf8               rpg/cake/DexNodes$DexSkill
   #12 = Class              #11           // rpg/cake/DexNodes$DexSkill
   #13 = Utf8               rpg/cake/DexNodes
   #14 = Class              #13           // rpg/cake/DexNodes
   #15 = Utf8               DexSkill
   #16 = Utf8               rpg/cake/DexNodes$DexStep
   #17 = Class              #16           // rpg/cake/DexNodes$DexStep
   #18 = Utf8               DexStep
   #19 = Utf8               rpg/cake/DexNodes$DexTree
   #20 = Class              #19           // rpg/cake/DexNodes$DexTree
   #21 = Utf8               DexTree
   #22 = Utf8               rpg/cake/Nodes$Node
   #23 = Class              #22           // rpg/cake/Nodes$Node
   #24 = Utf8               rpg/cake/Nodes
   #25 = Class              #24           // rpg/cake/Nodes
   #26 = Utf8               Node
   #27 = Utf8               rpg/cake/StrNodes$StrSkill
   #28 = Class              #27           // rpg/cake/StrNodes$StrSkill
   #29 = Utf8               rpg/cake/StrNodes
   #30 = Class              #29           // rpg/cake/StrNodes
   #31 = Utf8               StrSkill
   #32 = Utf8               rpg/cake/StrNodes$StrStep
   #33 = Class              #32           // rpg/cake/StrNodes$StrStep
   #34 = Utf8               StrStep
   #35 = Utf8               rpg/cake/StrNodes$StrTree
   #36 = Class              #35           // rpg/cake/StrNodes$StrTree
   #37 = Utf8               StrTree
   #38 = Utf8               rpg/cake/WisNodes$WisSkill
   #39 = Class              #38           // rpg/cake/WisNodes$WisSkill
   #40 = Utf8               rpg/cake/WisNodes
   #41 = Class              #40           // rpg/cake/WisNodes
   #42 = Utf8               WisSkill
   #43 = Utf8               rpg/cake/WisNodes$WisStep
   #44 = Class              #43           // rpg/cake/WisNodes$WisStep
   #45 = Utf8               WisStep
   #46 = Utf8               rpg/cake/WisNodes$WisTree
   #47 = Class              #46           // rpg/cake/WisNodes$WisTree
   #48 = Utf8               WisTree
   #49 = Utf8               archeryTree
   #50 = Utf8               (Lrpg/PlayerTraits;)Lrpg/SkillTreeRepr;
   #51 = Utf8               traits
   #52 = Utf8               rpg/cake/Nodes$
   #53 = Class              #52           // rpg/cake/Nodes$
   #54 = Utf8               MODULE$
   #55 = Utf8               Lrpg/cake/Nodes$;
   #56 = NameAndType        #54:#55       // MODULE$:Lrpg/cake/Nodes$;
   #57 = Fieldref           #53.#56       // rpg/cake/Nodes$.MODULE$:Lrpg/cake/Nodes$;
   #58 = Utf8               aimed
   #59 = String             #58           // aimed
   #60 = Utf8               <init>
   #61 = Utf8               (Lrpg/cake/Nodes;Ljava/lang/String;)V
   #62 = NameAndType        #60:#61       // "<init>":(Lrpg/cake/Nodes;Ljava/lang/String;)V
   #63 = Methodref          #39.#62       // rpg/cake/WisNodes$WisSkill."<init>":(Lrpg/cake/Nodes;Ljava/lang/String;)V
   #64 = Utf8               rapid
   #65 = String             #64           // rapid
   #66 = Methodref          #12.#62       // rpg/cake/DexNodes$DexSkill."<init>":(Lrpg/cake/Nodes;Ljava/lang/String;)V
   #67 = Utf8               (Lrpg/cake/Nodes;Lrpg/cake/Nodes$Node;)V
   #68 = NameAndType        #60:#67       // "<init>":(Lrpg/cake/Nodes;Lrpg/cake/Nodes$Node;)V
   #69 = Methodref          #44.#68       // rpg/cake/WisNodes$WisStep."<init>":(Lrpg/cake/Nodes;Lrpg/cake/Nodes$Node;)V
   #70 = Utf8               (Lrpg/cake/Nodes;Lrpg/cake/Nodes$Node;Lrpg/cake/Nodes$Node;)V
   #71 = NameAndType        #60:#70       // "<init>":(Lrpg/cake/Nodes;Lrpg/cake/Nodes$Node;Lrpg/cake/Nodes$Node;)V
   #72 = Methodref          #47.#71       // rpg/cake/WisNodes$WisTree."<init>":(Lrpg/cake/Nodes;Lrpg/cake/Nodes$Node;Lrpg/cake/Nodes$Node;)V
   #73 = Methodref          #17.#68       // rpg/cake/DexNodes$DexStep."<init>":(Lrpg/cake/Nodes;Lrpg/cake/Nodes$Node;)V
   #74 = Utf8               power
   #75 = String             #74           // power
   #76 = Methodref          #28.#62       // rpg/cake/StrNodes$StrSkill."<init>":(Lrpg/cake/Nodes;Ljava/lang/String;)V
   #77 = Utf8               double
   #78 = String             #77           // double
   #79 = Methodref          #33.#68       // rpg/cake/StrNodes$StrStep."<init>":(Lrpg/cake/Nodes;Lrpg/cake/Nodes$Node;)V
   #80 = Methodref          #36.#71       // rpg/cake/StrNodes$StrTree."<init>":(Lrpg/cake/Nodes;Lrpg/cake/Nodes$Node;Lrpg/cake/Nodes$Node;)V
   #81 = Methodref          #20.#71       // rpg/cake/DexNodes$DexTree."<init>":(Lrpg/cake/Nodes;Lrpg/cake/Nodes$Node;Lrpg/cake/Nodes$Node;)V
   #82 = Utf8               (Lrpg/cake/CakeSkillTrees;Lrpg/PlayerTraits;Lrpg/cake/DexNodes$DexTree;)V
   #83 = NameAndType        #60:#82       // "<init>":(Lrpg/cake/CakeSkillTrees;Lrpg/PlayerTraits;Lrpg/cake/DexNodes$DexTree;)V
   #84 = Methodref          #10.#83       // rpg/cake/CakeSkillTrees$$anon$1."<init>":(Lrpg/cake/CakeSkillTrees;Lrpg/PlayerTraits;Lrpg/cake/DexNodes$DexTree;)V
   #85 = Utf8               tree
   #86 = Utf8               Lrpg/cake/DexNodes$DexTree;
   #87 = Utf8               this
   #88 = Utf8               Lrpg/cake/CakeSkillTrees;
   #89 = Utf8               Lrpg/PlayerTraits;
   #90 = Utf8               ()V
   #91 = NameAndType        #60:#90       // "<init>":()V
   #92 = Methodref          #4.#91        // rpg/SkillTrees."<init>":()V
   #93 = Utf8               Code
   #94 = Utf8               LocalVariableTable
   #95 = Utf8               LineNumberTable
   #96 = Utf8               Signature
   #97 = Utf8               (Lrpg/PlayerTraits;)Lrpg/SkillTreeRepr<*>;
   #98 = Utf8               MethodParameters
   #99 = Utf8               SourceFile
  #100 = Utf8               InnerClasses
  #101 = Utf8               RuntimeVisibleAnnotations
  #102 = Utf8               ScalaInlineInfo
  #103 = Utf8               ScalaSig
{
  public rpg.SkillTreeRepr<?> archeryTree(rpg.PlayerTraits);
    descriptor: (Lrpg/PlayerTraits;)Lrpg/SkillTreeRepr;
    flags: ACC_PUBLIC
    Code:
      stack=17, locals=3, args_size=2
         0: new           #20                 // class rpg/cake/DexNodes$DexTree
         3: dup
         4: getstatic     #57                 // Field rpg/cake/Nodes$.MODULE$:Lrpg/cake/Nodes$;
         7: new           #17                 // class rpg/cake/DexNodes$DexStep
        10: dup
        11: getstatic     #57                 // Field rpg/cake/Nodes$.MODULE$:Lrpg/cake/Nodes$;
        14: new           #47                 // class rpg/cake/WisNodes$WisTree
        17: dup
        18: getstatic     #57                 // Field rpg/cake/Nodes$.MODULE$:Lrpg/cake/Nodes$;
        21: new           #39                 // class rpg/cake/WisNodes$WisSkill
        24: dup
        25: getstatic     #57                 // Field rpg/cake/Nodes$.MODULE$:Lrpg/cake/Nodes$;
        28: ldc           #59                 // String aimed
        30: invokespecial #63                 // Method rpg/cake/WisNodes$WisSkill."<init>":(Lrpg/cake/Nodes;Ljava/lang/String;)V
        33: new           #44                 // class rpg/cake/WisNodes$WisStep
        36: dup
        37: getstatic     #57                 // Field rpg/cake/Nodes$.MODULE$:Lrpg/cake/Nodes$;
        40: new           #12                 // class rpg/cake/DexNodes$DexSkill
        43: dup
        44: getstatic     #57                 // Field rpg/cake/Nodes$.MODULE$:Lrpg/cake/Nodes$;
        47: ldc           #65                 // String rapid
        49: invokespecial #66                 // Method rpg/cake/DexNodes$DexSkill."<init>":(Lrpg/cake/Nodes;Ljava/lang/String;)V
        52: invokespecial #69                 // Method rpg/cake/WisNodes$WisStep."<init>":(Lrpg/cake/Nodes;Lrpg/cake/Nodes$Node;)V
        55: invokespecial #72                 // Method rpg/cake/WisNodes$WisTree."<init>":(Lrpg/cake/Nodes;Lrpg/cake/Nodes$Node;Lrpg/cake/Nodes$Node;)V
        58: invokespecial #73                 // Method rpg/cake/DexNodes$DexStep."<init>":(Lrpg/cake/Nodes;Lrpg/cake/Nodes$Node;)V
        61: new           #36                 // class rpg/cake/StrNodes$StrTree
        64: dup
        65: getstatic     #57                 // Field rpg/cake/Nodes$.MODULE$:Lrpg/cake/Nodes$;
        68: new           #28                 // class rpg/cake/StrNodes$StrSkill
        71: dup
        72: getstatic     #57                 // Field rpg/cake/Nodes$.MODULE$:Lrpg/cake/Nodes$;
        75: ldc           #75                 // String power
        77: invokespecial #76                 // Method rpg/cake/StrNodes$StrSkill."<init>":(Lrpg/cake/Nodes;Ljava/lang/String;)V
        80: new           #33                 // class rpg/cake/StrNodes$StrStep
        83: dup
        84: getstatic     #57                 // Field rpg/cake/Nodes$.MODULE$:Lrpg/cake/Nodes$;
        87: new           #12                 // class rpg/cake/DexNodes$DexSkill
        90: dup
        91: getstatic     #57                 // Field rpg/cake/Nodes$.MODULE$:Lrpg/cake/Nodes$;
        94: ldc           #78                 // String double
        96: invokespecial #66                 // Method rpg/cake/DexNodes$DexSkill."<init>":(Lrpg/cake/Nodes;Ljava/lang/String;)V
        99: invokespecial #79                 // Method rpg/cake/StrNodes$StrStep."<init>":(Lrpg/cake/Nodes;Lrpg/cake/Nodes$Node;)V
       102: invokespecial #80                 // Method rpg/cake/StrNodes$StrTree."<init>":(Lrpg/cake/Nodes;Lrpg/cake/Nodes$Node;Lrpg/cake/Nodes$Node;)V
       105: invokespecial #81                 // Method rpg/cake/DexNodes$DexTree."<init>":(Lrpg/cake/Nodes;Lrpg/cake/Nodes$Node;Lrpg/cake/Nodes$Node;)V
       108: astore_2
       109: new           #10                 // class rpg/cake/CakeSkillTrees$$anon$1
       112: dup
       113: aconst_null
       114: aload_1
       115: aload_2
       116: invokespecial #84                 // Method rpg/cake/CakeSkillTrees$$anon$1."<init>":(Lrpg/cake/CakeSkillTrees;Lrpg/PlayerTraits;Lrpg/cake/DexNodes$DexTree;)V
       119: areturn
      LocalVariableTable:
        Start  Length  Slot  Name   Signature
          108      11     2  tree   Lrpg/cake/DexNodes$DexTree;
            0     120     0  this   Lrpg/cake/CakeSkillTrees;
            0     120     1 traits   Lrpg/PlayerTraits;
      LineNumberTable:
        line 66: 0
        line 67: 7
        line 68: 21
        line 69: 33
        line 71: 61
        line 72: 68
        line 73: 80
        line 76: 109
    Signature: #97                          // (Lrpg/PlayerTraits;)Lrpg/SkillTreeRepr<*>;
    MethodParameters:
      Name                           Flags
      traits                         final

  public rpg.cake.CakeSkillTrees();
    descriptor: ()V
    flags: ACC_PUBLIC
    Code:
      stack=1, locals=1, args_size=1
         0: aload_0
         1: invokespecial #92                 // Method rpg/SkillTrees."<init>":()V
         4: return
      LocalVariableTable:
        Start  Length  Slot  Name   Signature
            0       5     0  this   Lrpg/cake/CakeSkillTrees;
      LineNumberTable:
        line 54: 0
}
SourceFile: "CakeSkillTrees.scala"
InnerClasses:
     public final #10; //class rpg/cake/CakeSkillTrees$$anon$1
     public #15= #12 of #14; //DexSkill=class rpg/cake/DexNodes$DexSkill of class rpg/cake/DexNodes
     public #18= #17 of #14; //DexStep=class rpg/cake/DexNodes$DexStep of class rpg/cake/DexNodes
     public #21= #20 of #14; //DexTree=class rpg/cake/DexNodes$DexTree of class rpg/cake/DexNodes
     public #26= #23 of #25; //Node=class rpg/cake/Nodes$Node of class rpg/cake/Nodes
     public #31= #28 of #30; //StrSkill=class rpg/cake/StrNodes$StrSkill of class rpg/cake/StrNodes
     public #34= #33 of #30; //StrStep=class rpg/cake/StrNodes$StrStep of class rpg/cake/StrNodes
     public #37= #36 of #30; //StrTree=class rpg/cake/StrNodes$StrTree of class rpg/cake/StrNodes
     public #42= #39 of #41; //WisSkill=class rpg/cake/WisNodes$WisSkill of class rpg/cake/WisNodes
     public #45= #44 of #41; //WisStep=class rpg/cake/WisNodes$WisStep of class rpg/cake/WisNodes
     public #48= #47 of #41; //WisTree=class rpg/cake/WisNodes$WisTree of class rpg/cake/WisNodes
RuntimeVisibleAnnotations:
  0: #6(#7=s#8)
Error: unknown attribute
  ScalaInlineInfo: length = 0xE
   01 00 00 02 00 3C 00 5A 00 00 31 00 32 00
Error: unknown attribute
  ScalaSig: length = 0x3
   05 00 00
