Compiled from "TypeclassSkillTrees.scala"
public final class rpg.typeclass.naive.Node$$anon$3 implements rpg.typeclass.naive.Node$Summer<rpg.typeclass.naive.DexSkill> {
  public int sumExp(rpg.typeclass.naive.DexSkill, rpg.PlayerTraits);
    Code:
       0: aload_2
       1: invokevirtual #23                 // Method rpg/PlayerTraits.dexCost:()I
       4: ireturn

  public int sumExp(java.lang.Object, rpg.PlayerTraits);
    Code:
       0: aload_0
       1: aload_1
       2: checkcast     #30                 // class rpg/typeclass/naive/DexSkill
       5: aload_2
       6: invokevirtual #32                 // Method sumExp:(Lrpg/typeclass/naive/DexSkill;Lrpg/PlayerTraits;)I
       9: ireturn

  public rpg.typeclass.naive.Node$$anon$3();
    Code:
       0: aload_0
       1: invokespecial #37                 // Method java/lang/Object."<init>":()V
       4: return
}
