Classfile /home/krzysiek/workspace/scala-bcode-cutter/pref/target/scala-2.12/classes/rpg/typeclass/naive/TypeclassSkillTrees.class
  Last modified Apr 8, 2018; size 1882 bytes
  MD5 checksum b44e34425cf419817cf06c91c488e1cf
  Compiled from "TypeclassSkillTrees.scala"
public class rpg.typeclass.naive.TypeclassSkillTrees extends rpg.SkillTrees
  minor version: 0
  major version: 52
  flags: ACC_PUBLIC, ACC_SUPER
Constant pool:
   #1 = Utf8               rpg/typeclass/naive/TypeclassSkillTrees
   #2 = Class              #1             // rpg/typeclass/naive/TypeclassSkillTrees
   #3 = Utf8               rpg/SkillTrees
   #4 = Class              #3             // rpg/SkillTrees
   #5 = Utf8               TypeclassSkillTrees.scala
   #6 = Utf8               Lscala/reflect/ScalaSignature;
   #7 = Utf8               bytes
   #8 = Utf8               52A!\tB+9fG27o]*lS2dGK]3fg*1B]Lg/\t^=qKdm]:\t1A9h\"-aQ\"\n51!AC*lS2dGK]3fg\")qC!1A(8jiz\"!\t%iA)!\t%FCJ.:z)J,W\rQAq\taQBA\r56.7m)J,WMU3qeB1\t%i2#!AaDA`IE\n\"aHS\"A\t\nQa]2bYL!J9{G[5oOBEJO1!8zI31+!(/Y5ugB1bKYA7bsHK]1jiN
   #9 = Utf8               rpg/typeclass/naive/TypeclassSkillTrees$$anon$10
  #10 = Class              #9             // rpg/typeclass/naive/TypeclassSkillTrees$$anon$10
  #11 = Utf8               archeryTree
  #12 = Utf8               (Lrpg/PlayerTraits;)Lrpg/SkillTreeRepr;
  #13 = Utf8               traits
  #14 = Utf8               rpg/typeclass/naive/DexTree
  #15 = Class              #14            // rpg/typeclass/naive/DexTree
  #16 = Utf8               rpg/typeclass/naive/DexStep
  #17 = Class              #16            // rpg/typeclass/naive/DexStep
  #18 = Utf8               rpg/typeclass/naive/WisTree
  #19 = Class              #18            // rpg/typeclass/naive/WisTree
  #20 = Utf8               rpg/typeclass/naive/WisSkill
  #21 = Class              #20            // rpg/typeclass/naive/WisSkill
  #22 = Utf8               aimed
  #23 = String             #22            // aimed
  #24 = Utf8               <init>
  #25 = Utf8               (Ljava/lang/String;)V
  #26 = NameAndType        #24:#25        // "<init>":(Ljava/lang/String;)V
  #27 = Methodref          #21.#26        // rpg/typeclass/naive/WisSkill."<init>":(Ljava/lang/String;)V
  #28 = Utf8               rpg/typeclass/naive/WisStep
  #29 = Class              #28            // rpg/typeclass/naive/WisStep
  #30 = Utf8               rpg/typeclass/naive/DexSkill
  #31 = Class              #30            // rpg/typeclass/naive/DexSkill
  #32 = Utf8               rapid
  #33 = String             #32            // rapid
  #34 = Methodref          #31.#26        // rpg/typeclass/naive/DexSkill."<init>":(Ljava/lang/String;)V
  #35 = Utf8               (Ljava/lang/Object;)V
  #36 = NameAndType        #24:#35        // "<init>":(Ljava/lang/Object;)V
  #37 = Methodref          #29.#36        // rpg/typeclass/naive/WisStep."<init>":(Ljava/lang/Object;)V
  #38 = Utf8               (Ljava/lang/Object;Ljava/lang/Object;)V
  #39 = NameAndType        #24:#38        // "<init>":(Ljava/lang/Object;Ljava/lang/Object;)V
  #40 = Methodref          #19.#39        // rpg/typeclass/naive/WisTree."<init>":(Ljava/lang/Object;Ljava/lang/Object;)V
  #41 = Methodref          #17.#36        // rpg/typeclass/naive/DexStep."<init>":(Ljava/lang/Object;)V
  #42 = Utf8               rpg/typeclass/naive/StrTree
  #43 = Class              #42            // rpg/typeclass/naive/StrTree
  #44 = Utf8               rpg/typeclass/naive/StrSkill
  #45 = Class              #44            // rpg/typeclass/naive/StrSkill
  #46 = Utf8               power
  #47 = String             #46            // power
  #48 = Methodref          #45.#26        // rpg/typeclass/naive/StrSkill."<init>":(Ljava/lang/String;)V
  #49 = Utf8               rpg/typeclass/naive/StrStep
  #50 = Class              #49            // rpg/typeclass/naive/StrStep
  #51 = Utf8               double
  #52 = String             #51            // double
  #53 = Methodref          #50.#36        // rpg/typeclass/naive/StrStep."<init>":(Ljava/lang/Object;)V
  #54 = Methodref          #43.#39        // rpg/typeclass/naive/StrTree."<init>":(Ljava/lang/Object;Ljava/lang/Object;)V
  #55 = Methodref          #15.#39        // rpg/typeclass/naive/DexTree."<init>":(Ljava/lang/Object;Ljava/lang/Object;)V
  #56 = Utf8               (Lrpg/typeclass/naive/TypeclassSkillTrees;Lrpg/PlayerTraits;Lrpg/typeclass/naive/DexTree;)V
  #57 = NameAndType        #24:#56        // "<init>":(Lrpg/typeclass/naive/TypeclassSkillTrees;Lrpg/PlayerTraits;Lrpg/typeclass/naive/DexTree;)V
  #58 = Methodref          #10.#57        // rpg/typeclass/naive/TypeclassSkillTrees$$anon$10."<init>":(Lrpg/typeclass/naive/TypeclassSkillTrees;Lrpg/PlayerTraits;Lrpg/typeclass/naive/DexTree;)V
  #59 = Utf8               tree
  #60 = Utf8               Lrpg/typeclass/naive/DexTree;
  #61 = Utf8               this
  #62 = Utf8               Lrpg/typeclass/naive/TypeclassSkillTrees;
  #63 = Utf8               Lrpg/PlayerTraits;
  #64 = Utf8               ()V
  #65 = NameAndType        #24:#64        // "<init>":()V
  #66 = Methodref          #4.#65         // rpg/SkillTrees."<init>":()V
  #67 = Utf8               Code
  #68 = Utf8               LocalVariableTable
  #69 = Utf8               LineNumberTable
  #70 = Utf8               Signature
  #71 = Utf8               (Lrpg/PlayerTraits;)Lrpg/SkillTreeRepr<*>;
  #72 = Utf8               MethodParameters
  #73 = Utf8               SourceFile
  #74 = Utf8               InnerClasses
  #75 = Utf8               RuntimeVisibleAnnotations
  #76 = Utf8               ScalaInlineInfo
  #77 = Utf8               ScalaSig
{
  public rpg.SkillTreeRepr<?> archeryTree(rpg.PlayerTraits);
    descriptor: (Lrpg/PlayerTraits;)Lrpg/SkillTreeRepr;
    flags: ACC_PUBLIC
    Code:
      stack=12, locals=3, args_size=2
         0: new           #15                 // class rpg/typeclass/naive/DexTree
         3: dup
         4: new           #17                 // class rpg/typeclass/naive/DexStep
         7: dup
         8: new           #19                 // class rpg/typeclass/naive/WisTree
        11: dup
        12: new           #21                 // class rpg/typeclass/naive/WisSkill
        15: dup
        16: ldc           #23                 // String aimed
        18: invokespecial #27                 // Method rpg/typeclass/naive/WisSkill."<init>":(Ljava/lang/String;)V
        21: new           #29                 // class rpg/typeclass/naive/WisStep
        24: dup
        25: new           #31                 // class rpg/typeclass/naive/DexSkill
        28: dup
        29: ldc           #33                 // String rapid
        31: invokespecial #34                 // Method rpg/typeclass/naive/DexSkill."<init>":(Ljava/lang/String;)V
        34: invokespecial #37                 // Method rpg/typeclass/naive/WisStep."<init>":(Ljava/lang/Object;)V
        37: invokespecial #40                 // Method rpg/typeclass/naive/WisTree."<init>":(Ljava/lang/Object;Ljava/lang/Object;)V
        40: invokespecial #41                 // Method rpg/typeclass/naive/DexStep."<init>":(Ljava/lang/Object;)V
        43: new           #43                 // class rpg/typeclass/naive/StrTree
        46: dup
        47: new           #45                 // class rpg/typeclass/naive/StrSkill
        50: dup
        51: ldc           #47                 // String power
        53: invokespecial #48                 // Method rpg/typeclass/naive/StrSkill."<init>":(Ljava/lang/String;)V
        56: new           #50                 // class rpg/typeclass/naive/StrStep
        59: dup
        60: new           #31                 // class rpg/typeclass/naive/DexSkill
        63: dup
        64: ldc           #52                 // String double
        66: invokespecial #34                 // Method rpg/typeclass/naive/DexSkill."<init>":(Ljava/lang/String;)V
        69: invokespecial #53                 // Method rpg/typeclass/naive/StrStep."<init>":(Ljava/lang/Object;)V
        72: invokespecial #54                 // Method rpg/typeclass/naive/StrTree."<init>":(Ljava/lang/Object;Ljava/lang/Object;)V
        75: invokespecial #55                 // Method rpg/typeclass/naive/DexTree."<init>":(Ljava/lang/Object;Ljava/lang/Object;)V
        78: astore_2
        79: new           #10                 // class rpg/typeclass/naive/TypeclassSkillTrees$$anon$10
        82: dup
        83: aconst_null
        84: aload_1
        85: aload_2
        86: invokespecial #58                 // Method rpg/typeclass/naive/TypeclassSkillTrees$$anon$10."<init>":(Lrpg/typeclass/naive/TypeclassSkillTrees;Lrpg/PlayerTraits;Lrpg/typeclass/naive/DexTree;)V
        89: areturn
      LocalVariableTable:
        Start  Length  Slot  Name   Signature
           78      11     2  tree   Lrpg/typeclass/naive/DexTree;
            0      90     0  this   Lrpg/typeclass/naive/TypeclassSkillTrees;
            0      90     1 traits   Lrpg/PlayerTraits;
      LineNumberTable:
        line 89: 0
        line 90: 4
        line 91: 12
        line 92: 21
        line 94: 43
        line 95: 47
        line 96: 56
        line 102: 79
    Signature: #71                          // (Lrpg/PlayerTraits;)Lrpg/SkillTreeRepr<*>;
    MethodParameters:
      Name                           Flags
      traits                         final

  public rpg.typeclass.naive.TypeclassSkillTrees();
    descriptor: ()V
    flags: ACC_PUBLIC
    Code:
      stack=1, locals=1, args_size=1
         0: aload_0
         1: invokespecial #66                 // Method rpg/SkillTrees."<init>":()V
         4: return
      LocalVariableTable:
        Start  Length  Slot  Name   Signature
            0       5     0  this   Lrpg/typeclass/naive/TypeclassSkillTrees;
      LineNumberTable:
        line 81: 0
}
SourceFile: "TypeclassSkillTrees.scala"
InnerClasses:
     public final #10; //class rpg/typeclass/naive/TypeclassSkillTrees$$anon$10
RuntimeVisibleAnnotations:
  0: #6(#7=s#8)
Error: unknown attribute
  ScalaInlineInfo: length = 0xE
   01 00 00 02 00 18 00 40 00 00 0B 00 0C 00
Error: unknown attribute
  ScalaSig: length = 0x3
   05 00 00
