Compiled from "LambdasSkillTrees.scala"
public final class rpg.ooo.lambdas.LambdasSkillTrees$$anon$1 extends rpg.SkillTreeRepr<rpg.ooo.lambdas.Tree> {
  private final rpg.PlayerTraits traits$1;

  public int totalCost();
    Code:
       0: aload_0
       1: invokevirtual #19                 // Method tree:()Ljava/lang/Object;
       4: checkcast     #21                 // class rpg/ooo/lambdas/Tree
       7: aload_0
       8: getfield      #23                 // Field traits$1:Lrpg/PlayerTraits;
      11: invokevirtual #27                 // Method rpg/ooo/lambdas/Tree.cost:(Lrpg/PlayerTraits;)I
      14: ireturn

  public rpg.ooo.lambdas.LambdasSkillTrees$$anon$1(rpg.ooo.lambdas.LambdasSkillTrees, rpg.PlayerTraits, rpg.ooo.lambdas.Tree);
    Code:
       0: aload_0
       1: aload_2
       2: putfield      #23                 // Field traits$1:Lrpg/PlayerTraits;
       5: aload_0
       6: aload_3
       7: invokespecial #36                 // Method rpg/SkillTreeRepr."<init>":(Ljava/lang/Object;)V
      10: return
}
