Classfile /home/krzysiek/workspace/scala-bcode-cutter/pref/target/scala-2.12/classes/rpg/ooo/lambdas/Tree.class
  Last modified Apr 8, 2018; size 6307 bytes
  MD5 checksum 26f3762e30acef3e0ef8009d4cbb3c58
  Compiled from "LambdasSkillTrees.scala"
public class rpg.ooo.lambdas.Tree implements rpg.ooo.lambdas.Node,scala.Product,scala.Serializable
  minor version: 0
  major version: 52
  flags: ACC_PUBLIC, ACC_SUPER
Constant pool:
    #1 = Utf8               rpg/ooo/lambdas/Tree
    #2 = Class              #1            // rpg/ooo/lambdas/Tree
    #3 = Utf8               java/lang/Object
    #4 = Class              #3            // java/lang/Object
    #5 = Utf8               rpg/ooo/lambdas/Node
    #6 = Class              #5            // rpg/ooo/lambdas/Node
    #7 = Utf8               scala/Product
    #8 = Class              #7            // scala/Product
    #9 = Utf8               scala/Serializable
   #10 = Class              #9            // scala/Serializable
   #11 = Utf8               LambdasSkillTrees.scala
   #12 = Utf8               Lscala/reflect/ScalaSignature;
   #13 = Utf8               bytes
   #14 = Utf8               ecB&A:fK*1BYl'\rZ1t\t)a!Ap_>TaBeB<7A\n)Bc\t9i)1oY1mC&q:L(+4ER\"\nM!(pI\"aC\nYa!a)s_,8\r\taI!!M+'/[1mSj'\r\3\tm!Q3Aq\tAAZ3biV\tQ=\"BA\r%1UO\2uS>t\"E5\ta!$\r\ta\1zKJ$&/Y5ugB1\"JM11!8u!AA!E!i!4fCR+IA\t1,g\r^!!AQB\tB%#AmK$0\tU\r\",n5u!\tA!E!A:jO\"$C4A'=S:LGOkY:!)1D\ra;!)!F\ra!!)qF\ra!!)!C!w!1m\:u)\t!CC>s%ueLGo\t\t\"Aw]=\tU\n%i7y\n1Qc%AAAAqa CFEI$\r|/eKW;%cU\tqI.\n\nK6\t1JMIQO\2iK\W\r2\t!\"8o_RG/[8o\t6JA\tv]DWmY6fIZ'/[1oGDqA1+d_BLHZ3gCVdG\nQS#%\tY!C'q1m9zI,g-Y;mib-%\t%WaJ|G-^2u!J,g-=i\"a1qS!!0\t1gn?!!.<b\t\tGLTiJLgnG\t\t\"e1(o3vGR%/;z+!b4%\taZaJ|G-^2u2,W.8u)\tA7S&!:Lb7f\rJq\nb8%\te\aJ|G-^2uR,'/;peV\tEri\"lAg2\t!bY8mYG/[8o\t)(OJi\r^8s9!!AabY1oF,\rsr\"a>\nmd!a\"p_2,MYZ\t1iq!!AB}[1tQ{G-I!I1QA\ti>FO]5oOR\t!C\n\t\t\"1Q-];bYN$2!_A!aqAAAw!CA\t\tAA\n!&/Z3E\t)B\tAA'\t)\"!!!\tY\"!\t!A)TBAA\r\tyDeVtG/[7f\t#!#7:bGR4UO\2uS>t7C4+!\t!a\nMBCA+\t\t\"!QQFA%\t)a\=U\n\t$a\r6!11$aAuAaAKABB,:U!CAw\tq!8baBd>%#B@\rbAA!\t1q\n;j_:baCA#;AbAA$\t1A+9mKNB\"a8\tAa$PU!C#\n1B]3bIJ+7o7wKR1\t7UbAA,9\n1qJ6fGR
   #15 = Utf8               feat
   #16 = Utf8               Lscala/Function1;
   #17 = Utf8               Lscala/Function1<Lrpg/PlayerTraits;Ljava/lang/Object;>;
   #18 = Utf8               left
   #19 = Utf8               Lrpg/ooo/lambdas/Node;
   #20 = Utf8               right
   #21 = Utf8               unapply
   #22 = Utf8               (Lrpg/ooo/lambdas/Tree;)Lscala/Option;
   #23 = Utf8               rpg/ooo/lambdas/Tree$
   #24 = Class              #23           // rpg/ooo/lambdas/Tree$
   #25 = Utf8               MODULE$
   #26 = Utf8               Lrpg/ooo/lambdas/Tree$;
   #27 = NameAndType        #25:#26       // MODULE$:Lrpg/ooo/lambdas/Tree$;
   #28 = Fieldref           #24.#27       // rpg/ooo/lambdas/Tree$.MODULE$:Lrpg/ooo/lambdas/Tree$;
   #29 = NameAndType        #21:#22       // unapply:(Lrpg/ooo/lambdas/Tree;)Lscala/Option;
   #30 = Methodref          #24.#29       // rpg/ooo/lambdas/Tree$.unapply:(Lrpg/ooo/lambdas/Tree;)Lscala/Option;
   #31 = Utf8               apply
   #32 = Utf8               (Lscala/Function1;Lrpg/ooo/lambdas/Node;Lrpg/ooo/lambdas/Node;)Lrpg/ooo/lambdas/Tree;
   #33 = NameAndType        #31:#32       // apply:(Lscala/Function1;Lrpg/ooo/lambdas/Node;Lrpg/ooo/lambdas/Node;)Lrpg/ooo/lambdas/Tree;
   #34 = Methodref          #24.#33       // rpg/ooo/lambdas/Tree$.apply:(Lscala/Function1;Lrpg/ooo/lambdas/Node;Lrpg/ooo/lambdas/Node;)Lrpg/ooo/lambdas/Tree;
   #35 = Utf8               tupled
   #36 = Utf8               ()Lscala/Function1;
   #37 = NameAndType        #35:#36       // tupled:()Lscala/Function1;
   #38 = Methodref          #24.#37       // rpg/ooo/lambdas/Tree$.tupled:()Lscala/Function1;
   #39 = Utf8               curried
   #40 = NameAndType        #39:#36       // curried:()Lscala/Function1;
   #41 = Methodref          #24.#40       // rpg/ooo/lambdas/Tree$.curried:()Lscala/Function1;
   #42 = NameAndType        #15:#16       // feat:Lscala/Function1;
   #43 = Fieldref           #2.#42        // rpg/ooo/lambdas/Tree.feat:Lscala/Function1;
   #44 = Utf8               this
   #45 = Utf8               Lrpg/ooo/lambdas/Tree;
   #46 = Utf8               ()Lrpg/ooo/lambdas/Node;
   #47 = NameAndType        #18:#19       // left:Lrpg/ooo/lambdas/Node;
   #48 = Fieldref           #2.#47        // rpg/ooo/lambdas/Tree.left:Lrpg/ooo/lambdas/Node;
   #49 = NameAndType        #20:#19       // right:Lrpg/ooo/lambdas/Node;
   #50 = Fieldref           #2.#49        // rpg/ooo/lambdas/Tree.right:Lrpg/ooo/lambdas/Node;
   #51 = Utf8               cost
   #52 = Utf8               (Lrpg/PlayerTraits;)I
   #53 = Utf8               traits
   #54 = NameAndType        #18:#46       // left:()Lrpg/ooo/lambdas/Node;
   #55 = Methodref          #2.#54        // rpg/ooo/lambdas/Tree.left:()Lrpg/ooo/lambdas/Node;
   #56 = NameAndType        #51:#52       // cost:(Lrpg/PlayerTraits;)I
   #57 = InterfaceMethodref #6.#56        // rpg/ooo/lambdas/Node.cost:(Lrpg/PlayerTraits;)I
   #58 = NameAndType        #20:#46       // right:()Lrpg/ooo/lambdas/Node;
   #59 = Methodref          #2.#58        // rpg/ooo/lambdas/Tree.right:()Lrpg/ooo/lambdas/Node;
   #60 = NameAndType        #15:#36       // feat:()Lscala/Function1;
   #61 = Methodref          #2.#60        // rpg/ooo/lambdas/Tree.feat:()Lscala/Function1;
   #62 = Utf8               scala/Function1
   #63 = Class              #62           // scala/Function1
   #64 = Utf8               (Ljava/lang/Object;)Ljava/lang/Object;
   #65 = NameAndType        #31:#64       // apply:(Ljava/lang/Object;)Ljava/lang/Object;
   #66 = InterfaceMethodref #63.#65       // scala/Function1.apply:(Ljava/lang/Object;)Ljava/lang/Object;
   #67 = Utf8               scala/runtime/BoxesRunTime
   #68 = Class              #67           // scala/runtime/BoxesRunTime
   #69 = Utf8               unboxToInt
   #70 = Utf8               (Ljava/lang/Object;)I
   #71 = NameAndType        #69:#70       // unboxToInt:(Ljava/lang/Object;)I
   #72 = Methodref          #68.#71       // scala/runtime/BoxesRunTime.unboxToInt:(Ljava/lang/Object;)I
   #73 = Utf8               Lrpg/PlayerTraits;
   #74 = Utf8               copy
   #75 = Utf8               <init>
   #76 = Utf8               (Lscala/Function1;Lrpg/ooo/lambdas/Node;Lrpg/ooo/lambdas/Node;)V
   #77 = NameAndType        #75:#76       // "<init>":(Lscala/Function1;Lrpg/ooo/lambdas/Node;Lrpg/ooo/lambdas/Node;)V
   #78 = Methodref          #2.#77        // rpg/ooo/lambdas/Tree."<init>":(Lscala/Function1;Lrpg/ooo/lambdas/Node;Lrpg/ooo/lambdas/Node;)V
   #79 = Utf8               copy$default$1
   #80 = Utf8               copy$default$2
   #81 = Utf8               copy$default$3
   #82 = Utf8               productPrefix
   #83 = Utf8               ()Ljava/lang/String;
   #84 = Utf8               Tree
   #85 = String             #84           // Tree
   #86 = Utf8               productArity
   #87 = Utf8               ()I
   #88 = Utf8               productElement
   #89 = Utf8               (I)Ljava/lang/Object;
   #90 = Utf8               x$1
   #91 = Utf8               java/lang/IndexOutOfBoundsException
   #92 = Class              #91           // java/lang/IndexOutOfBoundsException
   #93 = Utf8               boxToInteger
   #94 = Utf8               (I)Ljava/lang/Integer;
   #95 = NameAndType        #93:#94       // boxToInteger:(I)Ljava/lang/Integer;
   #96 = Methodref          #68.#95       // scala/runtime/BoxesRunTime.boxToInteger:(I)Ljava/lang/Integer;
   #97 = Utf8               toString
   #98 = NameAndType        #97:#83       // toString:()Ljava/lang/String;
   #99 = Methodref          #4.#98        // java/lang/Object.toString:()Ljava/lang/String;
  #100 = Utf8               (Ljava/lang/String;)V
  #101 = NameAndType        #75:#100      // "<init>":(Ljava/lang/String;)V
  #102 = Methodref          #92.#101      // java/lang/IndexOutOfBoundsException."<init>":(Ljava/lang/String;)V
  #103 = Utf8               I
  #104 = Utf8               productIterator
  #105 = Utf8               ()Lscala/collection/Iterator;
  #106 = Utf8               scala/runtime/ScalaRunTime$
  #107 = Class              #106          // scala/runtime/ScalaRunTime$
  #108 = Utf8               Lscala/runtime/ScalaRunTime$;
  #109 = NameAndType        #25:#108      // MODULE$:Lscala/runtime/ScalaRunTime$;
  #110 = Fieldref           #107.#109     // scala/runtime/ScalaRunTime$.MODULE$:Lscala/runtime/ScalaRunTime$;
  #111 = Utf8               typedProductIterator
  #112 = Utf8               (Lscala/Product;)Lscala/collection/Iterator;
  #113 = NameAndType        #111:#112     // typedProductIterator:(Lscala/Product;)Lscala/collection/Iterator;
  #114 = Methodref          #107.#113     // scala/runtime/ScalaRunTime$.typedProductIterator:(Lscala/Product;)Lscala/collection/Iterator;
  #115 = Utf8               canEqual
  #116 = Utf8               (Ljava/lang/Object;)Z
  #117 = Utf8               Ljava/lang/Object;
  #118 = Utf8               hashCode
  #119 = Utf8               _hashCode
  #120 = Utf8               (Lscala/Product;)I
  #121 = NameAndType        #119:#120     // _hashCode:(Lscala/Product;)I
  #122 = Methodref          #107.#121     // scala/runtime/ScalaRunTime$._hashCode:(Lscala/Product;)I
  #123 = Utf8               _toString
  #124 = Utf8               (Lscala/Product;)Ljava/lang/String;
  #125 = NameAndType        #123:#124     // _toString:(Lscala/Product;)Ljava/lang/String;
  #126 = Methodref          #107.#125     // scala/runtime/ScalaRunTime$._toString:(Lscala/Product;)Ljava/lang/String;
  #127 = Utf8               equals
  #128 = NameAndType        #127:#116     // equals:(Ljava/lang/Object;)Z
  #129 = Methodref          #4.#128       // java/lang/Object.equals:(Ljava/lang/Object;)Z
  #130 = NameAndType        #115:#116     // canEqual:(Ljava/lang/Object;)Z
  #131 = Methodref          #2.#130       // rpg/ooo/lambdas/Tree.canEqual:(Ljava/lang/Object;)Z
  #132 = Utf8               ()V
  #133 = NameAndType        #75:#132      // "<init>":()V
  #134 = Methodref          #4.#133       // java/lang/Object."<init>":()V
  #135 = Utf8               $init$
  #136 = Utf8               (Lscala/Product;)V
  #137 = NameAndType        #135:#136     // $init$:(Lscala/Product;)V
  #138 = InterfaceMethodref #8.#137       // scala/Product.$init$:(Lscala/Product;)V
  #139 = Utf8               Signature
  #140 = Utf8               Code
  #141 = Utf8               (Lrpg/ooo/lambdas/Tree;)Lscala/Option<Lscala/Tuple3<Lscala/Function1<Lrpg/PlayerTraits;Ljava/lang/Object;>;Lrpg/ooo/lambdas/Node;Lrpg/ooo/lambdas/Node;>;>;
  #142 = Utf8               (Lscala/Function1<Lrpg/PlayerTraits;Ljava/lang/Object;>;Lrpg/ooo/lambdas/Node;Lrpg/ooo/lambdas/Node;)Lrpg/ooo/lambdas/Tree;
  #143 = Utf8               ()Lscala/Function1<Lscala/Tuple3<Lscala/Function1<Lrpg/PlayerTraits;Ljava/lang/Object;>;Lrpg/ooo/lambdas/Node;Lrpg/ooo/lambdas/Node;>;Lrpg/ooo/lambdas/Tree;>;
  #144 = Utf8               ()Lscala/Function1<Lscala/Function1<Lrpg/PlayerTraits;Ljava/lang/Object;>;Lscala/Function1<Lrpg/ooo/lambdas/Node;Lscala/Function1<Lrpg/ooo/lambdas/Node;Lrpg/ooo/lambdas/Tree;>;>;>;
  #145 = Utf8               LocalVariableTable
  #146 = Utf8               LineNumberTable
  #147 = Utf8               ()Lscala/Function1<Lrpg/PlayerTraits;Ljava/lang/Object;>;
  #148 = Utf8               MethodParameters
  #149 = Utf8               StackMapTable
  #150 = Utf8               ()Lscala/collection/Iterator<Ljava/lang/Object;>;
  #151 = Utf8               (Lscala/Function1<Lrpg/PlayerTraits;Ljava/lang/Object;>;Lrpg/ooo/lambdas/Node;Lrpg/ooo/lambdas/Node;)V
  #152 = Utf8               SourceFile
  #153 = Utf8               RuntimeVisibleAnnotations
  #154 = Utf8               ScalaInlineInfo
  #155 = Utf8               ScalaSig
{
  private final scala.Function1<rpg.PlayerTraits, java.lang.Object> feat;
    descriptor: Lscala/Function1;
    flags: ACC_PRIVATE, ACC_FINAL
    Signature: #17                          // Lscala/Function1<Lrpg/PlayerTraits;Ljava/lang/Object;>;

  private final rpg.ooo.lambdas.Node left;
    descriptor: Lrpg/ooo/lambdas/Node;
    flags: ACC_PRIVATE, ACC_FINAL

  private final rpg.ooo.lambdas.Node right;
    descriptor: Lrpg/ooo/lambdas/Node;
    flags: ACC_PRIVATE, ACC_FINAL

  public static scala.Option<scala.Tuple3<scala.Function1<rpg.PlayerTraits, java.lang.Object>, rpg.ooo.lambdas.Node, rpg.ooo.lambdas.Node>> unapply(rpg.ooo.lambdas.Tree);
    descriptor: (Lrpg/ooo/lambdas/Tree;)Lscala/Option;
    flags: ACC_PUBLIC, ACC_STATIC
    Code:
      stack=2, locals=1, args_size=1
         0: getstatic     #28                 // Field rpg/ooo/lambdas/Tree$.MODULE$:Lrpg/ooo/lambdas/Tree$;
         3: aload_0
         4: invokevirtual #30                 // Method rpg/ooo/lambdas/Tree$.unapply:(Lrpg/ooo/lambdas/Tree;)Lscala/Option;
         7: areturn
    Signature: #141                         // (Lrpg/ooo/lambdas/Tree;)Lscala/Option<Lscala/Tuple3<Lscala/Function1<Lrpg/PlayerTraits;Ljava/lang/Object;>;Lrpg/ooo/lambdas/Node;Lrpg/ooo/lambdas/Node;>;>;

  public static rpg.ooo.lambdas.Tree apply(scala.Function1<rpg.PlayerTraits, java.lang.Object>, rpg.ooo.lambdas.Node, rpg.ooo.lambdas.Node);
    descriptor: (Lscala/Function1;Lrpg/ooo/lambdas/Node;Lrpg/ooo/lambdas/Node;)Lrpg/ooo/lambdas/Tree;
    flags: ACC_PUBLIC, ACC_STATIC
    Code:
      stack=4, locals=3, args_size=3
         0: getstatic     #28                 // Field rpg/ooo/lambdas/Tree$.MODULE$:Lrpg/ooo/lambdas/Tree$;
         3: aload_0
         4: aload_1
         5: aload_2
         6: invokevirtual #34                 // Method rpg/ooo/lambdas/Tree$.apply:(Lscala/Function1;Lrpg/ooo/lambdas/Node;Lrpg/ooo/lambdas/Node;)Lrpg/ooo/lambdas/Tree;
         9: areturn
    Signature: #142                         // (Lscala/Function1<Lrpg/PlayerTraits;Ljava/lang/Object;>;Lrpg/ooo/lambdas/Node;Lrpg/ooo/lambdas/Node;)Lrpg/ooo/lambdas/Tree;

  public static scala.Function1<scala.Tuple3<scala.Function1<rpg.PlayerTraits, java.lang.Object>, rpg.ooo.lambdas.Node, rpg.ooo.lambdas.Node>, rpg.ooo.lambdas.Tree> tupled();
    descriptor: ()Lscala/Function1;
    flags: ACC_PUBLIC, ACC_STATIC
    Code:
      stack=1, locals=0, args_size=0
         0: getstatic     #28                 // Field rpg/ooo/lambdas/Tree$.MODULE$:Lrpg/ooo/lambdas/Tree$;
         3: invokevirtual #38                 // Method rpg/ooo/lambdas/Tree$.tupled:()Lscala/Function1;
         6: areturn
    Signature: #143                         // ()Lscala/Function1<Lscala/Tuple3<Lscala/Function1<Lrpg/PlayerTraits;Ljava/lang/Object;>;Lrpg/ooo/lambdas/Node;Lrpg/ooo/lambdas/Node;>;Lrpg/ooo/lambdas/Tree;>;

  public static scala.Function1<scala.Function1<rpg.PlayerTraits, java.lang.Object>, scala.Function1<rpg.ooo.lambdas.Node, scala.Function1<rpg.ooo.lambdas.Node, rpg.ooo.lambdas.Tree>>> curried();
    descriptor: ()Lscala/Function1;
    flags: ACC_PUBLIC, ACC_STATIC
    Code:
      stack=1, locals=0, args_size=0
         0: getstatic     #28                 // Field rpg/ooo/lambdas/Tree$.MODULE$:Lrpg/ooo/lambdas/Tree$;
         3: invokevirtual #41                 // Method rpg/ooo/lambdas/Tree$.curried:()Lscala/Function1;
         6: areturn
    Signature: #144                         // ()Lscala/Function1<Lscala/Function1<Lrpg/PlayerTraits;Ljava/lang/Object;>;Lscala/Function1<Lrpg/ooo/lambdas/Node;Lscala/Function1<Lrpg/ooo/lambdas/Node;Lrpg/ooo/lambdas/Tree;>;>;>;

  public scala.Function1<rpg.PlayerTraits, java.lang.Object> feat();
    descriptor: ()Lscala/Function1;
    flags: ACC_PUBLIC
    Code:
      stack=1, locals=1, args_size=1
         0: aload_0
         1: getfield      #43                 // Field feat:Lscala/Function1;
         4: areturn
      LocalVariableTable:
        Start  Length  Slot  Name   Signature
            0       5     0  this   Lrpg/ooo/lambdas/Tree;
      LineNumberTable:
        line 11: 0
    Signature: #147                         // ()Lscala/Function1<Lrpg/PlayerTraits;Ljava/lang/Object;>;

  public rpg.ooo.lambdas.Node left();
    descriptor: ()Lrpg/ooo/lambdas/Node;
    flags: ACC_PUBLIC
    Code:
      stack=1, locals=1, args_size=1
         0: aload_0
         1: getfield      #48                 // Field left:Lrpg/ooo/lambdas/Node;
         4: areturn
      LocalVariableTable:
        Start  Length  Slot  Name   Signature
            0       5     0  this   Lrpg/ooo/lambdas/Tree;
      LineNumberTable:
        line 11: 0

  public rpg.ooo.lambdas.Node right();
    descriptor: ()Lrpg/ooo/lambdas/Node;
    flags: ACC_PUBLIC
    Code:
      stack=1, locals=1, args_size=1
         0: aload_0
         1: getfield      #50                 // Field right:Lrpg/ooo/lambdas/Node;
         4: areturn
      LocalVariableTable:
        Start  Length  Slot  Name   Signature
            0       5     0  this   Lrpg/ooo/lambdas/Tree;
      LineNumberTable:
        line 11: 0

  public int cost(rpg.PlayerTraits);
    descriptor: (Lrpg/PlayerTraits;)I
    flags: ACC_PUBLIC
    Code:
      stack=3, locals=2, args_size=2
         0: aload_0
         1: invokevirtual #55                 // Method left:()Lrpg/ooo/lambdas/Node;
         4: aload_1
         5: invokeinterface #57,  2           // InterfaceMethod rpg/ooo/lambdas/Node.cost:(Lrpg/PlayerTraits;)I
        10: aload_0
        11: invokevirtual #59                 // Method right:()Lrpg/ooo/lambdas/Node;
        14: aload_1
        15: invokeinterface #57,  2           // InterfaceMethod rpg/ooo/lambdas/Node.cost:(Lrpg/PlayerTraits;)I
        20: iadd
        21: aload_0
        22: invokevirtual #61                 // Method feat:()Lscala/Function1;
        25: aload_1
        26: invokeinterface #66,  2           // InterfaceMethod scala/Function1.apply:(Ljava/lang/Object;)Ljava/lang/Object;
        31: invokestatic  #72                 // Method scala/runtime/BoxesRunTime.unboxToInt:(Ljava/lang/Object;)I
        34: iadd
        35: ireturn
      LocalVariableTable:
        Start  Length  Slot  Name   Signature
            0      36     0  this   Lrpg/ooo/lambdas/Tree;
            0      36     1 traits   Lrpg/PlayerTraits;
      LineNumberTable:
        line 13: 0
    MethodParameters:
      Name                           Flags
      traits                         final

  public rpg.ooo.lambdas.Tree copy(scala.Function1<rpg.PlayerTraits, java.lang.Object>, rpg.ooo.lambdas.Node, rpg.ooo.lambdas.Node);
    descriptor: (Lscala/Function1;Lrpg/ooo/lambdas/Node;Lrpg/ooo/lambdas/Node;)Lrpg/ooo/lambdas/Tree;
    flags: ACC_PUBLIC
    Code:
      stack=5, locals=4, args_size=4
         0: new           #2                  // class rpg/ooo/lambdas/Tree
         3: dup
         4: aload_1
         5: aload_2
         6: aload_3
         7: invokespecial #78                 // Method "<init>":(Lscala/Function1;Lrpg/ooo/lambdas/Node;Lrpg/ooo/lambdas/Node;)V
        10: areturn
      LocalVariableTable:
        Start  Length  Slot  Name   Signature
            0      11     0  this   Lrpg/ooo/lambdas/Tree;
            0      11     1  feat   Lscala/Function1;
            0      11     2  left   Lrpg/ooo/lambdas/Node;
            0      11     3 right   Lrpg/ooo/lambdas/Node;
      LineNumberTable:
        line 11: 0
    Signature: #142                         // (Lscala/Function1<Lrpg/PlayerTraits;Ljava/lang/Object;>;Lrpg/ooo/lambdas/Node;Lrpg/ooo/lambdas/Node;)Lrpg/ooo/lambdas/Tree;
    MethodParameters:
      Name                           Flags
      feat                           final
      left                           final
      right                          final

  public scala.Function1<rpg.PlayerTraits, java.lang.Object> copy$default$1();
    descriptor: ()Lscala/Function1;
    flags: ACC_PUBLIC
    Code:
      stack=1, locals=1, args_size=1
         0: aload_0
         1: invokevirtual #61                 // Method feat:()Lscala/Function1;
         4: areturn
      LocalVariableTable:
        Start  Length  Slot  Name   Signature
            0       5     0  this   Lrpg/ooo/lambdas/Tree;
      LineNumberTable:
        line 11: 0
    Signature: #147                         // ()Lscala/Function1<Lrpg/PlayerTraits;Ljava/lang/Object;>;

  public rpg.ooo.lambdas.Node copy$default$2();
    descriptor: ()Lrpg/ooo/lambdas/Node;
    flags: ACC_PUBLIC
    Code:
      stack=1, locals=1, args_size=1
         0: aload_0
         1: invokevirtual #55                 // Method left:()Lrpg/ooo/lambdas/Node;
         4: areturn
      LocalVariableTable:
        Start  Length  Slot  Name   Signature
            0       5     0  this   Lrpg/ooo/lambdas/Tree;
      LineNumberTable:
        line 11: 0

  public rpg.ooo.lambdas.Node copy$default$3();
    descriptor: ()Lrpg/ooo/lambdas/Node;
    flags: ACC_PUBLIC
    Code:
      stack=1, locals=1, args_size=1
         0: aload_0
         1: invokevirtual #59                 // Method right:()Lrpg/ooo/lambdas/Node;
         4: areturn
      LocalVariableTable:
        Start  Length  Slot  Name   Signature
            0       5     0  this   Lrpg/ooo/lambdas/Tree;
      LineNumberTable:
        line 11: 0

  public java.lang.String productPrefix();
    descriptor: ()Ljava/lang/String;
    flags: ACC_PUBLIC
    Code:
      stack=1, locals=1, args_size=1
         0: ldc           #85                 // String Tree
         2: areturn
      LocalVariableTable:
        Start  Length  Slot  Name   Signature
            0       3     0  this   Lrpg/ooo/lambdas/Tree;
      LineNumberTable:
        line 11: 0

  public int productArity();
    descriptor: ()I
    flags: ACC_PUBLIC
    Code:
      stack=1, locals=1, args_size=1
         0: iconst_3
         1: ireturn
      LocalVariableTable:
        Start  Length  Slot  Name   Signature
            0       2     0  this   Lrpg/ooo/lambdas/Tree;
      LineNumberTable:
        line 11: 0

  public java.lang.Object productElement(int);
    descriptor: (I)Ljava/lang/Object;
    flags: ACC_PUBLIC
    Code:
      stack=3, locals=3, args_size=2
         0: iload_1
         1: istore_2
         2: iload_2
         3: tableswitch   { // 0 to 2
                       0: 28
                       1: 35
                       2: 42
                 default: 49
            }
        28: aload_0
        29: invokevirtual #61                 // Method feat:()Lscala/Function1;
        32: goto          64
        35: aload_0
        36: invokevirtual #55                 // Method left:()Lrpg/ooo/lambdas/Node;
        39: goto          64
        42: aload_0
        43: invokevirtual #59                 // Method right:()Lrpg/ooo/lambdas/Node;
        46: goto          64
        49: new           #92                 // class java/lang/IndexOutOfBoundsException
        52: dup
        53: iload_1
        54: invokestatic  #96                 // Method scala/runtime/BoxesRunTime.boxToInteger:(I)Ljava/lang/Integer;
        57: invokevirtual #99                 // Method java/lang/Object.toString:()Ljava/lang/String;
        60: invokespecial #102                // Method java/lang/IndexOutOfBoundsException."<init>":(Ljava/lang/String;)V
        63: athrow
        64: areturn
      LocalVariableTable:
        Start  Length  Slot  Name   Signature
            0      65     0  this   Lrpg/ooo/lambdas/Tree;
            0      65     1   x$1   I
      LineNumberTable:
        line 11: 0
      StackMapTable: number_of_entries = 5
        frame_type = 252 /* append */
          offset_delta = 28
          locals = [ int ]
        frame_type = 6 /* same */
        frame_type = 6 /* same */
        frame_type = 6 /* same */
        frame_type = 78 /* same_locals_1_stack_item */
          stack = [ class java/lang/Object ]
    MethodParameters:
      Name                           Flags
      x$1                            final

  public scala.collection.Iterator<java.lang.Object> productIterator();
    descriptor: ()Lscala/collection/Iterator;
    flags: ACC_PUBLIC
    Code:
      stack=2, locals=1, args_size=1
         0: getstatic     #110                // Field scala/runtime/ScalaRunTime$.MODULE$:Lscala/runtime/ScalaRunTime$;
         3: aload_0
         4: invokevirtual #114                // Method scala/runtime/ScalaRunTime$.typedProductIterator:(Lscala/Product;)Lscala/collection/Iterator;
         7: areturn
      LocalVariableTable:
        Start  Length  Slot  Name   Signature
            0       8     0  this   Lrpg/ooo/lambdas/Tree;
      LineNumberTable:
        line 11: 0
    Signature: #150                         // ()Lscala/collection/Iterator<Ljava/lang/Object;>;

  public boolean canEqual(java.lang.Object);
    descriptor: (Ljava/lang/Object;)Z
    flags: ACC_PUBLIC
    Code:
      stack=1, locals=2, args_size=2
         0: aload_1
         1: instanceof    #2                  // class rpg/ooo/lambdas/Tree
         4: ireturn
      LocalVariableTable:
        Start  Length  Slot  Name   Signature
            0       5     0  this   Lrpg/ooo/lambdas/Tree;
            0       5     1   x$1   Ljava/lang/Object;
      LineNumberTable:
        line 11: 0
    MethodParameters:
      Name                           Flags
      x$1                            final

  public int hashCode();
    descriptor: ()I
    flags: ACC_PUBLIC
    Code:
      stack=2, locals=1, args_size=1
         0: getstatic     #110                // Field scala/runtime/ScalaRunTime$.MODULE$:Lscala/runtime/ScalaRunTime$;
         3: aload_0
         4: invokevirtual #122                // Method scala/runtime/ScalaRunTime$._hashCode:(Lscala/Product;)I
         7: ireturn
      LocalVariableTable:
        Start  Length  Slot  Name   Signature
            0       8     0  this   Lrpg/ooo/lambdas/Tree;
      LineNumberTable:
        line 11: 0

  public java.lang.String toString();
    descriptor: ()Ljava/lang/String;
    flags: ACC_PUBLIC
    Code:
      stack=2, locals=1, args_size=1
         0: getstatic     #110                // Field scala/runtime/ScalaRunTime$.MODULE$:Lscala/runtime/ScalaRunTime$;
         3: aload_0
         4: invokevirtual #126                // Method scala/runtime/ScalaRunTime$._toString:(Lscala/Product;)Ljava/lang/String;
         7: areturn
      LocalVariableTable:
        Start  Length  Slot  Name   Signature
            0       8     0  this   Lrpg/ooo/lambdas/Tree;
      LineNumberTable:
        line 11: 0

  public boolean equals(java.lang.Object);
    descriptor: (Ljava/lang/Object;)Z
    flags: ACC_PUBLIC
    Code:
      stack=2, locals=8, args_size=2
         0: aload_0
         1: aload_1
         2: if_acmpeq     150
         5: aload_1
         6: astore_3
         7: aload_3
         8: instanceof    #2                  // class rpg/ooo/lambdas/Tree
        11: ifeq          19
        14: iconst_1
        15: istore_2
        16: goto          27
        19: goto          22
        22: iconst_0
        23: istore_2
        24: goto          27
        27: iload_2
        28: ifeq          154
        31: aload_1
        32: checkcast     #2                  // class rpg/ooo/lambdas/Tree
        35: astore        4
        37: aload_0
        38: invokevirtual #61                 // Method feat:()Lscala/Function1;
        41: aload         4
        43: invokevirtual #61                 // Method feat:()Lscala/Function1;
        46: astore        5
        48: dup
        49: ifnonnull     61
        52: pop
        53: aload         5
        55: ifnull        69
        58: goto          146
        61: aload         5
        63: invokevirtual #129                // Method java/lang/Object.equals:(Ljava/lang/Object;)Z
        66: ifeq          146
        69: aload_0
        70: invokevirtual #55                 // Method left:()Lrpg/ooo/lambdas/Node;
        73: aload         4
        75: invokevirtual #55                 // Method left:()Lrpg/ooo/lambdas/Node;
        78: astore        6
        80: dup
        81: ifnonnull     93
        84: pop
        85: aload         6
        87: ifnull        101
        90: goto          146
        93: aload         6
        95: invokevirtual #129                // Method java/lang/Object.equals:(Ljava/lang/Object;)Z
        98: ifeq          146
       101: aload_0
       102: invokevirtual #59                 // Method right:()Lrpg/ooo/lambdas/Node;
       105: aload         4
       107: invokevirtual #59                 // Method right:()Lrpg/ooo/lambdas/Node;
       110: astore        7
       112: dup
       113: ifnonnull     125
       116: pop
       117: aload         7
       119: ifnull        133
       122: goto          146
       125: aload         7
       127: invokevirtual #129                // Method java/lang/Object.equals:(Ljava/lang/Object;)Z
       130: ifeq          146
       133: aload         4
       135: aload_0
       136: invokevirtual #131                // Method canEqual:(Ljava/lang/Object;)Z
       139: ifeq          146
       142: iconst_1
       143: goto          147
       146: iconst_0
       147: ifeq          154
       150: iconst_1
       151: goto          155
       154: iconst_0
       155: ireturn
      LocalVariableTable:
        Start  Length  Slot  Name   Signature
            0     156     0  this   Lrpg/ooo/lambdas/Tree;
            0     156     1   x$1   Ljava/lang/Object;
      LineNumberTable:
        line 11: 0
      StackMapTable: number_of_entries = 14
        frame_type = 253 /* append */
          offset_delta = 19
          locals = [ top, class java/lang/Object ]
        frame_type = 2 /* same */
        frame_type = 255 /* full_frame */
          offset_delta = 4
          locals = [ class rpg/ooo/lambdas/Tree, class java/lang/Object, int, class java/lang/Object ]
          stack = []
        frame_type = 255 /* full_frame */
          offset_delta = 33
          locals = [ class rpg/ooo/lambdas/Tree, class java/lang/Object, int, class java/lang/Object, class rpg/ooo/lambdas/Tree, class scala/Function1 ]
          stack = [ class scala/Function1 ]
        frame_type = 7 /* same */
        frame_type = 255 /* full_frame */
          offset_delta = 23
          locals = [ class rpg/ooo/lambdas/Tree, class java/lang/Object, int, class java/lang/Object, class rpg/ooo/lambdas/Tree, class scala/Function1, class rpg/ooo/lambdas/Node ]
          stack = [ class rpg/ooo/lambdas/Node ]
        frame_type = 7 /* same */
        frame_type = 255 /* full_frame */
          offset_delta = 23
          locals = [ class rpg/ooo/lambdas/Tree, class java/lang/Object, int, class java/lang/Object, class rpg/ooo/lambdas/Tree, class scala/Function1, class rpg/ooo/lambdas/Node, class rpg/ooo/lambdas/Node ]
          stack = [ class rpg/ooo/lambdas/Node ]
        frame_type = 7 /* same */
        frame_type = 249 /* chop */
          offset_delta = 12
        frame_type = 64 /* same_locals_1_stack_item */
          stack = [ int ]
        frame_type = 255 /* full_frame */
          offset_delta = 2
          locals = [ class rpg/ooo/lambdas/Tree, class java/lang/Object ]
          stack = []
        frame_type = 253 /* append */
          offset_delta = 3
          locals = [ int, class java/lang/Object ]
        frame_type = 255 /* full_frame */
          offset_delta = 0
          locals = [ class rpg/ooo/lambdas/Tree, class java/lang/Object ]
          stack = [ int ]
    MethodParameters:
      Name                           Flags
      x$1                            final

  public rpg.ooo.lambdas.Tree(scala.Function1<rpg.PlayerTraits, java.lang.Object>, rpg.ooo.lambdas.Node, rpg.ooo.lambdas.Node);
    descriptor: (Lscala/Function1;Lrpg/ooo/lambdas/Node;Lrpg/ooo/lambdas/Node;)V
    flags: ACC_PUBLIC
    Code:
      stack=2, locals=4, args_size=4
         0: aload_0
         1: aload_1
         2: putfield      #43                 // Field feat:Lscala/Function1;
         5: aload_0
         6: aload_2
         7: putfield      #48                 // Field left:Lrpg/ooo/lambdas/Node;
        10: aload_0
        11: aload_3
        12: putfield      #50                 // Field right:Lrpg/ooo/lambdas/Node;
        15: aload_0
        16: invokespecial #134                // Method java/lang/Object."<init>":()V
        19: aload_0
        20: invokestatic  #138                // InterfaceMethod scala/Product.$init$:(Lscala/Product;)V
        23: return
      LocalVariableTable:
        Start  Length  Slot  Name   Signature
            0      24     0  this   Lrpg/ooo/lambdas/Tree;
            0      24     1  feat   Lscala/Function1;
            0      24     2  left   Lrpg/ooo/lambdas/Node;
            0      24     3 right   Lrpg/ooo/lambdas/Node;
      LineNumberTable:
        line 11: 0
    Signature: #151                         // (Lscala/Function1<Lrpg/PlayerTraits;Ljava/lang/Object;>;Lrpg/ooo/lambdas/Node;Lrpg/ooo/lambdas/Node;)V
    MethodParameters:
      Name                           Flags
      feat                           final
      left                           final
      right                          final
}
SourceFile: "LambdasSkillTrees.scala"
RuntimeVisibleAnnotations:
  0: #12(#13=s#14)
Error: unknown attribute
  ScalaInlineInfo: length = 0x59
   01 00 00 11 00 4B 00 4C 00 00 73 00 74 00 00 4F
   00 24 00 00 50 00 2E 00 00 51 00 2E 00 00 4A 00
   20 00 00 33 00 34 00 00 7F 00 74 00 00 0F 00 24
   00 00 76 00 57 00 00 12 00 2E 00 00 56 00 57 00
   00 58 00 59 00 00 68 00 69 00 00 52 00 53 00 00
   14 00 2E 00 00 61 00 53 00
Error: unknown attribute
  ScalaSig: length = 0x3
   05 00 00
