Classfile /home/krzysiek/workspace/scala-bcode-cutter/pref/target/scala-2.12/classes/rpg/ooo/subcalls/OOOSkillTrees.class
  Last modified Apr 8, 2018; size 1819 bytes
  MD5 checksum 1307938a469e28f3df29486f15e891f8
  Compiled from "OOOSubcallsSkillTrees.scala"
public class rpg.ooo.subcalls.OOOSkillTrees extends rpg.SkillTrees
  minor version: 0
  major version: 52
  flags: ACC_PUBLIC, ACC_SUPER
Constant pool:
   #1 = Utf8               rpg/ooo/subcalls/OOOSkillTrees
   #2 = Class              #1             // rpg/ooo/subcalls/OOOSkillTrees
   #3 = Utf8               rpg/SkillTrees
   #4 = Class              #3             // rpg/SkillTrees
   #5 = Utf8               OOOSubcallsSkillTrees.scala
   #6 = Utf8               Lscala/reflect/ScalaSignature;
   #7 = Utf8               bytes
   #8 = Utf8               52A!\tiqjT(TW&dG:fKNT!aM,(mY1mYNT!!=|wNC\roZ'\t!5\ta!\r\tQ1k[5mYRX-Z:\t=A\t\rqJg.;?)\tC\n\"\t*aC1sG\",'/+sK$\"A1]acA5%D'.LG+sKV\r:maB\n;M\t\t!Ay1a2#\tyR!G5\tEC#8-7b\t!EAO_RDN\42BA\"\r\te.SM\rAKiJ^:-YB1F.Y=feR-;t
   #9 = Utf8               rpg/ooo/subcalls/OOOSkillTrees$$anon$1
  #10 = Class              #9             // rpg/ooo/subcalls/OOOSkillTrees$$anon$1
  #11 = Utf8               archeryTree
  #12 = Utf8               (Lrpg/PlayerTraits;)Lrpg/SkillTreeRepr;
  #13 = Utf8               traits
  #14 = Utf8               rpg/ooo/subcalls/DexTree
  #15 = Class              #14            // rpg/ooo/subcalls/DexTree
  #16 = Utf8               rpg/ooo/subcalls/DexStep
  #17 = Class              #16            // rpg/ooo/subcalls/DexStep
  #18 = Utf8               rpg/ooo/subcalls/WisTree
  #19 = Class              #18            // rpg/ooo/subcalls/WisTree
  #20 = Utf8               rpg/ooo/subcalls/WisSkill
  #21 = Class              #20            // rpg/ooo/subcalls/WisSkill
  #22 = Utf8               aimed
  #23 = String             #22            // aimed
  #24 = Utf8               <init>
  #25 = Utf8               (Ljava/lang/String;)V
  #26 = NameAndType        #24:#25        // "<init>":(Ljava/lang/String;)V
  #27 = Methodref          #21.#26        // rpg/ooo/subcalls/WisSkill."<init>":(Ljava/lang/String;)V
  #28 = Utf8               rpg/ooo/subcalls/WisStep
  #29 = Class              #28            // rpg/ooo/subcalls/WisStep
  #30 = Utf8               rpg/ooo/subcalls/DexSkill
  #31 = Class              #30            // rpg/ooo/subcalls/DexSkill
  #32 = Utf8               rapid
  #33 = String             #32            // rapid
  #34 = Methodref          #31.#26        // rpg/ooo/subcalls/DexSkill."<init>":(Ljava/lang/String;)V
  #35 = Utf8               (Lrpg/ooo/subcalls/Node;)V
  #36 = NameAndType        #24:#35        // "<init>":(Lrpg/ooo/subcalls/Node;)V
  #37 = Methodref          #29.#36        // rpg/ooo/subcalls/WisStep."<init>":(Lrpg/ooo/subcalls/Node;)V
  #38 = Utf8               (Lrpg/ooo/subcalls/Node;Lrpg/ooo/subcalls/Node;)V
  #39 = NameAndType        #24:#38        // "<init>":(Lrpg/ooo/subcalls/Node;Lrpg/ooo/subcalls/Node;)V
  #40 = Methodref          #19.#39        // rpg/ooo/subcalls/WisTree."<init>":(Lrpg/ooo/subcalls/Node;Lrpg/ooo/subcalls/Node;)V
  #41 = Methodref          #17.#36        // rpg/ooo/subcalls/DexStep."<init>":(Lrpg/ooo/subcalls/Node;)V
  #42 = Utf8               rpg/ooo/subcalls/StrTree
  #43 = Class              #42            // rpg/ooo/subcalls/StrTree
  #44 = Utf8               rpg/ooo/subcalls/StrSkill
  #45 = Class              #44            // rpg/ooo/subcalls/StrSkill
  #46 = Utf8               power
  #47 = String             #46            // power
  #48 = Methodref          #45.#26        // rpg/ooo/subcalls/StrSkill."<init>":(Ljava/lang/String;)V
  #49 = Utf8               rpg/ooo/subcalls/StrStep
  #50 = Class              #49            // rpg/ooo/subcalls/StrStep
  #51 = Utf8               double
  #52 = String             #51            // double
  #53 = Methodref          #50.#36        // rpg/ooo/subcalls/StrStep."<init>":(Lrpg/ooo/subcalls/Node;)V
  #54 = Methodref          #43.#39        // rpg/ooo/subcalls/StrTree."<init>":(Lrpg/ooo/subcalls/Node;Lrpg/ooo/subcalls/Node;)V
  #55 = Methodref          #15.#39        // rpg/ooo/subcalls/DexTree."<init>":(Lrpg/ooo/subcalls/Node;Lrpg/ooo/subcalls/Node;)V
  #56 = Utf8               (Lrpg/ooo/subcalls/OOOSkillTrees;Lrpg/PlayerTraits;Lrpg/ooo/subcalls/DexTree;)V
  #57 = NameAndType        #24:#56        // "<init>":(Lrpg/ooo/subcalls/OOOSkillTrees;Lrpg/PlayerTraits;Lrpg/ooo/subcalls/DexTree;)V
  #58 = Methodref          #10.#57        // rpg/ooo/subcalls/OOOSkillTrees$$anon$1."<init>":(Lrpg/ooo/subcalls/OOOSkillTrees;Lrpg/PlayerTraits;Lrpg/ooo/subcalls/DexTree;)V
  #59 = Utf8               tree
  #60 = Utf8               Lrpg/ooo/subcalls/DexTree;
  #61 = Utf8               this
  #62 = Utf8               Lrpg/ooo/subcalls/OOOSkillTrees;
  #63 = Utf8               Lrpg/PlayerTraits;
  #64 = Utf8               ()V
  #65 = NameAndType        #24:#64        // "<init>":()V
  #66 = Methodref          #4.#65         // rpg/SkillTrees."<init>":()V
  #67 = Utf8               Code
  #68 = Utf8               LocalVariableTable
  #69 = Utf8               LineNumberTable
  #70 = Utf8               Signature
  #71 = Utf8               (Lrpg/PlayerTraits;)Lrpg/SkillTreeRepr<*>;
  #72 = Utf8               MethodParameters
  #73 = Utf8               SourceFile
  #74 = Utf8               InnerClasses
  #75 = Utf8               RuntimeVisibleAnnotations
  #76 = Utf8               ScalaInlineInfo
  #77 = Utf8               ScalaSig
{
  public rpg.SkillTreeRepr<?> archeryTree(rpg.PlayerTraits);
    descriptor: (Lrpg/PlayerTraits;)Lrpg/SkillTreeRepr;
    flags: ACC_PUBLIC
    Code:
      stack=12, locals=3, args_size=2
         0: new           #15                 // class rpg/ooo/subcalls/DexTree
         3: dup
         4: new           #17                 // class rpg/ooo/subcalls/DexStep
         7: dup
         8: new           #19                 // class rpg/ooo/subcalls/WisTree
        11: dup
        12: new           #21                 // class rpg/ooo/subcalls/WisSkill
        15: dup
        16: ldc           #23                 // String aimed
        18: invokespecial #27                 // Method rpg/ooo/subcalls/WisSkill."<init>":(Ljava/lang/String;)V
        21: new           #29                 // class rpg/ooo/subcalls/WisStep
        24: dup
        25: new           #31                 // class rpg/ooo/subcalls/DexSkill
        28: dup
        29: ldc           #33                 // String rapid
        31: invokespecial #34                 // Method rpg/ooo/subcalls/DexSkill."<init>":(Ljava/lang/String;)V
        34: invokespecial #37                 // Method rpg/ooo/subcalls/WisStep."<init>":(Lrpg/ooo/subcalls/Node;)V
        37: invokespecial #40                 // Method rpg/ooo/subcalls/WisTree."<init>":(Lrpg/ooo/subcalls/Node;Lrpg/ooo/subcalls/Node;)V
        40: invokespecial #41                 // Method rpg/ooo/subcalls/DexStep."<init>":(Lrpg/ooo/subcalls/Node;)V
        43: new           #43                 // class rpg/ooo/subcalls/StrTree
        46: dup
        47: new           #45                 // class rpg/ooo/subcalls/StrSkill
        50: dup
        51: ldc           #47                 // String power
        53: invokespecial #48                 // Method rpg/ooo/subcalls/StrSkill."<init>":(Ljava/lang/String;)V
        56: new           #50                 // class rpg/ooo/subcalls/StrStep
        59: dup
        60: new           #31                 // class rpg/ooo/subcalls/DexSkill
        63: dup
        64: ldc           #52                 // String double
        66: invokespecial #34                 // Method rpg/ooo/subcalls/DexSkill."<init>":(Ljava/lang/String;)V
        69: invokespecial #53                 // Method rpg/ooo/subcalls/StrStep."<init>":(Lrpg/ooo/subcalls/Node;)V
        72: invokespecial #54                 // Method rpg/ooo/subcalls/StrTree."<init>":(Lrpg/ooo/subcalls/Node;Lrpg/ooo/subcalls/Node;)V
        75: invokespecial #55                 // Method rpg/ooo/subcalls/DexTree."<init>":(Lrpg/ooo/subcalls/Node;Lrpg/ooo/subcalls/Node;)V
        78: astore_2
        79: new           #10                 // class rpg/ooo/subcalls/OOOSkillTrees$$anon$1
        82: dup
        83: aconst_null
        84: aload_1
        85: aload_2
        86: invokespecial #58                 // Method rpg/ooo/subcalls/OOOSkillTrees$$anon$1."<init>":(Lrpg/ooo/subcalls/OOOSkillTrees;Lrpg/PlayerTraits;Lrpg/ooo/subcalls/DexTree;)V
        89: areturn
      LocalVariableTable:
        Start  Length  Slot  Name   Signature
           78      11     2  tree   Lrpg/ooo/subcalls/DexTree;
            0      90     0  this   Lrpg/ooo/subcalls/OOOSkillTrees;
            0      90     1 traits   Lrpg/PlayerTraits;
      LineNumberTable:
        line 71: 0
        line 72: 4
        line 73: 12
        line 74: 21
        line 76: 43
        line 77: 47
        line 78: 56
        line 81: 79
    Signature: #71                          // (Lrpg/PlayerTraits;)Lrpg/SkillTreeRepr<*>;
    MethodParameters:
      Name                           Flags
      traits                         final

  public rpg.ooo.subcalls.OOOSkillTrees();
    descriptor: ()V
    flags: ACC_PUBLIC
    Code:
      stack=1, locals=1, args_size=1
         0: aload_0
         1: invokespecial #66                 // Method rpg/SkillTrees."<init>":()V
         4: return
      LocalVariableTable:
        Start  Length  Slot  Name   Signature
            0       5     0  this   Lrpg/ooo/subcalls/OOOSkillTrees;
      LineNumberTable:
        line 63: 0
}
SourceFile: "OOOSubcallsSkillTrees.scala"
InnerClasses:
     public final #10; //class rpg/ooo/subcalls/OOOSkillTrees$$anon$1
RuntimeVisibleAnnotations:
  0: #6(#7=s#8)
Error: unknown attribute
  ScalaInlineInfo: length = 0xE
   01 00 00 02 00 18 00 40 00 00 0B 00 0C 00
Error: unknown attribute
  ScalaSig: length = 0x3
   05 00 00
