Compiled from "OOOSubcallsSkillTrees.scala"
public final class rpg.ooo.subcalls.WisSkill$ extends scala.runtime.AbstractFunction1<java.lang.String, rpg.ooo.subcalls.WisSkill> implements scala.Serializable {
  public static rpg.ooo.subcalls.WisSkill$ MODULE$;

  public static {};
    Code:
       0: new           #2                  // class rpg/ooo/subcalls/WisSkill$
       3: invokespecial #15                 // Method "<init>":()V
       6: return

  public final java.lang.String toString();
    Code:
       0: ldc           #19                 // String WisSkill
       2: areturn

  public rpg.ooo.subcalls.WisSkill apply(java.lang.String);
    Code:
       0: new           #25                 // class rpg/ooo/subcalls/WisSkill
       3: dup
       4: aload_1
       5: invokespecial #28                 // Method rpg/ooo/subcalls/WisSkill."<init>":(Ljava/lang/String;)V
       8: areturn

  public scala.Option<java.lang.String> unapply(rpg.ooo.subcalls.WisSkill);
    Code:
       0: aload_1
       1: ifnonnull     10
       4: getstatic     #37                 // Field scala/None$.MODULE$:Lscala/None$;
       7: goto          21
      10: new           #39                 // class scala/Some
      13: dup
      14: aload_1
      15: invokevirtual #41                 // Method rpg/ooo/subcalls/WisSkill.name:()Ljava/lang/String;
      18: invokespecial #44                 // Method scala/Some."<init>":(Ljava/lang/Object;)V
      21: areturn

  private java.lang.Object readResolve();
    Code:
       0: getstatic     #51                 // Field MODULE$:Lrpg/ooo/subcalls/WisSkill$;
       3: areturn

  public java.lang.Object apply(java.lang.Object);
    Code:
       0: aload_0
       1: aload_1
       2: checkcast     #55                 // class java/lang/String
       5: invokevirtual #57                 // Method apply:(Ljava/lang/String;)Lrpg/ooo/subcalls/WisSkill;
       8: areturn

  private rpg.ooo.subcalls.WisSkill$();
    Code:
       0: aload_0
       1: invokespecial #59                 // Method scala/runtime/AbstractFunction1."<init>":()V
       4: aload_0
       5: putstatic     #51                 // Field MODULE$:Lrpg/ooo/subcalls/WisSkill$;
       8: return
}
