Compiled from "CakeSkillTrees.scala"
public class rpg.cake2.StrNodes$StrTree$ extends scala.runtime.AbstractFunction2<rpg.cake2.NodesTraits$Node, rpg.cake2.NodesTraits$Node, rpg.cake2.StrNodes$StrTree> implements scala.Serializable {
  private final rpg.cake2.NodesTraits $outer;

  public final java.lang.String toString();
    Code:
       0: ldc           #24                 // String StrTree
       2: areturn

  public rpg.cake2.StrNodes$StrTree apply(rpg.cake2.NodesTraits$Node, rpg.cake2.NodesTraits$Node);
    Code:
       0: new           #15                 // class rpg/cake2/StrNodes$StrTree
       3: dup
       4: aload_0
       5: getfield      #32                 // Field $outer:Lrpg/cake2/NodesTraits;
       8: aload_1
       9: aload_2
      10: invokespecial #36                 // Method rpg/cake2/StrNodes$StrTree."<init>":(Lrpg/cake2/NodesTraits;Lrpg/cake2/NodesTraits$Node;Lrpg/cake2/NodesTraits$Node;)V
      13: areturn

  public scala.Option<scala.Tuple2<rpg.cake2.NodesTraits$Node, rpg.cake2.NodesTraits$Node>> unapply(rpg.cake2.StrNodes$StrTree);
    Code:
       0: aload_1
       1: ifnonnull     10
       4: getstatic     #46                 // Field scala/None$.MODULE$:Lscala/None$;
       7: goto          32
      10: new           #48                 // class scala/Some
      13: dup
      14: new           #50                 // class scala/Tuple2
      17: dup
      18: aload_1
      19: invokevirtual #53                 // Method rpg/cake2/StrNodes$StrTree.left:()Lrpg/cake2/NodesTraits$Node;
      22: aload_1
      23: invokevirtual #55                 // Method rpg/cake2/StrNodes$StrTree.right:()Lrpg/cake2/NodesTraits$Node;
      26: invokespecial #58                 // Method scala/Tuple2."<init>":(Ljava/lang/Object;Ljava/lang/Object;)V
      29: invokespecial #61                 // Method scala/Some."<init>":(Ljava/lang/Object;)V
      32: areturn

  public java.lang.Object apply(java.lang.Object, java.lang.Object);
    Code:
       0: aload_0
       1: aload_1
       2: checkcast     #10                 // class rpg/cake2/NodesTraits$Node
       5: aload_2
       6: checkcast     #10                 // class rpg/cake2/NodesTraits$Node
       9: invokevirtual #69                 // Method apply:(Lrpg/cake2/NodesTraits$Node;Lrpg/cake2/NodesTraits$Node;)Lrpg/cake2/StrNodes$StrTree;
      12: areturn

  public rpg.cake2.StrNodes$StrTree$(rpg.cake2.NodesTraits);
    Code:
       0: aload_1
       1: ifnonnull     6
       4: aconst_null
       5: athrow
       6: aload_0
       7: aload_1
       8: putfield      #32                 // Field $outer:Lrpg/cake2/NodesTraits;
      11: aload_0
      12: invokespecial #74                 // Method scala/runtime/AbstractFunction2."<init>":()V
      15: return
}
