Classfile /home/krzysiek/workspace/scala-bcode-cutter/pref/target/scala-2.12/classes/rpg/patmat/WisTree.class
  Last modified Apr 8, 2018; size 4745 bytes
  MD5 checksum 93cc18fb7349123966da6747996eb9a8
  Compiled from "PatMatSkillTrees.scala"
public class rpg.patmat.WisTree implements rpg.patmat.Node,scala.Product,scala.Serializable
  minor version: 0
  major version: 52
  flags: ACC_PUBLIC, ACC_SUPER
Constant pool:
    #1 = Utf8               rpg/patmat/WisTree
    #2 = Class              #1            // rpg/patmat/WisTree
    #3 = Utf8               java/lang/Object
    #4 = Class              #3            // java/lang/Object
    #5 = Utf8               rpg/patmat/Node
    #6 = Class              #5            // rpg/patmat/Node
    #7 = Utf8               scala/Product
    #8 = Class              #7            // scala/Product
    #9 = Utf8               scala/Serializable
   #10 = Class              #9            // scala/Serializable
   #11 = Utf8               PatMatSkillTrees.scala
   #12 = Utf8               Lscala/reflect/ScalaSignature;
   #13 = Utf8               bytes
   #14 = Utf8               bBqaV5t)J,WM\t1/;nCRT!BeB<7A\n!q!#\t1iA)1oY1mC&QB:L(+4=R\"\nE!(pI\"!C\n\nQQ!a)s_,8\r\tYI!aM+'/[1mSj'\r\3\te!Q3Ai\tA\3giV\ta\tE\t!aWM;!!qA!f\nQ!:jO\"$#\rILw\r;!\"$aN\5u}QA%\n=\"B\r\"q\"\"qb%\t!KG>F%U-Bq!GaCOA\t\t5!C]q1m9zI,g-Y;mi\nT#A+94&AI:T\"AQ*!C;oG\",7m[3e\t1$\"b]:|G/;j_:L!O#Ut7\r[3dW$g+:jC:W\rC;EI\r|/eKW;%e!9AAA\nj!9s_,8\r)sKL0F?!\tyD)DA\t\t%)mC:<'\"A\"\t)g/Yaa;sS:<bB$%\tS\raJ|G-^2uJLG/_BBS*1!8ui!!A9a:pIVG/7f[tGP%BU#*1!8zF*!AA%12)!!ABYq:pIVG/;fe$xN]/BlW(eS!A\r|G\3di&|g.]3\nA\n^3sCR|'C_IA0\rg.R9vC2$\"Y2%\tB2un7fC:DqaU/q\nCfI\t4!7[\"pI$!Q\t\t\"j!!xn;sS:<G# \t-!C!Y1Q-];bYN$\"Y7\tMS!a9qNAAaB,jgRX-\tE4q!#!oErgVR^<j!m*\tqA];oi&lW-yk\n\tIY:ueGOR;oGRLwN\t\t\nH>ADq[9C~cI@\=\tz3q\rA=q\rA\n\t!CA\tq!8baBd\nU#B=bAA\t1q\n;j_:R!CA\t9I1!a!V7fe!IqCA\rJq\"CAcIBA-X-3SKN|GN^3}cA \"%1!\r='.Z2u
   #15 = Utf8               left
   #16 = Utf8               Lrpg/patmat/Node;
   #17 = Utf8               right
   #18 = Utf8               unapply
   #19 = Utf8               (Lrpg/patmat/WisTree;)Lscala/Option;
   #20 = Utf8               rpg/patmat/WisTree$
   #21 = Class              #20           // rpg/patmat/WisTree$
   #22 = Utf8               MODULE$
   #23 = Utf8               Lrpg/patmat/WisTree$;
   #24 = NameAndType        #22:#23       // MODULE$:Lrpg/patmat/WisTree$;
   #25 = Fieldref           #21.#24       // rpg/patmat/WisTree$.MODULE$:Lrpg/patmat/WisTree$;
   #26 = NameAndType        #18:#19       // unapply:(Lrpg/patmat/WisTree;)Lscala/Option;
   #27 = Methodref          #21.#26       // rpg/patmat/WisTree$.unapply:(Lrpg/patmat/WisTree;)Lscala/Option;
   #28 = Utf8               apply
   #29 = Utf8               (Lrpg/patmat/Node;Lrpg/patmat/Node;)Lrpg/patmat/WisTree;
   #30 = NameAndType        #28:#29       // apply:(Lrpg/patmat/Node;Lrpg/patmat/Node;)Lrpg/patmat/WisTree;
   #31 = Methodref          #21.#30       // rpg/patmat/WisTree$.apply:(Lrpg/patmat/Node;Lrpg/patmat/Node;)Lrpg/patmat/WisTree;
   #32 = Utf8               tupled
   #33 = Utf8               ()Lscala/Function1;
   #34 = NameAndType        #32:#33       // tupled:()Lscala/Function1;
   #35 = Methodref          #21.#34       // rpg/patmat/WisTree$.tupled:()Lscala/Function1;
   #36 = Utf8               curried
   #37 = NameAndType        #36:#33       // curried:()Lscala/Function1;
   #38 = Methodref          #21.#37       // rpg/patmat/WisTree$.curried:()Lscala/Function1;
   #39 = Utf8               ()Lrpg/patmat/Node;
   #40 = NameAndType        #15:#16       // left:Lrpg/patmat/Node;
   #41 = Fieldref           #2.#40        // rpg/patmat/WisTree.left:Lrpg/patmat/Node;
   #42 = Utf8               this
   #43 = Utf8               Lrpg/patmat/WisTree;
   #44 = NameAndType        #17:#16       // right:Lrpg/patmat/Node;
   #45 = Fieldref           #2.#44        // rpg/patmat/WisTree.right:Lrpg/patmat/Node;
   #46 = Utf8               copy
   #47 = Utf8               <init>
   #48 = Utf8               (Lrpg/patmat/Node;Lrpg/patmat/Node;)V
   #49 = NameAndType        #47:#48       // "<init>":(Lrpg/patmat/Node;Lrpg/patmat/Node;)V
   #50 = Methodref          #2.#49        // rpg/patmat/WisTree."<init>":(Lrpg/patmat/Node;Lrpg/patmat/Node;)V
   #51 = Utf8               copy$default$1
   #52 = NameAndType        #15:#39       // left:()Lrpg/patmat/Node;
   #53 = Methodref          #2.#52        // rpg/patmat/WisTree.left:()Lrpg/patmat/Node;
   #54 = Utf8               copy$default$2
   #55 = NameAndType        #17:#39       // right:()Lrpg/patmat/Node;
   #56 = Methodref          #2.#55        // rpg/patmat/WisTree.right:()Lrpg/patmat/Node;
   #57 = Utf8               productPrefix
   #58 = Utf8               ()Ljava/lang/String;
   #59 = Utf8               WisTree
   #60 = String             #59           // WisTree
   #61 = Utf8               productArity
   #62 = Utf8               ()I
   #63 = Utf8               productElement
   #64 = Utf8               (I)Ljava/lang/Object;
   #65 = Utf8               x$1
   #66 = Utf8               java/lang/IndexOutOfBoundsException
   #67 = Class              #66           // java/lang/IndexOutOfBoundsException
   #68 = Utf8               scala/runtime/BoxesRunTime
   #69 = Class              #68           // scala/runtime/BoxesRunTime
   #70 = Utf8               boxToInteger
   #71 = Utf8               (I)Ljava/lang/Integer;
   #72 = NameAndType        #70:#71       // boxToInteger:(I)Ljava/lang/Integer;
   #73 = Methodref          #69.#72       // scala/runtime/BoxesRunTime.boxToInteger:(I)Ljava/lang/Integer;
   #74 = Utf8               toString
   #75 = NameAndType        #74:#58       // toString:()Ljava/lang/String;
   #76 = Methodref          #4.#75        // java/lang/Object.toString:()Ljava/lang/String;
   #77 = Utf8               (Ljava/lang/String;)V
   #78 = NameAndType        #47:#77       // "<init>":(Ljava/lang/String;)V
   #79 = Methodref          #67.#78       // java/lang/IndexOutOfBoundsException."<init>":(Ljava/lang/String;)V
   #80 = Utf8               I
   #81 = Utf8               productIterator
   #82 = Utf8               ()Lscala/collection/Iterator;
   #83 = Utf8               scala/runtime/ScalaRunTime$
   #84 = Class              #83           // scala/runtime/ScalaRunTime$
   #85 = Utf8               Lscala/runtime/ScalaRunTime$;
   #86 = NameAndType        #22:#85       // MODULE$:Lscala/runtime/ScalaRunTime$;
   #87 = Fieldref           #84.#86       // scala/runtime/ScalaRunTime$.MODULE$:Lscala/runtime/ScalaRunTime$;
   #88 = Utf8               typedProductIterator
   #89 = Utf8               (Lscala/Product;)Lscala/collection/Iterator;
   #90 = NameAndType        #88:#89       // typedProductIterator:(Lscala/Product;)Lscala/collection/Iterator;
   #91 = Methodref          #84.#90       // scala/runtime/ScalaRunTime$.typedProductIterator:(Lscala/Product;)Lscala/collection/Iterator;
   #92 = Utf8               canEqual
   #93 = Utf8               (Ljava/lang/Object;)Z
   #94 = Utf8               Ljava/lang/Object;
   #95 = Utf8               hashCode
   #96 = Utf8               _hashCode
   #97 = Utf8               (Lscala/Product;)I
   #98 = NameAndType        #96:#97       // _hashCode:(Lscala/Product;)I
   #99 = Methodref          #84.#98       // scala/runtime/ScalaRunTime$._hashCode:(Lscala/Product;)I
  #100 = Utf8               _toString
  #101 = Utf8               (Lscala/Product;)Ljava/lang/String;
  #102 = NameAndType        #100:#101     // _toString:(Lscala/Product;)Ljava/lang/String;
  #103 = Methodref          #84.#102      // scala/runtime/ScalaRunTime$._toString:(Lscala/Product;)Ljava/lang/String;
  #104 = Utf8               equals
  #105 = NameAndType        #104:#93      // equals:(Ljava/lang/Object;)Z
  #106 = Methodref          #4.#105       // java/lang/Object.equals:(Ljava/lang/Object;)Z
  #107 = NameAndType        #92:#93       // canEqual:(Ljava/lang/Object;)Z
  #108 = Methodref          #2.#107       // rpg/patmat/WisTree.canEqual:(Ljava/lang/Object;)Z
  #109 = Utf8               ()V
  #110 = NameAndType        #47:#109      // "<init>":()V
  #111 = Methodref          #4.#110       // java/lang/Object."<init>":()V
  #112 = Utf8               $init$
  #113 = Utf8               (Lscala/Product;)V
  #114 = NameAndType        #112:#113     // $init$:(Lscala/Product;)V
  #115 = InterfaceMethodref #8.#114       // scala/Product.$init$:(Lscala/Product;)V
  #116 = Utf8               Code
  #117 = Utf8               Signature
  #118 = Utf8               (Lrpg/patmat/WisTree;)Lscala/Option<Lscala/Tuple2<Lrpg/patmat/Node;Lrpg/patmat/Node;>;>;
  #119 = Utf8               ()Lscala/Function1<Lscala/Tuple2<Lrpg/patmat/Node;Lrpg/patmat/Node;>;Lrpg/patmat/WisTree;>;
  #120 = Utf8               ()Lscala/Function1<Lrpg/patmat/Node;Lscala/Function1<Lrpg/patmat/Node;Lrpg/patmat/WisTree;>;>;
  #121 = Utf8               LocalVariableTable
  #122 = Utf8               LineNumberTable
  #123 = Utf8               MethodParameters
  #124 = Utf8               StackMapTable
  #125 = Utf8               ()Lscala/collection/Iterator<Ljava/lang/Object;>;
  #126 = Utf8               SourceFile
  #127 = Utf8               RuntimeVisibleAnnotations
  #128 = Utf8               ScalaInlineInfo
  #129 = Utf8               ScalaSig
{
  private final rpg.patmat.Node left;
    descriptor: Lrpg/patmat/Node;
    flags: ACC_PRIVATE, ACC_FINAL

  private final rpg.patmat.Node right;
    descriptor: Lrpg/patmat/Node;
    flags: ACC_PRIVATE, ACC_FINAL

  public static scala.Option<scala.Tuple2<rpg.patmat.Node, rpg.patmat.Node>> unapply(rpg.patmat.WisTree);
    descriptor: (Lrpg/patmat/WisTree;)Lscala/Option;
    flags: ACC_PUBLIC, ACC_STATIC
    Code:
      stack=2, locals=1, args_size=1
         0: getstatic     #25                 // Field rpg/patmat/WisTree$.MODULE$:Lrpg/patmat/WisTree$;
         3: aload_0
         4: invokevirtual #27                 // Method rpg/patmat/WisTree$.unapply:(Lrpg/patmat/WisTree;)Lscala/Option;
         7: areturn
    Signature: #118                         // (Lrpg/patmat/WisTree;)Lscala/Option<Lscala/Tuple2<Lrpg/patmat/Node;Lrpg/patmat/Node;>;>;

  public static rpg.patmat.WisTree apply(rpg.patmat.Node, rpg.patmat.Node);
    descriptor: (Lrpg/patmat/Node;Lrpg/patmat/Node;)Lrpg/patmat/WisTree;
    flags: ACC_PUBLIC, ACC_STATIC
    Code:
      stack=3, locals=2, args_size=2
         0: getstatic     #25                 // Field rpg/patmat/WisTree$.MODULE$:Lrpg/patmat/WisTree$;
         3: aload_0
         4: aload_1
         5: invokevirtual #31                 // Method rpg/patmat/WisTree$.apply:(Lrpg/patmat/Node;Lrpg/patmat/Node;)Lrpg/patmat/WisTree;
         8: areturn

  public static scala.Function1<scala.Tuple2<rpg.patmat.Node, rpg.patmat.Node>, rpg.patmat.WisTree> tupled();
    descriptor: ()Lscala/Function1;
    flags: ACC_PUBLIC, ACC_STATIC
    Code:
      stack=1, locals=0, args_size=0
         0: getstatic     #25                 // Field rpg/patmat/WisTree$.MODULE$:Lrpg/patmat/WisTree$;
         3: invokevirtual #35                 // Method rpg/patmat/WisTree$.tupled:()Lscala/Function1;
         6: areturn
    Signature: #119                         // ()Lscala/Function1<Lscala/Tuple2<Lrpg/patmat/Node;Lrpg/patmat/Node;>;Lrpg/patmat/WisTree;>;

  public static scala.Function1<rpg.patmat.Node, scala.Function1<rpg.patmat.Node, rpg.patmat.WisTree>> curried();
    descriptor: ()Lscala/Function1;
    flags: ACC_PUBLIC, ACC_STATIC
    Code:
      stack=1, locals=0, args_size=0
         0: getstatic     #25                 // Field rpg/patmat/WisTree$.MODULE$:Lrpg/patmat/WisTree$;
         3: invokevirtual #38                 // Method rpg/patmat/WisTree$.curried:()Lscala/Function1;
         6: areturn
    Signature: #120                         // ()Lscala/Function1<Lrpg/patmat/Node;Lscala/Function1<Lrpg/patmat/Node;Lrpg/patmat/WisTree;>;>;

  public rpg.patmat.Node left();
    descriptor: ()Lrpg/patmat/Node;
    flags: ACC_PUBLIC
    Code:
      stack=1, locals=1, args_size=1
         0: aload_0
         1: getfield      #41                 // Field left:Lrpg/patmat/Node;
         4: areturn
      LocalVariableTable:
        Start  Length  Slot  Name   Signature
            0       5     0  this   Lrpg/patmat/WisTree;
      LineNumberTable:
        line 10: 0

  public rpg.patmat.Node right();
    descriptor: ()Lrpg/patmat/Node;
    flags: ACC_PUBLIC
    Code:
      stack=1, locals=1, args_size=1
         0: aload_0
         1: getfield      #45                 // Field right:Lrpg/patmat/Node;
         4: areturn
      LocalVariableTable:
        Start  Length  Slot  Name   Signature
            0       5     0  this   Lrpg/patmat/WisTree;
      LineNumberTable:
        line 10: 0

  public rpg.patmat.WisTree copy(rpg.patmat.Node, rpg.patmat.Node);
    descriptor: (Lrpg/patmat/Node;Lrpg/patmat/Node;)Lrpg/patmat/WisTree;
    flags: ACC_PUBLIC
    Code:
      stack=4, locals=3, args_size=3
         0: new           #2                  // class rpg/patmat/WisTree
         3: dup
         4: aload_1
         5: aload_2
         6: invokespecial #50                 // Method "<init>":(Lrpg/patmat/Node;Lrpg/patmat/Node;)V
         9: areturn
      LocalVariableTable:
        Start  Length  Slot  Name   Signature
            0      10     0  this   Lrpg/patmat/WisTree;
            0      10     1  left   Lrpg/patmat/Node;
            0      10     2 right   Lrpg/patmat/Node;
      LineNumberTable:
        line 10: 0
    MethodParameters:
      Name                           Flags
      left                           final
      right                          final

  public rpg.patmat.Node copy$default$1();
    descriptor: ()Lrpg/patmat/Node;
    flags: ACC_PUBLIC
    Code:
      stack=1, locals=1, args_size=1
         0: aload_0
         1: invokevirtual #53                 // Method left:()Lrpg/patmat/Node;
         4: areturn
      LocalVariableTable:
        Start  Length  Slot  Name   Signature
            0       5     0  this   Lrpg/patmat/WisTree;
      LineNumberTable:
        line 10: 0

  public rpg.patmat.Node copy$default$2();
    descriptor: ()Lrpg/patmat/Node;
    flags: ACC_PUBLIC
    Code:
      stack=1, locals=1, args_size=1
         0: aload_0
         1: invokevirtual #56                 // Method right:()Lrpg/patmat/Node;
         4: areturn
      LocalVariableTable:
        Start  Length  Slot  Name   Signature
            0       5     0  this   Lrpg/patmat/WisTree;
      LineNumberTable:
        line 10: 0

  public java.lang.String productPrefix();
    descriptor: ()Ljava/lang/String;
    flags: ACC_PUBLIC
    Code:
      stack=1, locals=1, args_size=1
         0: ldc           #60                 // String WisTree
         2: areturn
      LocalVariableTable:
        Start  Length  Slot  Name   Signature
            0       3     0  this   Lrpg/patmat/WisTree;
      LineNumberTable:
        line 10: 0

  public int productArity();
    descriptor: ()I
    flags: ACC_PUBLIC
    Code:
      stack=1, locals=1, args_size=1
         0: iconst_2
         1: ireturn
      LocalVariableTable:
        Start  Length  Slot  Name   Signature
            0       2     0  this   Lrpg/patmat/WisTree;
      LineNumberTable:
        line 10: 0

  public java.lang.Object productElement(int);
    descriptor: (I)Ljava/lang/Object;
    flags: ACC_PUBLIC
    Code:
      stack=3, locals=3, args_size=2
         0: iload_1
         1: istore_2
         2: iload_2
         3: tableswitch   { // 0 to 1
                       0: 24
                       1: 31
                 default: 38
            }
        24: aload_0
        25: invokevirtual #53                 // Method left:()Lrpg/patmat/Node;
        28: goto          53
        31: aload_0
        32: invokevirtual #56                 // Method right:()Lrpg/patmat/Node;
        35: goto          53
        38: new           #67                 // class java/lang/IndexOutOfBoundsException
        41: dup
        42: iload_1
        43: invokestatic  #73                 // Method scala/runtime/BoxesRunTime.boxToInteger:(I)Ljava/lang/Integer;
        46: invokevirtual #76                 // Method java/lang/Object.toString:()Ljava/lang/String;
        49: invokespecial #79                 // Method java/lang/IndexOutOfBoundsException."<init>":(Ljava/lang/String;)V
        52: athrow
        53: areturn
      LocalVariableTable:
        Start  Length  Slot  Name   Signature
            0      54     0  this   Lrpg/patmat/WisTree;
            0      54     1   x$1   I
      LineNumberTable:
        line 10: 0
      StackMapTable: number_of_entries = 4
        frame_type = 252 /* append */
          offset_delta = 24
          locals = [ int ]
        frame_type = 6 /* same */
        frame_type = 6 /* same */
        frame_type = 78 /* same_locals_1_stack_item */
          stack = [ class rpg/patmat/Node ]
    MethodParameters:
      Name                           Flags
      x$1                            final

  public scala.collection.Iterator<java.lang.Object> productIterator();
    descriptor: ()Lscala/collection/Iterator;
    flags: ACC_PUBLIC
    Code:
      stack=2, locals=1, args_size=1
         0: getstatic     #87                 // Field scala/runtime/ScalaRunTime$.MODULE$:Lscala/runtime/ScalaRunTime$;
         3: aload_0
         4: invokevirtual #91                 // Method scala/runtime/ScalaRunTime$.typedProductIterator:(Lscala/Product;)Lscala/collection/Iterator;
         7: areturn
      LocalVariableTable:
        Start  Length  Slot  Name   Signature
            0       8     0  this   Lrpg/patmat/WisTree;
      LineNumberTable:
        line 10: 0
    Signature: #125                         // ()Lscala/collection/Iterator<Ljava/lang/Object;>;

  public boolean canEqual(java.lang.Object);
    descriptor: (Ljava/lang/Object;)Z
    flags: ACC_PUBLIC
    Code:
      stack=1, locals=2, args_size=2
         0: aload_1
         1: instanceof    #2                  // class rpg/patmat/WisTree
         4: ireturn
      LocalVariableTable:
        Start  Length  Slot  Name   Signature
            0       5     0  this   Lrpg/patmat/WisTree;
            0       5     1   x$1   Ljava/lang/Object;
      LineNumberTable:
        line 10: 0
    MethodParameters:
      Name                           Flags
      x$1                            final

  public int hashCode();
    descriptor: ()I
    flags: ACC_PUBLIC
    Code:
      stack=2, locals=1, args_size=1
         0: getstatic     #87                 // Field scala/runtime/ScalaRunTime$.MODULE$:Lscala/runtime/ScalaRunTime$;
         3: aload_0
         4: invokevirtual #99                 // Method scala/runtime/ScalaRunTime$._hashCode:(Lscala/Product;)I
         7: ireturn
      LocalVariableTable:
        Start  Length  Slot  Name   Signature
            0       8     0  this   Lrpg/patmat/WisTree;
      LineNumberTable:
        line 10: 0

  public java.lang.String toString();
    descriptor: ()Ljava/lang/String;
    flags: ACC_PUBLIC
    Code:
      stack=2, locals=1, args_size=1
         0: getstatic     #87                 // Field scala/runtime/ScalaRunTime$.MODULE$:Lscala/runtime/ScalaRunTime$;
         3: aload_0
         4: invokevirtual #103                // Method scala/runtime/ScalaRunTime$._toString:(Lscala/Product;)Ljava/lang/String;
         7: areturn
      LocalVariableTable:
        Start  Length  Slot  Name   Signature
            0       8     0  this   Lrpg/patmat/WisTree;
      LineNumberTable:
        line 10: 0

  public boolean equals(java.lang.Object);
    descriptor: (Ljava/lang/Object;)Z
    flags: ACC_PUBLIC
    Code:
      stack=2, locals=7, args_size=2
         0: aload_0
         1: aload_1
         2: if_acmpeq     118
         5: aload_1
         6: astore_3
         7: aload_3
         8: instanceof    #2                  // class rpg/patmat/WisTree
        11: ifeq          19
        14: iconst_1
        15: istore_2
        16: goto          27
        19: goto          22
        22: iconst_0
        23: istore_2
        24: goto          27
        27: iload_2
        28: ifeq          122
        31: aload_1
        32: checkcast     #2                  // class rpg/patmat/WisTree
        35: astore        4
        37: aload_0
        38: invokevirtual #53                 // Method left:()Lrpg/patmat/Node;
        41: aload         4
        43: invokevirtual #53                 // Method left:()Lrpg/patmat/Node;
        46: astore        5
        48: dup
        49: ifnonnull     61
        52: pop
        53: aload         5
        55: ifnull        69
        58: goto          114
        61: aload         5
        63: invokevirtual #106                // Method java/lang/Object.equals:(Ljava/lang/Object;)Z
        66: ifeq          114
        69: aload_0
        70: invokevirtual #56                 // Method right:()Lrpg/patmat/Node;
        73: aload         4
        75: invokevirtual #56                 // Method right:()Lrpg/patmat/Node;
        78: astore        6
        80: dup
        81: ifnonnull     93
        84: pop
        85: aload         6
        87: ifnull        101
        90: goto          114
        93: aload         6
        95: invokevirtual #106                // Method java/lang/Object.equals:(Ljava/lang/Object;)Z
        98: ifeq          114
       101: aload         4
       103: aload_0
       104: invokevirtual #108                // Method canEqual:(Ljava/lang/Object;)Z
       107: ifeq          114
       110: iconst_1
       111: goto          115
       114: iconst_0
       115: ifeq          122
       118: iconst_1
       119: goto          123
       122: iconst_0
       123: ireturn
      LocalVariableTable:
        Start  Length  Slot  Name   Signature
            0     124     0  this   Lrpg/patmat/WisTree;
            0     124     1   x$1   Ljava/lang/Object;
      LineNumberTable:
        line 10: 0
      StackMapTable: number_of_entries = 12
        frame_type = 253 /* append */
          offset_delta = 19
          locals = [ top, class java/lang/Object ]
        frame_type = 2 /* same */
        frame_type = 255 /* full_frame */
          offset_delta = 4
          locals = [ class rpg/patmat/WisTree, class java/lang/Object, int, class java/lang/Object ]
          stack = []
        frame_type = 255 /* full_frame */
          offset_delta = 33
          locals = [ class rpg/patmat/WisTree, class java/lang/Object, int, class java/lang/Object, class rpg/patmat/WisTree, class rpg/patmat/Node ]
          stack = [ class rpg/patmat/Node ]
        frame_type = 7 /* same */
        frame_type = 255 /* full_frame */
          offset_delta = 23
          locals = [ class rpg/patmat/WisTree, class java/lang/Object, int, class java/lang/Object, class rpg/patmat/WisTree, class rpg/patmat/Node, class rpg/patmat/Node ]
          stack = [ class rpg/patmat/Node ]
        frame_type = 7 /* same */
        frame_type = 250 /* chop */
          offset_delta = 12
        frame_type = 64 /* same_locals_1_stack_item */
          stack = [ int ]
        frame_type = 255 /* full_frame */
          offset_delta = 2
          locals = [ class rpg/patmat/WisTree, class java/lang/Object ]
          stack = []
        frame_type = 253 /* append */
          offset_delta = 3
          locals = [ int, class java/lang/Object ]
        frame_type = 255 /* full_frame */
          offset_delta = 0
          locals = [ class rpg/patmat/WisTree, class java/lang/Object ]
          stack = [ int ]
    MethodParameters:
      Name                           Flags
      x$1                            final

  public rpg.patmat.WisTree(rpg.patmat.Node, rpg.patmat.Node);
    descriptor: (Lrpg/patmat/Node;Lrpg/patmat/Node;)V
    flags: ACC_PUBLIC
    Code:
      stack=2, locals=3, args_size=3
         0: aload_0
         1: aload_1
         2: putfield      #41                 // Field left:Lrpg/patmat/Node;
         5: aload_0
         6: aload_2
         7: putfield      #45                 // Field right:Lrpg/patmat/Node;
        10: aload_0
        11: invokespecial #111                // Method java/lang/Object."<init>":()V
        14: aload_0
        15: invokestatic  #115                // InterfaceMethod scala/Product.$init$:(Lscala/Product;)V
        18: return
      LocalVariableTable:
        Start  Length  Slot  Name   Signature
            0      19     0  this   Lrpg/patmat/WisTree;
            0      19     1  left   Lrpg/patmat/Node;
            0      19     2 right   Lrpg/patmat/Node;
      LineNumberTable:
        line 10: 0
    MethodParameters:
      Name                           Flags
      left                           final
      right                          final
}
SourceFile: "PatMatSkillTrees.scala"
RuntimeVisibleAnnotations:
  0: #12(#13=s#14)
Error: unknown attribute
  ScalaInlineInfo: length = 0x4A
   01 00 00 0E 00 2F 00 30 00 00 5C 00 5D 00 00 33
   00 27 00 00 36 00 27 00 00 2E 00 1D 00 00 68 00
   5D 00 00 5F 00 3E 00 00 0F 00 27 00 00 3D 00 3E
   00 00 3F 00 40 00 00 51 00 52 00 00 39 00 3A 00
   00 11 00 27 00 00 4A 00 3A 00
Error: unknown attribute
  ScalaSig: length = 0x3
   05 00 00
