Classfile /home/krzysiek/workspace/scala-bcode-cutter/pref/target/scala-2.12/classes/rpg/patmat/steppedClass/StrStep.class
  Last modified Apr 8, 2018; size 4559 bytes
  MD5 checksum 5685508fa910a3cfbc94880d99130f39
  Compiled from "PatMatSkillTrees.scala"
public class rpg.patmat.steppedClass.StrStep extends rpg.patmat.steppedClass.Step implements scala.Product,scala.Serializable
  minor version: 0
  major version: 52
  flags: ACC_PUBLIC, ACC_SUPER
Constant pool:
    #1 = Utf8               rpg/patmat/steppedClass/StrStep
    #2 = Class              #1            // rpg/patmat/steppedClass/StrStep
    #3 = Utf8               rpg/patmat/steppedClass/Step
    #4 = Class              #3            // rpg/patmat/steppedClass/Step
    #5 = Utf8               scala/Product
    #6 = Class              #5            // scala/Product
    #7 = Utf8               scala/Serializable
    #8 = Class              #7            // scala/Serializable
    #9 = Utf8               PatMatSkillTrees.scala
   #10 = Utf8               Lscala/reflect/ScalaSignature;
   #11 = Utf8               bytes
   #12 = Utf8               EaB&qa;s'R,O\ta1^3qa$7\t\1tg*QABa$X.;\t1A9hB)A1D%QB'R,%5\tCC8-7b\tCAQe>$Wo;=)B1VM]5bY&TM7f!AA!f\nIA;p+QCA\ta\"AO_,#Q|C!%=S:LGOE\r\"a\tay\t!CM!1m9z)\tsCIA\t\t%!CUq1m9zI,g-Y;mi\nT#A+ia3&A9T\"AA\n!C;oG\",7m[3e\t#b]:|G/;j_:L!N#Ut7\r[3dW$g+:jC:W\rC7IIAxZ;diBXMZ5y+ACA?Q$BA=aM\4u\nAA[1wC&qH'RN\4\t!CaO]8ek$I]5usV\t1\t\t&Q\t:$bB$%\tSaJ|G-^2u2,W.8u)\tIE\n&1\n:LbB'G\raQq\nbB(%\tUaJ|G-^2uR,'/;peV\tES+&ka)B\t!bY8mYG/[8o\t16KJi\r^8sA!!AebY1oF,\r5v\"aD.\nq\"a\"p_2,M^\t1Jy!!AB[1tQ{G-\"9!\rAA\n;p'RN\4aBq!c-fcVGn5Dq!3jBj\t6M#(o;faB1b\t\t\t#m'\rYW\t]FT\"%Dp\t#Ask:$.\3\nI|'!E!cgRm;Gk:G/[8oc!)eCiR\t!CcWIQI2\t]\!CAq)\r9msR!%1Y\rAw.\t\"!})h.9qYf$2!`A!\ryaPGBaa9uS>tCAu\ta$C-\t\"\nY!/Z1e%x<f)\t\tYE:I1!a;y%M[3di
   #13 = Utf8               to
   #14 = Utf8               Lrpg/patmat/steppedClass/Node;
   #15 = Utf8               unapply
   #16 = Utf8               (Lrpg/patmat/steppedClass/StrStep;)Lscala/Option;
   #17 = Utf8               rpg/patmat/steppedClass/StrStep$
   #18 = Class              #17           // rpg/patmat/steppedClass/StrStep$
   #19 = Utf8               MODULE$
   #20 = Utf8               Lrpg/patmat/steppedClass/StrStep$;
   #21 = NameAndType        #19:#20       // MODULE$:Lrpg/patmat/steppedClass/StrStep$;
   #22 = Fieldref           #18.#21       // rpg/patmat/steppedClass/StrStep$.MODULE$:Lrpg/patmat/steppedClass/StrStep$;
   #23 = NameAndType        #15:#16       // unapply:(Lrpg/patmat/steppedClass/StrStep;)Lscala/Option;
   #24 = Methodref          #18.#23       // rpg/patmat/steppedClass/StrStep$.unapply:(Lrpg/patmat/steppedClass/StrStep;)Lscala/Option;
   #25 = Utf8               apply
   #26 = Utf8               (Lrpg/patmat/steppedClass/Node;)Lrpg/patmat/steppedClass/StrStep;
   #27 = NameAndType        #25:#26       // apply:(Lrpg/patmat/steppedClass/Node;)Lrpg/patmat/steppedClass/StrStep;
   #28 = Methodref          #18.#27       // rpg/patmat/steppedClass/StrStep$.apply:(Lrpg/patmat/steppedClass/Node;)Lrpg/patmat/steppedClass/StrStep;
   #29 = Utf8               andThen
   #30 = Utf8               (Lscala/Function1;)Lscala/Function1;
   #31 = NameAndType        #29:#30       // andThen:(Lscala/Function1;)Lscala/Function1;
   #32 = Methodref          #18.#31       // rpg/patmat/steppedClass/StrStep$.andThen:(Lscala/Function1;)Lscala/Function1;
   #33 = Utf8               compose
   #34 = NameAndType        #33:#30       // compose:(Lscala/Function1;)Lscala/Function1;
   #35 = Methodref          #18.#34       // rpg/patmat/steppedClass/StrStep$.compose:(Lscala/Function1;)Lscala/Function1;
   #36 = Utf8               ()Lrpg/patmat/steppedClass/Node;
   #37 = NameAndType        #13:#14       // to:Lrpg/patmat/steppedClass/Node;
   #38 = Fieldref           #2.#37        // rpg/patmat/steppedClass/StrStep.to:Lrpg/patmat/steppedClass/Node;
   #39 = Utf8               this
   #40 = Utf8               Lrpg/patmat/steppedClass/StrStep;
   #41 = Utf8               copy
   #42 = Utf8               <init>
   #43 = Utf8               (Lrpg/patmat/steppedClass/Node;)V
   #44 = NameAndType        #42:#43       // "<init>":(Lrpg/patmat/steppedClass/Node;)V
   #45 = Methodref          #2.#44        // rpg/patmat/steppedClass/StrStep."<init>":(Lrpg/patmat/steppedClass/Node;)V
   #46 = Utf8               copy$default$1
   #47 = NameAndType        #13:#36       // to:()Lrpg/patmat/steppedClass/Node;
   #48 = Methodref          #2.#47        // rpg/patmat/steppedClass/StrStep.to:()Lrpg/patmat/steppedClass/Node;
   #49 = Utf8               productPrefix
   #50 = Utf8               ()Ljava/lang/String;
   #51 = Utf8               StrStep
   #52 = String             #51           // StrStep
   #53 = Utf8               productArity
   #54 = Utf8               ()I
   #55 = Utf8               productElement
   #56 = Utf8               (I)Ljava/lang/Object;
   #57 = Utf8               x$1
   #58 = Utf8               java/lang/IndexOutOfBoundsException
   #59 = Class              #58           // java/lang/IndexOutOfBoundsException
   #60 = Utf8               scala/runtime/BoxesRunTime
   #61 = Class              #60           // scala/runtime/BoxesRunTime
   #62 = Utf8               boxToInteger
   #63 = Utf8               (I)Ljava/lang/Integer;
   #64 = NameAndType        #62:#63       // boxToInteger:(I)Ljava/lang/Integer;
   #65 = Methodref          #61.#64       // scala/runtime/BoxesRunTime.boxToInteger:(I)Ljava/lang/Integer;
   #66 = Utf8               java/lang/Object
   #67 = Class              #66           // java/lang/Object
   #68 = Utf8               toString
   #69 = NameAndType        #68:#50       // toString:()Ljava/lang/String;
   #70 = Methodref          #67.#69       // java/lang/Object.toString:()Ljava/lang/String;
   #71 = Utf8               (Ljava/lang/String;)V
   #72 = NameAndType        #42:#71       // "<init>":(Ljava/lang/String;)V
   #73 = Methodref          #59.#72       // java/lang/IndexOutOfBoundsException."<init>":(Ljava/lang/String;)V
   #74 = Utf8               I
   #75 = Utf8               rpg/patmat/steppedClass/Node
   #76 = Class              #75           // rpg/patmat/steppedClass/Node
   #77 = Utf8               productIterator
   #78 = Utf8               ()Lscala/collection/Iterator;
   #79 = Utf8               scala/runtime/ScalaRunTime$
   #80 = Class              #79           // scala/runtime/ScalaRunTime$
   #81 = Utf8               Lscala/runtime/ScalaRunTime$;
   #82 = NameAndType        #19:#81       // MODULE$:Lscala/runtime/ScalaRunTime$;
   #83 = Fieldref           #80.#82       // scala/runtime/ScalaRunTime$.MODULE$:Lscala/runtime/ScalaRunTime$;
   #84 = Utf8               typedProductIterator
   #85 = Utf8               (Lscala/Product;)Lscala/collection/Iterator;
   #86 = NameAndType        #84:#85       // typedProductIterator:(Lscala/Product;)Lscala/collection/Iterator;
   #87 = Methodref          #80.#86       // scala/runtime/ScalaRunTime$.typedProductIterator:(Lscala/Product;)Lscala/collection/Iterator;
   #88 = Utf8               canEqual
   #89 = Utf8               (Ljava/lang/Object;)Z
   #90 = Utf8               Ljava/lang/Object;
   #91 = Utf8               hashCode
   #92 = Utf8               _hashCode
   #93 = Utf8               (Lscala/Product;)I
   #94 = NameAndType        #92:#93       // _hashCode:(Lscala/Product;)I
   #95 = Methodref          #80.#94       // scala/runtime/ScalaRunTime$._hashCode:(Lscala/Product;)I
   #96 = Utf8               _toString
   #97 = Utf8               (Lscala/Product;)Ljava/lang/String;
   #98 = NameAndType        #96:#97       // _toString:(Lscala/Product;)Ljava/lang/String;
   #99 = Methodref          #80.#98       // scala/runtime/ScalaRunTime$._toString:(Lscala/Product;)Ljava/lang/String;
  #100 = Utf8               equals
  #101 = NameAndType        #100:#89      // equals:(Ljava/lang/Object;)Z
  #102 = Methodref          #67.#101      // java/lang/Object.equals:(Ljava/lang/Object;)Z
  #103 = NameAndType        #88:#89       // canEqual:(Ljava/lang/Object;)Z
  #104 = Methodref          #2.#103       // rpg/patmat/steppedClass/StrStep.canEqual:(Ljava/lang/Object;)Z
  #105 = Utf8               ()V
  #106 = NameAndType        #42:#105      // "<init>":()V
  #107 = Methodref          #4.#106       // rpg/patmat/steppedClass/Step."<init>":()V
  #108 = Utf8               $init$
  #109 = Utf8               (Lscala/Product;)V
  #110 = NameAndType        #108:#109     // $init$:(Lscala/Product;)V
  #111 = InterfaceMethodref #6.#110       // scala/Product.$init$:(Lscala/Product;)V
  #112 = Utf8               Code
  #113 = Utf8               Signature
  #114 = Utf8               (Lrpg/patmat/steppedClass/StrStep;)Lscala/Option<Lrpg/patmat/steppedClass/Node;>;
  #115 = Utf8               <A:Ljava/lang/Object;>(Lscala/Function1<Lrpg/patmat/steppedClass/StrStep;TA;>;)Lscala/Function1<Lrpg/patmat/steppedClass/Node;TA;>;
  #116 = Utf8               <A:Ljava/lang/Object;>(Lscala/Function1<TA;Lrpg/patmat/steppedClass/Node;>;)Lscala/Function1<TA;Lrpg/patmat/steppedClass/StrStep;>;
  #117 = Utf8               LocalVariableTable
  #118 = Utf8               LineNumberTable
  #119 = Utf8               MethodParameters
  #120 = Utf8               StackMapTable
  #121 = Utf8               ()Lscala/collection/Iterator<Ljava/lang/Object;>;
  #122 = Utf8               SourceFile
  #123 = Utf8               RuntimeVisibleAnnotations
  #124 = Utf8               ScalaInlineInfo
  #125 = Utf8               ScalaSig
{
  private final rpg.patmat.steppedClass.Node to;
    descriptor: Lrpg/patmat/steppedClass/Node;
    flags: ACC_PRIVATE, ACC_FINAL

  public static scala.Option<rpg.patmat.steppedClass.Node> unapply(rpg.patmat.steppedClass.StrStep);
    descriptor: (Lrpg/patmat/steppedClass/StrStep;)Lscala/Option;
    flags: ACC_PUBLIC, ACC_STATIC
    Code:
      stack=2, locals=1, args_size=1
         0: getstatic     #22                 // Field rpg/patmat/steppedClass/StrStep$.MODULE$:Lrpg/patmat/steppedClass/StrStep$;
         3: aload_0
         4: invokevirtual #24                 // Method rpg/patmat/steppedClass/StrStep$.unapply:(Lrpg/patmat/steppedClass/StrStep;)Lscala/Option;
         7: areturn
    Signature: #114                         // (Lrpg/patmat/steppedClass/StrStep;)Lscala/Option<Lrpg/patmat/steppedClass/Node;>;

  public static rpg.patmat.steppedClass.StrStep apply(rpg.patmat.steppedClass.Node);
    descriptor: (Lrpg/patmat/steppedClass/Node;)Lrpg/patmat/steppedClass/StrStep;
    flags: ACC_PUBLIC, ACC_STATIC
    Code:
      stack=2, locals=1, args_size=1
         0: getstatic     #22                 // Field rpg/patmat/steppedClass/StrStep$.MODULE$:Lrpg/patmat/steppedClass/StrStep$;
         3: aload_0
         4: invokevirtual #28                 // Method rpg/patmat/steppedClass/StrStep$.apply:(Lrpg/patmat/steppedClass/Node;)Lrpg/patmat/steppedClass/StrStep;
         7: areturn

  public static <A extends java.lang.Object> scala.Function1<rpg.patmat.steppedClass.Node, A> andThen(scala.Function1<rpg.patmat.steppedClass.StrStep, A>);
    descriptor: (Lscala/Function1;)Lscala/Function1;
    flags: ACC_PUBLIC, ACC_STATIC
    Code:
      stack=2, locals=1, args_size=1
         0: getstatic     #22                 // Field rpg/patmat/steppedClass/StrStep$.MODULE$:Lrpg/patmat/steppedClass/StrStep$;
         3: aload_0
         4: invokevirtual #32                 // Method rpg/patmat/steppedClass/StrStep$.andThen:(Lscala/Function1;)Lscala/Function1;
         7: areturn
    Signature: #115                         // <A:Ljava/lang/Object;>(Lscala/Function1<Lrpg/patmat/steppedClass/StrStep;TA;>;)Lscala/Function1<Lrpg/patmat/steppedClass/Node;TA;>;

  public static <A extends java.lang.Object> scala.Function1<A, rpg.patmat.steppedClass.StrStep> compose(scala.Function1<A, rpg.patmat.steppedClass.Node>);
    descriptor: (Lscala/Function1;)Lscala/Function1;
    flags: ACC_PUBLIC, ACC_STATIC
    Code:
      stack=2, locals=1, args_size=1
         0: getstatic     #22                 // Field rpg/patmat/steppedClass/StrStep$.MODULE$:Lrpg/patmat/steppedClass/StrStep$;
         3: aload_0
         4: invokevirtual #35                 // Method rpg/patmat/steppedClass/StrStep$.compose:(Lscala/Function1;)Lscala/Function1;
         7: areturn
    Signature: #116                         // <A:Ljava/lang/Object;>(Lscala/Function1<TA;Lrpg/patmat/steppedClass/Node;>;)Lscala/Function1<TA;Lrpg/patmat/steppedClass/StrStep;>;

  public rpg.patmat.steppedClass.Node to();
    descriptor: ()Lrpg/patmat/steppedClass/Node;
    flags: ACC_PUBLIC
    Code:
      stack=1, locals=1, args_size=1
         0: aload_0
         1: getfield      #38                 // Field to:Lrpg/patmat/steppedClass/Node;
         4: areturn
      LocalVariableTable:
        Start  Length  Slot  Name   Signature
            0       5     0  this   Lrpg/patmat/steppedClass/StrStep;
      LineNumberTable:
        line 18: 0

  public rpg.patmat.steppedClass.StrStep copy(rpg.patmat.steppedClass.Node);
    descriptor: (Lrpg/patmat/steppedClass/Node;)Lrpg/patmat/steppedClass/StrStep;
    flags: ACC_PUBLIC
    Code:
      stack=3, locals=2, args_size=2
         0: new           #2                  // class rpg/patmat/steppedClass/StrStep
         3: dup
         4: aload_1
         5: invokespecial #45                 // Method "<init>":(Lrpg/patmat/steppedClass/Node;)V
         8: areturn
      LocalVariableTable:
        Start  Length  Slot  Name   Signature
            0       9     0  this   Lrpg/patmat/steppedClass/StrStep;
            0       9     1    to   Lrpg/patmat/steppedClass/Node;
      LineNumberTable:
        line 18: 0
    MethodParameters:
      Name                           Flags
      to                             final

  public rpg.patmat.steppedClass.Node copy$default$1();
    descriptor: ()Lrpg/patmat/steppedClass/Node;
    flags: ACC_PUBLIC
    Code:
      stack=1, locals=1, args_size=1
         0: aload_0
         1: invokevirtual #48                 // Method to:()Lrpg/patmat/steppedClass/Node;
         4: areturn
      LocalVariableTable:
        Start  Length  Slot  Name   Signature
            0       5     0  this   Lrpg/patmat/steppedClass/StrStep;
      LineNumberTable:
        line 18: 0

  public java.lang.String productPrefix();
    descriptor: ()Ljava/lang/String;
    flags: ACC_PUBLIC
    Code:
      stack=1, locals=1, args_size=1
         0: ldc           #52                 // String StrStep
         2: areturn
      LocalVariableTable:
        Start  Length  Slot  Name   Signature
            0       3     0  this   Lrpg/patmat/steppedClass/StrStep;
      LineNumberTable:
        line 18: 0

  public int productArity();
    descriptor: ()I
    flags: ACC_PUBLIC
    Code:
      stack=1, locals=1, args_size=1
         0: iconst_1
         1: ireturn
      LocalVariableTable:
        Start  Length  Slot  Name   Signature
            0       2     0  this   Lrpg/patmat/steppedClass/StrStep;
      LineNumberTable:
        line 18: 0

  public java.lang.Object productElement(int);
    descriptor: (I)Ljava/lang/Object;
    flags: ACC_PUBLIC
    Code:
      stack=3, locals=3, args_size=2
         0: iload_1
         1: istore_2
         2: iload_2
         3: tableswitch   { // 0 to 0
                       0: 20
                 default: 27
            }
        20: aload_0
        21: invokevirtual #48                 // Method to:()Lrpg/patmat/steppedClass/Node;
        24: goto          42
        27: new           #59                 // class java/lang/IndexOutOfBoundsException
        30: dup
        31: iload_1
        32: invokestatic  #65                 // Method scala/runtime/BoxesRunTime.boxToInteger:(I)Ljava/lang/Integer;
        35: invokevirtual #70                 // Method java/lang/Object.toString:()Ljava/lang/String;
        38: invokespecial #73                 // Method java/lang/IndexOutOfBoundsException."<init>":(Ljava/lang/String;)V
        41: athrow
        42: areturn
      LocalVariableTable:
        Start  Length  Slot  Name   Signature
            0      43     0  this   Lrpg/patmat/steppedClass/StrStep;
            0      43     1   x$1   I
      LineNumberTable:
        line 18: 0
      StackMapTable: number_of_entries = 3
        frame_type = 252 /* append */
          offset_delta = 20
          locals = [ int ]
        frame_type = 6 /* same */
        frame_type = 78 /* same_locals_1_stack_item */
          stack = [ class rpg/patmat/steppedClass/Node ]
    MethodParameters:
      Name                           Flags
      x$1                            final

  public scala.collection.Iterator<java.lang.Object> productIterator();
    descriptor: ()Lscala/collection/Iterator;
    flags: ACC_PUBLIC
    Code:
      stack=2, locals=1, args_size=1
         0: getstatic     #83                 // Field scala/runtime/ScalaRunTime$.MODULE$:Lscala/runtime/ScalaRunTime$;
         3: aload_0
         4: invokevirtual #87                 // Method scala/runtime/ScalaRunTime$.typedProductIterator:(Lscala/Product;)Lscala/collection/Iterator;
         7: areturn
      LocalVariableTable:
        Start  Length  Slot  Name   Signature
            0       8     0  this   Lrpg/patmat/steppedClass/StrStep;
      LineNumberTable:
        line 18: 0
    Signature: #121                         // ()Lscala/collection/Iterator<Ljava/lang/Object;>;

  public boolean canEqual(java.lang.Object);
    descriptor: (Ljava/lang/Object;)Z
    flags: ACC_PUBLIC
    Code:
      stack=1, locals=2, args_size=2
         0: aload_1
         1: instanceof    #2                  // class rpg/patmat/steppedClass/StrStep
         4: ireturn
      LocalVariableTable:
        Start  Length  Slot  Name   Signature
            0       5     0  this   Lrpg/patmat/steppedClass/StrStep;
            0       5     1   x$1   Ljava/lang/Object;
      LineNumberTable:
        line 18: 0
    MethodParameters:
      Name                           Flags
      x$1                            final

  public int hashCode();
    descriptor: ()I
    flags: ACC_PUBLIC
    Code:
      stack=2, locals=1, args_size=1
         0: getstatic     #83                 // Field scala/runtime/ScalaRunTime$.MODULE$:Lscala/runtime/ScalaRunTime$;
         3: aload_0
         4: invokevirtual #95                 // Method scala/runtime/ScalaRunTime$._hashCode:(Lscala/Product;)I
         7: ireturn
      LocalVariableTable:
        Start  Length  Slot  Name   Signature
            0       8     0  this   Lrpg/patmat/steppedClass/StrStep;
      LineNumberTable:
        line 18: 0

  public java.lang.String toString();
    descriptor: ()Ljava/lang/String;
    flags: ACC_PUBLIC
    Code:
      stack=2, locals=1, args_size=1
         0: getstatic     #83                 // Field scala/runtime/ScalaRunTime$.MODULE$:Lscala/runtime/ScalaRunTime$;
         3: aload_0
         4: invokevirtual #99                 // Method scala/runtime/ScalaRunTime$._toString:(Lscala/Product;)Ljava/lang/String;
         7: areturn
      LocalVariableTable:
        Start  Length  Slot  Name   Signature
            0       8     0  this   Lrpg/patmat/steppedClass/StrStep;
      LineNumberTable:
        line 18: 0

  public boolean equals(java.lang.Object);
    descriptor: (Ljava/lang/Object;)Z
    flags: ACC_PUBLIC
    Code:
      stack=2, locals=6, args_size=2
         0: aload_0
         1: aload_1
         2: if_acmpeq     86
         5: aload_1
         6: astore_3
         7: aload_3
         8: instanceof    #2                  // class rpg/patmat/steppedClass/StrStep
        11: ifeq          19
        14: iconst_1
        15: istore_2
        16: goto          27
        19: goto          22
        22: iconst_0
        23: istore_2
        24: goto          27
        27: iload_2
        28: ifeq          90
        31: aload_1
        32: checkcast     #2                  // class rpg/patmat/steppedClass/StrStep
        35: astore        4
        37: aload_0
        38: invokevirtual #48                 // Method to:()Lrpg/patmat/steppedClass/Node;
        41: aload         4
        43: invokevirtual #48                 // Method to:()Lrpg/patmat/steppedClass/Node;
        46: astore        5
        48: dup
        49: ifnonnull     61
        52: pop
        53: aload         5
        55: ifnull        69
        58: goto          82
        61: aload         5
        63: invokevirtual #102                // Method java/lang/Object.equals:(Ljava/lang/Object;)Z
        66: ifeq          82
        69: aload         4
        71: aload_0
        72: invokevirtual #104                // Method canEqual:(Ljava/lang/Object;)Z
        75: ifeq          82
        78: iconst_1
        79: goto          83
        82: iconst_0
        83: ifeq          90
        86: iconst_1
        87: goto          91
        90: iconst_0
        91: ireturn
      LocalVariableTable:
        Start  Length  Slot  Name   Signature
            0      92     0  this   Lrpg/patmat/steppedClass/StrStep;
            0      92     1   x$1   Ljava/lang/Object;
      LineNumberTable:
        line 18: 0
      StackMapTable: number_of_entries = 10
        frame_type = 253 /* append */
          offset_delta = 19
          locals = [ top, class java/lang/Object ]
        frame_type = 2 /* same */
        frame_type = 255 /* full_frame */
          offset_delta = 4
          locals = [ class rpg/patmat/steppedClass/StrStep, class java/lang/Object, int, class java/lang/Object ]
          stack = []
        frame_type = 255 /* full_frame */
          offset_delta = 33
          locals = [ class rpg/patmat/steppedClass/StrStep, class java/lang/Object, int, class java/lang/Object, class rpg/patmat/steppedClass/StrStep, class rpg/patmat/steppedClass/Node ]
          stack = [ class rpg/patmat/steppedClass/Node ]
        frame_type = 7 /* same */
        frame_type = 12 /* same */
        frame_type = 64 /* same_locals_1_stack_item */
          stack = [ int ]
        frame_type = 255 /* full_frame */
          offset_delta = 2
          locals = [ class rpg/patmat/steppedClass/StrStep, class java/lang/Object ]
          stack = []
        frame_type = 253 /* append */
          offset_delta = 3
          locals = [ int, class java/lang/Object ]
        frame_type = 255 /* full_frame */
          offset_delta = 0
          locals = [ class rpg/patmat/steppedClass/StrStep, class java/lang/Object ]
          stack = [ int ]
    MethodParameters:
      Name                           Flags
      x$1                            final

  public rpg.patmat.steppedClass.StrStep(rpg.patmat.steppedClass.Node);
    descriptor: (Lrpg/patmat/steppedClass/Node;)V
    flags: ACC_PUBLIC
    Code:
      stack=2, locals=2, args_size=2
         0: aload_0
         1: aload_1
         2: putfield      #38                 // Field to:Lrpg/patmat/steppedClass/Node;
         5: aload_0
         6: invokespecial #107                // Method rpg/patmat/steppedClass/Step."<init>":()V
         9: aload_0
        10: invokestatic  #111                // InterfaceMethod scala/Product.$init$:(Lscala/Product;)V
        13: return
      LocalVariableTable:
        Start  Length  Slot  Name   Signature
            0      14     0  this   Lrpg/patmat/steppedClass/StrStep;
            0      14     1    to   Lrpg/patmat/steppedClass/Node;
      LineNumberTable:
        line 18: 0
    MethodParameters:
      Name                           Flags
      to                             final
}
SourceFile: "PatMatSkillTrees.scala"
RuntimeVisibleAnnotations:
  0: #10(#11=s#12)
Error: unknown attribute
  ScalaInlineInfo: length = 0x40
   01 00 00 0C 00 2A 00 2B 00 00 58 00 59 00 00 2E
   00 24 00 00 29 00 1A 00 00 64 00 59 00 00 5B 00
   36 00 00 35 00 36 00 00 37 00 38 00 00 4D 00 4E
   00 00 31 00 32 00 00 0D 00 24 00 00 44 00 32 00

Error: unknown attribute
  ScalaSig: length = 0x3
   05 00 00
