Compiled from "TypeclassSkillTrees.scala"
public final class rpg.typeclass.naive.DexSkill$ extends scala.runtime.AbstractFunction1<java.lang.String, rpg.typeclass.naive.DexSkill> implements scala.Serializable {
  public static rpg.typeclass.naive.DexSkill$ MODULE$;

  public static {};
    Code:
       0: new           #2                  // class rpg/typeclass/naive/DexSkill$
       3: invokespecial #15                 // Method "<init>":()V
       6: return

  public final java.lang.String toString();
    Code:
       0: ldc           #19                 // String DexSkill
       2: areturn

  public rpg.typeclass.naive.DexSkill apply(java.lang.String);
    Code:
       0: new           #25                 // class rpg/typeclass/naive/DexSkill
       3: dup
       4: aload_1
       5: invokespecial #28                 // Method rpg/typeclass/naive/DexSkill."<init>":(Ljava/lang/String;)V
       8: areturn

  public scala.Option<java.lang.String> unapply(rpg.typeclass.naive.DexSkill);
    Code:
       0: aload_1
       1: ifnonnull     10
       4: getstatic     #37                 // Field scala/None$.MODULE$:Lscala/None$;
       7: goto          21
      10: new           #39                 // class scala/Some
      13: dup
      14: aload_1
      15: invokevirtual #41                 // Method rpg/typeclass/naive/DexSkill.name:()Ljava/lang/String;
      18: invokespecial #44                 // Method scala/Some."<init>":(Ljava/lang/Object;)V
      21: areturn

  private java.lang.Object readResolve();
    Code:
       0: getstatic     #51                 // Field MODULE$:Lrpg/typeclass/naive/DexSkill$;
       3: areturn

  public java.lang.Object apply(java.lang.Object);
    Code:
       0: aload_0
       1: aload_1
       2: checkcast     #55                 // class java/lang/String
       5: invokevirtual #57                 // Method apply:(Ljava/lang/String;)Lrpg/typeclass/naive/DexSkill;
       8: areturn

  private rpg.typeclass.naive.DexSkill$();
    Code:
       0: aload_0
       1: invokespecial #59                 // Method scala/runtime/AbstractFunction1."<init>":()V
       4: aload_0
       5: putstatic     #51                 // Field MODULE$:Lrpg/typeclass/naive/DexSkill$;
       8: return
}
