Classfile /home/krzysiek/workspace/scala-bcode-cutter/pref/target/scala-2.12/classes/rpg/ooo/lambdas/Skill.class
  Last modified Apr 8, 2018; size 5734 bytes
  MD5 checksum 138369abe2ef92b915367374e266469c
  Compiled from "LambdasSkillTrees.scala"
public class rpg.ooo.lambdas.Skill implements rpg.ooo.lambdas.Node,scala.Product,scala.Serializable
  minor version: 0
  major version: 52
  flags: ACC_PUBLIC, ACC_SUPER
Constant pool:
    #1 = Utf8               rpg/ooo/lambdas/Skill
    #2 = Class              #1            // rpg/ooo/lambdas/Skill
    #3 = Utf8               java/lang/Object
    #4 = Class              #3            // java/lang/Object
    #5 = Utf8               rpg/ooo/lambdas/Node
    #6 = Class              #5            // rpg/ooo/lambdas/Node
    #7 = Utf8               scala/Product
    #8 = Class              #7            // scala/Product
    #9 = Utf8               scala/Serializable
   #10 = Class              #9            // scala/Serializable
   #11 = Utf8               LambdasSkillTrees.scala
   #12 = Utf8               Lscala/reflect/ScalaSignature;
   #13 = Utf8               bytes
   #14 = Utf8               mcB&QaU6jY2T!a1WN3bg*QAB_>|'\"AIxmQF-qQ\"5\tQa]2bYL!a\rsPU3g!\t\t\"#D\t\"AO_,CA\t1BBAQe>$Wo;-ABA\r\r1VM]5bY&TM7f!YA!f\na4fCR,!\tyC% \tIa)8di&|g.\r\tC\tjABGA7bsHK]1jiN\"aC\nb!aA%oi\"AB\tB%Q$AgK$+\tU\r\",q-\31\"!9CA\r$BA\ta$o\8u}%1D!J,G-4\nU2$AB*ue&twM4!AB\tB%A&AoC6,C;1(=S:LGOyurCA\tY1Q1-\"Bwn;\"B\"@A;sC&$8CFI$\t\r|/yCbBE!\r!U\n1-Q!%A-abY8qs\"WMZ1vYR$'FMU\tiRjKO!\tyE+DQ\t\t&+Av]DWmY6fI*1DC:tw^1uS>tBA+QE)hn5fG.,GMV1sSt7-/\t\n\"Y9w]=%I4-7uII*!Y5CqaC,Aqe>$Wo;Qe4_;BalY?*-YYtwMCcQM^1\nUzbB3%\tAZ\raJ|G-^2uJLG/_I!9AA\nIA9s_,8\r^#mK6,gU6\"aC6\n1d!aA!os\"9anZA!a=%c!9AA\n\na9s_,8\r^%uKJGo:I2a<k!(BA;\r)w7fGRLwN\oR\";fe$xNs\t\t\"{!M\#rkdGCA>!\tYA0~\t9!i\8mKtb8y\rA\n!C!\t[1tQ{G-I!IqB\ti>FO]5oOR\tQC\t\t\"1Q-];bYN$2a_A\t!q1BAQw!CA\tAA6.7m!\r\t\t\t\t\t#M)DA/A9qDA;1bTBAA\r\tDeVtG/[7f\t9#!\t#7:bGR4UO\2uS>t'C;3!\t!a]BCA3\t\t\"\n!QGA\r%\t)a\r\=q\n)$a\t\rm\ty1QqaY!Q1HA\r%\t)!Ut\r9msR!qHA&!YIA#\r\tB$n8-\t9%\n%CBUkBdWM\r\n\nI$!AAq\n11)\t\t&!%1KeGMU3t_24X\rVAa,a\nesLPE*,7\r
   #15 = Utf8               feat
   #16 = Utf8               Lscala/Function1;
   #17 = Utf8               Lscala/Function1<Lrpg/PlayerTraits;Ljava/lang/Object;>;
   #18 = Utf8               name
   #19 = Utf8               Ljava/lang/String;
   #20 = Utf8               unapply
   #21 = Utf8               (Lrpg/ooo/lambdas/Skill;)Lscala/Option;
   #22 = Utf8               rpg/ooo/lambdas/Skill$
   #23 = Class              #22           // rpg/ooo/lambdas/Skill$
   #24 = Utf8               MODULE$
   #25 = Utf8               Lrpg/ooo/lambdas/Skill$;
   #26 = NameAndType        #24:#25       // MODULE$:Lrpg/ooo/lambdas/Skill$;
   #27 = Fieldref           #23.#26       // rpg/ooo/lambdas/Skill$.MODULE$:Lrpg/ooo/lambdas/Skill$;
   #28 = NameAndType        #20:#21       // unapply:(Lrpg/ooo/lambdas/Skill;)Lscala/Option;
   #29 = Methodref          #23.#28       // rpg/ooo/lambdas/Skill$.unapply:(Lrpg/ooo/lambdas/Skill;)Lscala/Option;
   #30 = Utf8               apply
   #31 = Utf8               (Lscala/Function1;Ljava/lang/String;)Lrpg/ooo/lambdas/Skill;
   #32 = NameAndType        #30:#31       // apply:(Lscala/Function1;Ljava/lang/String;)Lrpg/ooo/lambdas/Skill;
   #33 = Methodref          #23.#32       // rpg/ooo/lambdas/Skill$.apply:(Lscala/Function1;Ljava/lang/String;)Lrpg/ooo/lambdas/Skill;
   #34 = Utf8               tupled
   #35 = Utf8               ()Lscala/Function1;
   #36 = NameAndType        #34:#35       // tupled:()Lscala/Function1;
   #37 = Methodref          #23.#36       // rpg/ooo/lambdas/Skill$.tupled:()Lscala/Function1;
   #38 = Utf8               curried
   #39 = NameAndType        #38:#35       // curried:()Lscala/Function1;
   #40 = Methodref          #23.#39       // rpg/ooo/lambdas/Skill$.curried:()Lscala/Function1;
   #41 = NameAndType        #15:#16       // feat:Lscala/Function1;
   #42 = Fieldref           #2.#41        // rpg/ooo/lambdas/Skill.feat:Lscala/Function1;
   #43 = Utf8               this
   #44 = Utf8               Lrpg/ooo/lambdas/Skill;
   #45 = Utf8               ()Ljava/lang/String;
   #46 = NameAndType        #18:#19       // name:Ljava/lang/String;
   #47 = Fieldref           #2.#46        // rpg/ooo/lambdas/Skill.name:Ljava/lang/String;
   #48 = Utf8               cost
   #49 = Utf8               (Lrpg/PlayerTraits;)I
   #50 = Utf8               traits
   #51 = NameAndType        #15:#35       // feat:()Lscala/Function1;
   #52 = Methodref          #2.#51        // rpg/ooo/lambdas/Skill.feat:()Lscala/Function1;
   #53 = Utf8               scala/Function1
   #54 = Class              #53           // scala/Function1
   #55 = Utf8               (Ljava/lang/Object;)Ljava/lang/Object;
   #56 = NameAndType        #30:#55       // apply:(Ljava/lang/Object;)Ljava/lang/Object;
   #57 = InterfaceMethodref #54.#56       // scala/Function1.apply:(Ljava/lang/Object;)Ljava/lang/Object;
   #58 = Utf8               scala/runtime/BoxesRunTime
   #59 = Class              #58           // scala/runtime/BoxesRunTime
   #60 = Utf8               unboxToInt
   #61 = Utf8               (Ljava/lang/Object;)I
   #62 = NameAndType        #60:#61       // unboxToInt:(Ljava/lang/Object;)I
   #63 = Methodref          #59.#62       // scala/runtime/BoxesRunTime.unboxToInt:(Ljava/lang/Object;)I
   #64 = Utf8               Lrpg/PlayerTraits;
   #65 = Utf8               copy
   #66 = Utf8               <init>
   #67 = Utf8               (Lscala/Function1;Ljava/lang/String;)V
   #68 = NameAndType        #66:#67       // "<init>":(Lscala/Function1;Ljava/lang/String;)V
   #69 = Methodref          #2.#68        // rpg/ooo/lambdas/Skill."<init>":(Lscala/Function1;Ljava/lang/String;)V
   #70 = Utf8               copy$default$1
   #71 = Utf8               copy$default$2
   #72 = NameAndType        #18:#45       // name:()Ljava/lang/String;
   #73 = Methodref          #2.#72        // rpg/ooo/lambdas/Skill.name:()Ljava/lang/String;
   #74 = Utf8               productPrefix
   #75 = Utf8               Skill
   #76 = String             #75           // Skill
   #77 = Utf8               productArity
   #78 = Utf8               ()I
   #79 = Utf8               productElement
   #80 = Utf8               (I)Ljava/lang/Object;
   #81 = Utf8               x$1
   #82 = Utf8               java/lang/IndexOutOfBoundsException
   #83 = Class              #82           // java/lang/IndexOutOfBoundsException
   #84 = Utf8               boxToInteger
   #85 = Utf8               (I)Ljava/lang/Integer;
   #86 = NameAndType        #84:#85       // boxToInteger:(I)Ljava/lang/Integer;
   #87 = Methodref          #59.#86       // scala/runtime/BoxesRunTime.boxToInteger:(I)Ljava/lang/Integer;
   #88 = Utf8               toString
   #89 = NameAndType        #88:#45       // toString:()Ljava/lang/String;
   #90 = Methodref          #4.#89        // java/lang/Object.toString:()Ljava/lang/String;
   #91 = Utf8               (Ljava/lang/String;)V
   #92 = NameAndType        #66:#91       // "<init>":(Ljava/lang/String;)V
   #93 = Methodref          #83.#92       // java/lang/IndexOutOfBoundsException."<init>":(Ljava/lang/String;)V
   #94 = Utf8               I
   #95 = Utf8               productIterator
   #96 = Utf8               ()Lscala/collection/Iterator;
   #97 = Utf8               scala/runtime/ScalaRunTime$
   #98 = Class              #97           // scala/runtime/ScalaRunTime$
   #99 = Utf8               Lscala/runtime/ScalaRunTime$;
  #100 = NameAndType        #24:#99       // MODULE$:Lscala/runtime/ScalaRunTime$;
  #101 = Fieldref           #98.#100      // scala/runtime/ScalaRunTime$.MODULE$:Lscala/runtime/ScalaRunTime$;
  #102 = Utf8               typedProductIterator
  #103 = Utf8               (Lscala/Product;)Lscala/collection/Iterator;
  #104 = NameAndType        #102:#103     // typedProductIterator:(Lscala/Product;)Lscala/collection/Iterator;
  #105 = Methodref          #98.#104      // scala/runtime/ScalaRunTime$.typedProductIterator:(Lscala/Product;)Lscala/collection/Iterator;
  #106 = Utf8               canEqual
  #107 = Utf8               (Ljava/lang/Object;)Z
  #108 = Utf8               Ljava/lang/Object;
  #109 = Utf8               hashCode
  #110 = Utf8               _hashCode
  #111 = Utf8               (Lscala/Product;)I
  #112 = NameAndType        #110:#111     // _hashCode:(Lscala/Product;)I
  #113 = Methodref          #98.#112      // scala/runtime/ScalaRunTime$._hashCode:(Lscala/Product;)I
  #114 = Utf8               _toString
  #115 = Utf8               (Lscala/Product;)Ljava/lang/String;
  #116 = NameAndType        #114:#115     // _toString:(Lscala/Product;)Ljava/lang/String;
  #117 = Methodref          #98.#116      // scala/runtime/ScalaRunTime$._toString:(Lscala/Product;)Ljava/lang/String;
  #118 = Utf8               equals
  #119 = NameAndType        #118:#107     // equals:(Ljava/lang/Object;)Z
  #120 = Methodref          #4.#119       // java/lang/Object.equals:(Ljava/lang/Object;)Z
  #121 = NameAndType        #106:#107     // canEqual:(Ljava/lang/Object;)Z
  #122 = Methodref          #2.#121       // rpg/ooo/lambdas/Skill.canEqual:(Ljava/lang/Object;)Z
  #123 = Utf8               java/lang/String
  #124 = Class              #123          // java/lang/String
  #125 = Utf8               ()V
  #126 = NameAndType        #66:#125      // "<init>":()V
  #127 = Methodref          #4.#126       // java/lang/Object."<init>":()V
  #128 = Utf8               $init$
  #129 = Utf8               (Lscala/Product;)V
  #130 = NameAndType        #128:#129     // $init$:(Lscala/Product;)V
  #131 = InterfaceMethodref #8.#130       // scala/Product.$init$:(Lscala/Product;)V
  #132 = Utf8               Signature
  #133 = Utf8               Code
  #134 = Utf8               (Lrpg/ooo/lambdas/Skill;)Lscala/Option<Lscala/Tuple2<Lscala/Function1<Lrpg/PlayerTraits;Ljava/lang/Object;>;Ljava/lang/String;>;>;
  #135 = Utf8               (Lscala/Function1<Lrpg/PlayerTraits;Ljava/lang/Object;>;Ljava/lang/String;)Lrpg/ooo/lambdas/Skill;
  #136 = Utf8               ()Lscala/Function1<Lscala/Tuple2<Lscala/Function1<Lrpg/PlayerTraits;Ljava/lang/Object;>;Ljava/lang/String;>;Lrpg/ooo/lambdas/Skill;>;
  #137 = Utf8               ()Lscala/Function1<Lscala/Function1<Lrpg/PlayerTraits;Ljava/lang/Object;>;Lscala/Function1<Ljava/lang/String;Lrpg/ooo/lambdas/Skill;>;>;
  #138 = Utf8               LocalVariableTable
  #139 = Utf8               LineNumberTable
  #140 = Utf8               ()Lscala/Function1<Lrpg/PlayerTraits;Ljava/lang/Object;>;
  #141 = Utf8               MethodParameters
  #142 = Utf8               StackMapTable
  #143 = Utf8               ()Lscala/collection/Iterator<Ljava/lang/Object;>;
  #144 = Utf8               (Lscala/Function1<Lrpg/PlayerTraits;Ljava/lang/Object;>;Ljava/lang/String;)V
  #145 = Utf8               SourceFile
  #146 = Utf8               RuntimeVisibleAnnotations
  #147 = Utf8               ScalaInlineInfo
  #148 = Utf8               ScalaSig
{
  private final scala.Function1<rpg.PlayerTraits, java.lang.Object> feat;
    descriptor: Lscala/Function1;
    flags: ACC_PRIVATE, ACC_FINAL
    Signature: #17                          // Lscala/Function1<Lrpg/PlayerTraits;Ljava/lang/Object;>;

  private final java.lang.String name;
    descriptor: Ljava/lang/String;
    flags: ACC_PRIVATE, ACC_FINAL

  public static scala.Option<scala.Tuple2<scala.Function1<rpg.PlayerTraits, java.lang.Object>, java.lang.String>> unapply(rpg.ooo.lambdas.Skill);
    descriptor: (Lrpg/ooo/lambdas/Skill;)Lscala/Option;
    flags: ACC_PUBLIC, ACC_STATIC
    Code:
      stack=2, locals=1, args_size=1
         0: getstatic     #27                 // Field rpg/ooo/lambdas/Skill$.MODULE$:Lrpg/ooo/lambdas/Skill$;
         3: aload_0
         4: invokevirtual #29                 // Method rpg/ooo/lambdas/Skill$.unapply:(Lrpg/ooo/lambdas/Skill;)Lscala/Option;
         7: areturn
    Signature: #134                         // (Lrpg/ooo/lambdas/Skill;)Lscala/Option<Lscala/Tuple2<Lscala/Function1<Lrpg/PlayerTraits;Ljava/lang/Object;>;Ljava/lang/String;>;>;

  public static rpg.ooo.lambdas.Skill apply(scala.Function1<rpg.PlayerTraits, java.lang.Object>, java.lang.String);
    descriptor: (Lscala/Function1;Ljava/lang/String;)Lrpg/ooo/lambdas/Skill;
    flags: ACC_PUBLIC, ACC_STATIC
    Code:
      stack=3, locals=2, args_size=2
         0: getstatic     #27                 // Field rpg/ooo/lambdas/Skill$.MODULE$:Lrpg/ooo/lambdas/Skill$;
         3: aload_0
         4: aload_1
         5: invokevirtual #33                 // Method rpg/ooo/lambdas/Skill$.apply:(Lscala/Function1;Ljava/lang/String;)Lrpg/ooo/lambdas/Skill;
         8: areturn
    Signature: #135                         // (Lscala/Function1<Lrpg/PlayerTraits;Ljava/lang/Object;>;Ljava/lang/String;)Lrpg/ooo/lambdas/Skill;

  public static scala.Function1<scala.Tuple2<scala.Function1<rpg.PlayerTraits, java.lang.Object>, java.lang.String>, rpg.ooo.lambdas.Skill> tupled();
    descriptor: ()Lscala/Function1;
    flags: ACC_PUBLIC, ACC_STATIC
    Code:
      stack=1, locals=0, args_size=0
         0: getstatic     #27                 // Field rpg/ooo/lambdas/Skill$.MODULE$:Lrpg/ooo/lambdas/Skill$;
         3: invokevirtual #37                 // Method rpg/ooo/lambdas/Skill$.tupled:()Lscala/Function1;
         6: areturn
    Signature: #136                         // ()Lscala/Function1<Lscala/Tuple2<Lscala/Function1<Lrpg/PlayerTraits;Ljava/lang/Object;>;Ljava/lang/String;>;Lrpg/ooo/lambdas/Skill;>;

  public static scala.Function1<scala.Function1<rpg.PlayerTraits, java.lang.Object>, scala.Function1<java.lang.String, rpg.ooo.lambdas.Skill>> curried();
    descriptor: ()Lscala/Function1;
    flags: ACC_PUBLIC, ACC_STATIC
    Code:
      stack=1, locals=0, args_size=0
         0: getstatic     #27                 // Field rpg/ooo/lambdas/Skill$.MODULE$:Lrpg/ooo/lambdas/Skill$;
         3: invokevirtual #40                 // Method rpg/ooo/lambdas/Skill$.curried:()Lscala/Function1;
         6: areturn
    Signature: #137                         // ()Lscala/Function1<Lscala/Function1<Lrpg/PlayerTraits;Ljava/lang/Object;>;Lscala/Function1<Ljava/lang/String;Lrpg/ooo/lambdas/Skill;>;>;

  public scala.Function1<rpg.PlayerTraits, java.lang.Object> feat();
    descriptor: ()Lscala/Function1;
    flags: ACC_PUBLIC
    Code:
      stack=1, locals=1, args_size=1
         0: aload_0
         1: getfield      #42                 // Field feat:Lscala/Function1;
         4: areturn
      LocalVariableTable:
        Start  Length  Slot  Name   Signature
            0       5     0  this   Lrpg/ooo/lambdas/Skill;
      LineNumberTable:
        line 20: 0
    Signature: #140                         // ()Lscala/Function1<Lrpg/PlayerTraits;Ljava/lang/Object;>;

  public java.lang.String name();
    descriptor: ()Ljava/lang/String;
    flags: ACC_PUBLIC
    Code:
      stack=1, locals=1, args_size=1
         0: aload_0
         1: getfield      #47                 // Field name:Ljava/lang/String;
         4: areturn
      LocalVariableTable:
        Start  Length  Slot  Name   Signature
            0       5     0  this   Lrpg/ooo/lambdas/Skill;
      LineNumberTable:
        line 20: 0

  public int cost(rpg.PlayerTraits);
    descriptor: (Lrpg/PlayerTraits;)I
    flags: ACC_PUBLIC
    Code:
      stack=2, locals=2, args_size=2
         0: aload_0
         1: invokevirtual #52                 // Method feat:()Lscala/Function1;
         4: aload_1
         5: invokeinterface #57,  2           // InterfaceMethod scala/Function1.apply:(Ljava/lang/Object;)Ljava/lang/Object;
        10: invokestatic  #63                 // Method scala/runtime/BoxesRunTime.unboxToInt:(Ljava/lang/Object;)I
        13: ireturn
      LocalVariableTable:
        Start  Length  Slot  Name   Signature
            0      14     0  this   Lrpg/ooo/lambdas/Skill;
            0      14     1 traits   Lrpg/PlayerTraits;
      LineNumberTable:
        line 21: 0
    MethodParameters:
      Name                           Flags
      traits                         final

  public rpg.ooo.lambdas.Skill copy(scala.Function1<rpg.PlayerTraits, java.lang.Object>, java.lang.String);
    descriptor: (Lscala/Function1;Ljava/lang/String;)Lrpg/ooo/lambdas/Skill;
    flags: ACC_PUBLIC
    Code:
      stack=4, locals=3, args_size=3
         0: new           #2                  // class rpg/ooo/lambdas/Skill
         3: dup
         4: aload_1
         5: aload_2
         6: invokespecial #69                 // Method "<init>":(Lscala/Function1;Ljava/lang/String;)V
         9: areturn
      LocalVariableTable:
        Start  Length  Slot  Name   Signature
            0      10     0  this   Lrpg/ooo/lambdas/Skill;
            0      10     1  feat   Lscala/Function1;
            0      10     2  name   Ljava/lang/String;
      LineNumberTable:
        line 20: 0
    Signature: #135                         // (Lscala/Function1<Lrpg/PlayerTraits;Ljava/lang/Object;>;Ljava/lang/String;)Lrpg/ooo/lambdas/Skill;
    MethodParameters:
      Name                           Flags
      feat                           final
      name                           final

  public scala.Function1<rpg.PlayerTraits, java.lang.Object> copy$default$1();
    descriptor: ()Lscala/Function1;
    flags: ACC_PUBLIC
    Code:
      stack=1, locals=1, args_size=1
         0: aload_0
         1: invokevirtual #52                 // Method feat:()Lscala/Function1;
         4: areturn
      LocalVariableTable:
        Start  Length  Slot  Name   Signature
            0       5     0  this   Lrpg/ooo/lambdas/Skill;
      LineNumberTable:
        line 20: 0
    Signature: #140                         // ()Lscala/Function1<Lrpg/PlayerTraits;Ljava/lang/Object;>;

  public java.lang.String copy$default$2();
    descriptor: ()Ljava/lang/String;
    flags: ACC_PUBLIC
    Code:
      stack=1, locals=1, args_size=1
         0: aload_0
         1: invokevirtual #73                 // Method name:()Ljava/lang/String;
         4: areturn
      LocalVariableTable:
        Start  Length  Slot  Name   Signature
            0       5     0  this   Lrpg/ooo/lambdas/Skill;
      LineNumberTable:
        line 20: 0

  public java.lang.String productPrefix();
    descriptor: ()Ljava/lang/String;
    flags: ACC_PUBLIC
    Code:
      stack=1, locals=1, args_size=1
         0: ldc           #76                 // String Skill
         2: areturn
      LocalVariableTable:
        Start  Length  Slot  Name   Signature
            0       3     0  this   Lrpg/ooo/lambdas/Skill;
      LineNumberTable:
        line 20: 0

  public int productArity();
    descriptor: ()I
    flags: ACC_PUBLIC
    Code:
      stack=1, locals=1, args_size=1
         0: iconst_2
         1: ireturn
      LocalVariableTable:
        Start  Length  Slot  Name   Signature
            0       2     0  this   Lrpg/ooo/lambdas/Skill;
      LineNumberTable:
        line 20: 0

  public java.lang.Object productElement(int);
    descriptor: (I)Ljava/lang/Object;
    flags: ACC_PUBLIC
    Code:
      stack=3, locals=3, args_size=2
         0: iload_1
         1: istore_2
         2: iload_2
         3: tableswitch   { // 0 to 1
                       0: 24
                       1: 31
                 default: 38
            }
        24: aload_0
        25: invokevirtual #52                 // Method feat:()Lscala/Function1;
        28: goto          53
        31: aload_0
        32: invokevirtual #73                 // Method name:()Ljava/lang/String;
        35: goto          53
        38: new           #83                 // class java/lang/IndexOutOfBoundsException
        41: dup
        42: iload_1
        43: invokestatic  #87                 // Method scala/runtime/BoxesRunTime.boxToInteger:(I)Ljava/lang/Integer;
        46: invokevirtual #90                 // Method java/lang/Object.toString:()Ljava/lang/String;
        49: invokespecial #93                 // Method java/lang/IndexOutOfBoundsException."<init>":(Ljava/lang/String;)V
        52: athrow
        53: areturn
      LocalVariableTable:
        Start  Length  Slot  Name   Signature
            0      54     0  this   Lrpg/ooo/lambdas/Skill;
            0      54     1   x$1   I
      LineNumberTable:
        line 20: 0
      StackMapTable: number_of_entries = 4
        frame_type = 252 /* append */
          offset_delta = 24
          locals = [ int ]
        frame_type = 6 /* same */
        frame_type = 6 /* same */
        frame_type = 78 /* same_locals_1_stack_item */
          stack = [ class java/lang/Object ]
    MethodParameters:
      Name                           Flags
      x$1                            final

  public scala.collection.Iterator<java.lang.Object> productIterator();
    descriptor: ()Lscala/collection/Iterator;
    flags: ACC_PUBLIC
    Code:
      stack=2, locals=1, args_size=1
         0: getstatic     #101                // Field scala/runtime/ScalaRunTime$.MODULE$:Lscala/runtime/ScalaRunTime$;
         3: aload_0
         4: invokevirtual #105                // Method scala/runtime/ScalaRunTime$.typedProductIterator:(Lscala/Product;)Lscala/collection/Iterator;
         7: areturn
      LocalVariableTable:
        Start  Length  Slot  Name   Signature
            0       8     0  this   Lrpg/ooo/lambdas/Skill;
      LineNumberTable:
        line 20: 0
    Signature: #143                         // ()Lscala/collection/Iterator<Ljava/lang/Object;>;

  public boolean canEqual(java.lang.Object);
    descriptor: (Ljava/lang/Object;)Z
    flags: ACC_PUBLIC
    Code:
      stack=1, locals=2, args_size=2
         0: aload_1
         1: instanceof    #2                  // class rpg/ooo/lambdas/Skill
         4: ireturn
      LocalVariableTable:
        Start  Length  Slot  Name   Signature
            0       5     0  this   Lrpg/ooo/lambdas/Skill;
            0       5     1   x$1   Ljava/lang/Object;
      LineNumberTable:
        line 20: 0
    MethodParameters:
      Name                           Flags
      x$1                            final

  public int hashCode();
    descriptor: ()I
    flags: ACC_PUBLIC
    Code:
      stack=2, locals=1, args_size=1
         0: getstatic     #101                // Field scala/runtime/ScalaRunTime$.MODULE$:Lscala/runtime/ScalaRunTime$;
         3: aload_0
         4: invokevirtual #113                // Method scala/runtime/ScalaRunTime$._hashCode:(Lscala/Product;)I
         7: ireturn
      LocalVariableTable:
        Start  Length  Slot  Name   Signature
            0       8     0  this   Lrpg/ooo/lambdas/Skill;
      LineNumberTable:
        line 20: 0

  public java.lang.String toString();
    descriptor: ()Ljava/lang/String;
    flags: ACC_PUBLIC
    Code:
      stack=2, locals=1, args_size=1
         0: getstatic     #101                // Field scala/runtime/ScalaRunTime$.MODULE$:Lscala/runtime/ScalaRunTime$;
         3: aload_0
         4: invokevirtual #117                // Method scala/runtime/ScalaRunTime$._toString:(Lscala/Product;)Ljava/lang/String;
         7: areturn
      LocalVariableTable:
        Start  Length  Slot  Name   Signature
            0       8     0  this   Lrpg/ooo/lambdas/Skill;
      LineNumberTable:
        line 20: 0

  public boolean equals(java.lang.Object);
    descriptor: (Ljava/lang/Object;)Z
    flags: ACC_PUBLIC
    Code:
      stack=2, locals=7, args_size=2
         0: aload_0
         1: aload_1
         2: if_acmpeq     118
         5: aload_1
         6: astore_3
         7: aload_3
         8: instanceof    #2                  // class rpg/ooo/lambdas/Skill
        11: ifeq          19
        14: iconst_1
        15: istore_2
        16: goto          27
        19: goto          22
        22: iconst_0
        23: istore_2
        24: goto          27
        27: iload_2
        28: ifeq          122
        31: aload_1
        32: checkcast     #2                  // class rpg/ooo/lambdas/Skill
        35: astore        4
        37: aload_0
        38: invokevirtual #52                 // Method feat:()Lscala/Function1;
        41: aload         4
        43: invokevirtual #52                 // Method feat:()Lscala/Function1;
        46: astore        5
        48: dup
        49: ifnonnull     61
        52: pop
        53: aload         5
        55: ifnull        69
        58: goto          114
        61: aload         5
        63: invokevirtual #120                // Method java/lang/Object.equals:(Ljava/lang/Object;)Z
        66: ifeq          114
        69: aload_0
        70: invokevirtual #73                 // Method name:()Ljava/lang/String;
        73: aload         4
        75: invokevirtual #73                 // Method name:()Ljava/lang/String;
        78: astore        6
        80: dup
        81: ifnonnull     93
        84: pop
        85: aload         6
        87: ifnull        101
        90: goto          114
        93: aload         6
        95: invokevirtual #120                // Method java/lang/Object.equals:(Ljava/lang/Object;)Z
        98: ifeq          114
       101: aload         4
       103: aload_0
       104: invokevirtual #122                // Method canEqual:(Ljava/lang/Object;)Z
       107: ifeq          114
       110: iconst_1
       111: goto          115
       114: iconst_0
       115: ifeq          122
       118: iconst_1
       119: goto          123
       122: iconst_0
       123: ireturn
      LocalVariableTable:
        Start  Length  Slot  Name   Signature
            0     124     0  this   Lrpg/ooo/lambdas/Skill;
            0     124     1   x$1   Ljava/lang/Object;
      LineNumberTable:
        line 20: 0
      StackMapTable: number_of_entries = 12
        frame_type = 253 /* append */
          offset_delta = 19
          locals = [ top, class java/lang/Object ]
        frame_type = 2 /* same */
        frame_type = 255 /* full_frame */
          offset_delta = 4
          locals = [ class rpg/ooo/lambdas/Skill, class java/lang/Object, int, class java/lang/Object ]
          stack = []
        frame_type = 255 /* full_frame */
          offset_delta = 33
          locals = [ class rpg/ooo/lambdas/Skill, class java/lang/Object, int, class java/lang/Object, class rpg/ooo/lambdas/Skill, class scala/Function1 ]
          stack = [ class scala/Function1 ]
        frame_type = 7 /* same */
        frame_type = 255 /* full_frame */
          offset_delta = 23
          locals = [ class rpg/ooo/lambdas/Skill, class java/lang/Object, int, class java/lang/Object, class rpg/ooo/lambdas/Skill, class scala/Function1, class java/lang/String ]
          stack = [ class java/lang/String ]
        frame_type = 7 /* same */
        frame_type = 250 /* chop */
          offset_delta = 12
        frame_type = 64 /* same_locals_1_stack_item */
          stack = [ int ]
        frame_type = 255 /* full_frame */
          offset_delta = 2
          locals = [ class rpg/ooo/lambdas/Skill, class java/lang/Object ]
          stack = []
        frame_type = 253 /* append */
          offset_delta = 3
          locals = [ int, class java/lang/Object ]
        frame_type = 255 /* full_frame */
          offset_delta = 0
          locals = [ class rpg/ooo/lambdas/Skill, class java/lang/Object ]
          stack = [ int ]
    MethodParameters:
      Name                           Flags
      x$1                            final

  public rpg.ooo.lambdas.Skill(scala.Function1<rpg.PlayerTraits, java.lang.Object>, java.lang.String);
    descriptor: (Lscala/Function1;Ljava/lang/String;)V
    flags: ACC_PUBLIC
    Code:
      stack=2, locals=3, args_size=3
         0: aload_0
         1: aload_1
         2: putfield      #42                 // Field feat:Lscala/Function1;
         5: aload_0
         6: aload_2
         7: putfield      #47                 // Field name:Ljava/lang/String;
        10: aload_0
        11: invokespecial #127                // Method java/lang/Object."<init>":()V
        14: aload_0
        15: invokestatic  #131                // InterfaceMethod scala/Product.$init$:(Lscala/Product;)V
        18: return
      LocalVariableTable:
        Start  Length  Slot  Name   Signature
            0      19     0  this   Lrpg/ooo/lambdas/Skill;
            0      19     1  feat   Lscala/Function1;
            0      19     2  name   Ljava/lang/String;
      LineNumberTable:
        line 20: 0
    Signature: #144                         // (Lscala/Function1<Lrpg/PlayerTraits;Ljava/lang/Object;>;Ljava/lang/String;)V
    MethodParameters:
      Name                           Flags
      feat                           final
      name                           final
}
SourceFile: "LambdasSkillTrees.scala"
RuntimeVisibleAnnotations:
  0: #12(#13=s#14)
Error: unknown attribute
  ScalaInlineInfo: length = 0x4F
   01 00 00 0F 00 42 00 43 00 00 6A 00 6B 00 00 46
   00 23 00 00 47 00 2D 00 00 41 00 1F 00 00 30 00
   31 00 00 76 00 6B 00 00 0F 00 23 00 00 6D 00 4E
   00 00 12 00 2D 00 00 4D 00 4E 00 00 4F 00 50 00
   00 5F 00 60 00 00 4A 00 2D 00 00 58 00 2D 00
Error: unknown attribute
  ScalaSig: length = 0x3
   05 00 00
