Classfile /home/krzysiek/workspace/scala-bcode-cutter/pref/target/scala-2.12/classes/rpg/ooo/lambdas/LambdasSkillTrees.class
  Last modified Apr 8, 2018; size 5465 bytes
  MD5 checksum 574e981df68ccd428d11bc2aef3ca4a3
  Compiled from "LambdasSkillTrees.scala"
public class rpg.ooo.lambdas.LambdasSkillTrees extends rpg.SkillTrees
  minor version: 0
  major version: 52
  flags: ACC_PUBLIC, ACC_SUPER
Constant pool:
    #1 = Utf8               rpg/ooo/lambdas/LambdasSkillTrees
    #2 = Class              #1            // rpg/ooo/lambdas/LambdasSkillTrees
    #3 = Utf8               rpg/SkillTrees
    #4 = Class              #3            // rpg/SkillTrees
    #5 = Utf8               LambdasSkillTrees.scala
    #6 = Utf8               Lscala/reflect/ScalaSignature;
    #7 = Utf8               bytes
    #8 = Utf8               52A!\t\tB*Y7cI8k[5mYRX-Z:\r!a7b[\n$m\t1a\8p9a:qO1C!\tYA\"D\tiaATW&dG:fKNDQaA\taP5oSRtD#A\tIQ\"\tQAI8\r[3ssRX--!$a-A\"$\r\ti1k[5mYRX-*faJ\"a\rIQdEA\tA?\nCA&!\t3%D\"!B:dC2B\"qu5j]\"\t\n\n#aA!os\")faU1AO]1jiN\"aC\n12!)mCf,':bSR
    #9 = Utf8               java/lang/invoke/MethodHandles$Lookup
   #10 = Class              #9            // java/lang/invoke/MethodHandles$Lookup
   #11 = Utf8               java/lang/invoke/MethodHandles
   #12 = Class              #11           // java/lang/invoke/MethodHandles
   #13 = Utf8               Lookup
   #14 = Utf8               rpg/ooo/lambdas/LambdasSkillTrees$$anon$1
   #15 = Class              #14           // rpg/ooo/lambdas/LambdasSkillTrees$$anon$1
   #16 = Utf8               archeryTree
   #17 = Utf8               (Lrpg/PlayerTraits;)Lrpg/SkillTreeRepr;
   #18 = Utf8               traits
   #19 = Utf8               rpg/ooo/lambdas/Tree
   #20 = Class              #19           // rpg/ooo/lambdas/Tree
   #21 = Utf8               java/lang/invoke/LambdaMetafactory
   #22 = Class              #21           // java/lang/invoke/LambdaMetafactory
   #23 = Utf8               altMetafactory
   #24 = Utf8               (Ljava/lang/invoke/MethodHandles$Lookup;Ljava/lang/String;Ljava/lang/invoke/MethodType;[Ljava/lang/Object;)Ljava/lang/invoke/CallSite;
   #25 = NameAndType        #23:#24       // altMetafactory:(Ljava/lang/invoke/MethodHandles$Lookup;Ljava/lang/String;Ljava/lang/invoke/MethodType;[Ljava/lang/Object;)Ljava/lang/invoke/CallSite;
   #26 = Methodref          #22.#25       // java/lang/invoke/LambdaMetafactory.altMetafactory:(Ljava/lang/invoke/MethodHandles$Lookup;Ljava/lang/String;Ljava/lang/invoke/MethodType;[Ljava/lang/Object;)Ljava/lang/invoke/CallSite;
   #27 = MethodHandle       #6:#26        // invokestatic java/lang/invoke/LambdaMetafactory.altMetafactory:(Ljava/lang/invoke/MethodHandles$Lookup;Ljava/lang/String;Ljava/lang/invoke/MethodType;[Ljava/lang/Object;)Ljava/lang/invoke/CallSite;
   #28 = Utf8               (Ljava/lang/Object;)Ljava/lang/Object;
   #29 = MethodType         #28           //  (Ljava/lang/Object;)Ljava/lang/Object;
   #30 = Utf8               $anonfun$archeryTree$1$adapted
   #31 = Utf8               (Lrpg/PlayerTraits;)Ljava/lang/Object;
   #32 = NameAndType        #30:#31       // $anonfun$archeryTree$1$adapted:(Lrpg/PlayerTraits;)Ljava/lang/Object;
   #33 = Methodref          #2.#32        // rpg/ooo/lambdas/LambdasSkillTrees.$anonfun$archeryTree$1$adapted:(Lrpg/PlayerTraits;)Ljava/lang/Object;
   #34 = MethodHandle       #6:#33        // invokestatic rpg/ooo/lambdas/LambdasSkillTrees.$anonfun$archeryTree$1$adapted:(Lrpg/PlayerTraits;)Ljava/lang/Object;
   #35 = MethodType         #31           //  (Lrpg/PlayerTraits;)Ljava/lang/Object;
   #36 = Integer            7
   #37 = Integer            1
   #38 = Utf8               scala/Serializable
   #39 = Class              #38           // scala/Serializable
   #40 = Utf8               apply
   #41 = Utf8               ()Lscala/Function1;
   #42 = NameAndType        #40:#41       // apply:()Lscala/Function1;
   #43 = InvokeDynamic      #0:#42        // #0:apply:()Lscala/Function1;
   #44 = Utf8               rpg/ooo/lambdas/Step
   #45 = Class              #44           // rpg/ooo/lambdas/Step
   #46 = Utf8               $anonfun$archeryTree$2$adapted
   #47 = NameAndType        #46:#31       // $anonfun$archeryTree$2$adapted:(Lrpg/PlayerTraits;)Ljava/lang/Object;
   #48 = Methodref          #2.#47        // rpg/ooo/lambdas/LambdasSkillTrees.$anonfun$archeryTree$2$adapted:(Lrpg/PlayerTraits;)Ljava/lang/Object;
   #49 = MethodHandle       #6:#48        // invokestatic rpg/ooo/lambdas/LambdasSkillTrees.$anonfun$archeryTree$2$adapted:(Lrpg/PlayerTraits;)Ljava/lang/Object;
   #50 = InvokeDynamic      #1:#42        // #1:apply:()Lscala/Function1;
   #51 = Utf8               $anonfun$archeryTree$3$adapted
   #52 = NameAndType        #51:#31       // $anonfun$archeryTree$3$adapted:(Lrpg/PlayerTraits;)Ljava/lang/Object;
   #53 = Methodref          #2.#52        // rpg/ooo/lambdas/LambdasSkillTrees.$anonfun$archeryTree$3$adapted:(Lrpg/PlayerTraits;)Ljava/lang/Object;
   #54 = MethodHandle       #6:#53        // invokestatic rpg/ooo/lambdas/LambdasSkillTrees.$anonfun$archeryTree$3$adapted:(Lrpg/PlayerTraits;)Ljava/lang/Object;
   #55 = InvokeDynamic      #2:#42        // #2:apply:()Lscala/Function1;
   #56 = Utf8               rpg/ooo/lambdas/Skill
   #57 = Class              #56           // rpg/ooo/lambdas/Skill
   #58 = Utf8               $anonfun$archeryTree$4$adapted
   #59 = NameAndType        #58:#31       // $anonfun$archeryTree$4$adapted:(Lrpg/PlayerTraits;)Ljava/lang/Object;
   #60 = Methodref          #2.#59        // rpg/ooo/lambdas/LambdasSkillTrees.$anonfun$archeryTree$4$adapted:(Lrpg/PlayerTraits;)Ljava/lang/Object;
   #61 = MethodHandle       #6:#60        // invokestatic rpg/ooo/lambdas/LambdasSkillTrees.$anonfun$archeryTree$4$adapted:(Lrpg/PlayerTraits;)Ljava/lang/Object;
   #62 = InvokeDynamic      #3:#42        // #3:apply:()Lscala/Function1;
   #63 = Utf8               aimed
   #64 = String             #63           // aimed
   #65 = Utf8               <init>
   #66 = Utf8               (Lscala/Function1;Ljava/lang/String;)V
   #67 = NameAndType        #65:#66       // "<init>":(Lscala/Function1;Ljava/lang/String;)V
   #68 = Methodref          #57.#67       // rpg/ooo/lambdas/Skill."<init>":(Lscala/Function1;Ljava/lang/String;)V
   #69 = Utf8               $anonfun$archeryTree$5$adapted
   #70 = NameAndType        #69:#31       // $anonfun$archeryTree$5$adapted:(Lrpg/PlayerTraits;)Ljava/lang/Object;
   #71 = Methodref          #2.#70        // rpg/ooo/lambdas/LambdasSkillTrees.$anonfun$archeryTree$5$adapted:(Lrpg/PlayerTraits;)Ljava/lang/Object;
   #72 = MethodHandle       #6:#71        // invokestatic rpg/ooo/lambdas/LambdasSkillTrees.$anonfun$archeryTree$5$adapted:(Lrpg/PlayerTraits;)Ljava/lang/Object;
   #73 = InvokeDynamic      #4:#42        // #4:apply:()Lscala/Function1;
   #74 = Utf8               $anonfun$archeryTree$6$adapted
   #75 = NameAndType        #74:#31       // $anonfun$archeryTree$6$adapted:(Lrpg/PlayerTraits;)Ljava/lang/Object;
   #76 = Methodref          #2.#75        // rpg/ooo/lambdas/LambdasSkillTrees.$anonfun$archeryTree$6$adapted:(Lrpg/PlayerTraits;)Ljava/lang/Object;
   #77 = MethodHandle       #6:#76        // invokestatic rpg/ooo/lambdas/LambdasSkillTrees.$anonfun$archeryTree$6$adapted:(Lrpg/PlayerTraits;)Ljava/lang/Object;
   #78 = InvokeDynamic      #5:#42        // #5:apply:()Lscala/Function1;
   #79 = Utf8               rapid
   #80 = String             #79           // rapid
   #81 = Utf8               (Lscala/Function1;Lrpg/ooo/lambdas/Node;)V
   #82 = NameAndType        #65:#81       // "<init>":(Lscala/Function1;Lrpg/ooo/lambdas/Node;)V
   #83 = Methodref          #45.#82       // rpg/ooo/lambdas/Step."<init>":(Lscala/Function1;Lrpg/ooo/lambdas/Node;)V
   #84 = Utf8               (Lscala/Function1;Lrpg/ooo/lambdas/Node;Lrpg/ooo/lambdas/Node;)V
   #85 = NameAndType        #65:#84       // "<init>":(Lscala/Function1;Lrpg/ooo/lambdas/Node;Lrpg/ooo/lambdas/Node;)V
   #86 = Methodref          #20.#85       // rpg/ooo/lambdas/Tree."<init>":(Lscala/Function1;Lrpg/ooo/lambdas/Node;Lrpg/ooo/lambdas/Node;)V
   #87 = Utf8               $anonfun$archeryTree$7$adapted
   #88 = NameAndType        #87:#31       // $anonfun$archeryTree$7$adapted:(Lrpg/PlayerTraits;)Ljava/lang/Object;
   #89 = Methodref          #2.#88        // rpg/ooo/lambdas/LambdasSkillTrees.$anonfun$archeryTree$7$adapted:(Lrpg/PlayerTraits;)Ljava/lang/Object;
   #90 = MethodHandle       #6:#89        // invokestatic rpg/ooo/lambdas/LambdasSkillTrees.$anonfun$archeryTree$7$adapted:(Lrpg/PlayerTraits;)Ljava/lang/Object;
   #91 = InvokeDynamic      #6:#42        // #6:apply:()Lscala/Function1;
   #92 = Utf8               $anonfun$archeryTree$8$adapted
   #93 = NameAndType        #92:#31       // $anonfun$archeryTree$8$adapted:(Lrpg/PlayerTraits;)Ljava/lang/Object;
   #94 = Methodref          #2.#93        // rpg/ooo/lambdas/LambdasSkillTrees.$anonfun$archeryTree$8$adapted:(Lrpg/PlayerTraits;)Ljava/lang/Object;
   #95 = MethodHandle       #6:#94        // invokestatic rpg/ooo/lambdas/LambdasSkillTrees.$anonfun$archeryTree$8$adapted:(Lrpg/PlayerTraits;)Ljava/lang/Object;
   #96 = InvokeDynamic      #7:#42        // #7:apply:()Lscala/Function1;
   #97 = Utf8               power
   #98 = String             #97           // power
   #99 = Utf8               $anonfun$archeryTree$9$adapted
  #100 = NameAndType        #99:#31       // $anonfun$archeryTree$9$adapted:(Lrpg/PlayerTraits;)Ljava/lang/Object;
  #101 = Methodref          #2.#100       // rpg/ooo/lambdas/LambdasSkillTrees.$anonfun$archeryTree$9$adapted:(Lrpg/PlayerTraits;)Ljava/lang/Object;
  #102 = MethodHandle       #6:#101       // invokestatic rpg/ooo/lambdas/LambdasSkillTrees.$anonfun$archeryTree$9$adapted:(Lrpg/PlayerTraits;)Ljava/lang/Object;
  #103 = InvokeDynamic      #8:#42        // #8:apply:()Lscala/Function1;
  #104 = Utf8               $anonfun$archeryTree$10$adapted
  #105 = NameAndType        #104:#31      // $anonfun$archeryTree$10$adapted:(Lrpg/PlayerTraits;)Ljava/lang/Object;
  #106 = Methodref          #2.#105       // rpg/ooo/lambdas/LambdasSkillTrees.$anonfun$archeryTree$10$adapted:(Lrpg/PlayerTraits;)Ljava/lang/Object;
  #107 = MethodHandle       #6:#106       // invokestatic rpg/ooo/lambdas/LambdasSkillTrees.$anonfun$archeryTree$10$adapted:(Lrpg/PlayerTraits;)Ljava/lang/Object;
  #108 = InvokeDynamic      #9:#42        // #9:apply:()Lscala/Function1;
  #109 = Utf8               double
  #110 = String             #109          // double
  #111 = Utf8               (Lrpg/ooo/lambdas/LambdasSkillTrees;Lrpg/PlayerTraits;Lrpg/ooo/lambdas/Tree;)V
  #112 = NameAndType        #65:#111      // "<init>":(Lrpg/ooo/lambdas/LambdasSkillTrees;Lrpg/PlayerTraits;Lrpg/ooo/lambdas/Tree;)V
  #113 = Methodref          #15.#112      // rpg/ooo/lambdas/LambdasSkillTrees$$anon$1."<init>":(Lrpg/ooo/lambdas/LambdasSkillTrees;Lrpg/PlayerTraits;Lrpg/ooo/lambdas/Tree;)V
  #114 = Utf8               tree
  #115 = Utf8               Lrpg/ooo/lambdas/Tree;
  #116 = Utf8               this
  #117 = Utf8               Lrpg/ooo/lambdas/LambdasSkillTrees;
  #118 = Utf8               Lrpg/PlayerTraits;
  #119 = Utf8               $anonfun$archeryTree$1
  #120 = Utf8               (Lrpg/PlayerTraits;)I
  #121 = Utf8               x$1
  #122 = Utf8               rpg/PlayerTraits
  #123 = Class              #122          // rpg/PlayerTraits
  #124 = Utf8               dexCost
  #125 = Utf8               ()I
  #126 = NameAndType        #124:#125     // dexCost:()I
  #127 = Methodref          #123.#126     // rpg/PlayerTraits.dexCost:()I
  #128 = Utf8               $anonfun$archeryTree$2
  #129 = Utf8               x$2
  #130 = Utf8               $anonfun$archeryTree$3
  #131 = Utf8               x$3
  #132 = Utf8               wisCost
  #133 = NameAndType        #132:#125     // wisCost:()I
  #134 = Methodref          #123.#133     // rpg/PlayerTraits.wisCost:()I
  #135 = Utf8               $anonfun$archeryTree$4
  #136 = Utf8               x$4
  #137 = Utf8               $anonfun$archeryTree$5
  #138 = Utf8               x$5
  #139 = Utf8               $anonfun$archeryTree$6
  #140 = Utf8               x$6
  #141 = Utf8               $anonfun$archeryTree$7
  #142 = Utf8               x$7
  #143 = Utf8               strCost
  #144 = NameAndType        #143:#125     // strCost:()I
  #145 = Methodref          #123.#144     // rpg/PlayerTraits.strCost:()I
  #146 = Utf8               $anonfun$archeryTree$8
  #147 = Utf8               x$8
  #148 = Utf8               $anonfun$archeryTree$9
  #149 = Utf8               x$9
  #150 = Utf8               $anonfun$archeryTree$10
  #151 = Utf8               x$10
  #152 = Utf8               ()V
  #153 = NameAndType        #65:#152      // "<init>":()V
  #154 = Methodref          #4.#153       // rpg/SkillTrees."<init>":()V
  #155 = NameAndType        #119:#120     // $anonfun$archeryTree$1:(Lrpg/PlayerTraits;)I
  #156 = Methodref          #2.#155       // rpg/ooo/lambdas/LambdasSkillTrees.$anonfun$archeryTree$1:(Lrpg/PlayerTraits;)I
  #157 = Utf8               scala/runtime/BoxesRunTime
  #158 = Class              #157          // scala/runtime/BoxesRunTime
  #159 = Utf8               boxToInteger
  #160 = Utf8               (I)Ljava/lang/Integer;
  #161 = NameAndType        #159:#160     // boxToInteger:(I)Ljava/lang/Integer;
  #162 = Methodref          #158.#161     // scala/runtime/BoxesRunTime.boxToInteger:(I)Ljava/lang/Integer;
  #163 = NameAndType        #128:#120     // $anonfun$archeryTree$2:(Lrpg/PlayerTraits;)I
  #164 = Methodref          #2.#163       // rpg/ooo/lambdas/LambdasSkillTrees.$anonfun$archeryTree$2:(Lrpg/PlayerTraits;)I
  #165 = NameAndType        #130:#120     // $anonfun$archeryTree$3:(Lrpg/PlayerTraits;)I
  #166 = Methodref          #2.#165       // rpg/ooo/lambdas/LambdasSkillTrees.$anonfun$archeryTree$3:(Lrpg/PlayerTraits;)I
  #167 = NameAndType        #135:#120     // $anonfun$archeryTree$4:(Lrpg/PlayerTraits;)I
  #168 = Methodref          #2.#167       // rpg/ooo/lambdas/LambdasSkillTrees.$anonfun$archeryTree$4:(Lrpg/PlayerTraits;)I
  #169 = NameAndType        #137:#120     // $anonfun$archeryTree$5:(Lrpg/PlayerTraits;)I
  #170 = Methodref          #2.#169       // rpg/ooo/lambdas/LambdasSkillTrees.$anonfun$archeryTree$5:(Lrpg/PlayerTraits;)I
  #171 = NameAndType        #139:#120     // $anonfun$archeryTree$6:(Lrpg/PlayerTraits;)I
  #172 = Methodref          #2.#171       // rpg/ooo/lambdas/LambdasSkillTrees.$anonfun$archeryTree$6:(Lrpg/PlayerTraits;)I
  #173 = NameAndType        #141:#120     // $anonfun$archeryTree$7:(Lrpg/PlayerTraits;)I
  #174 = Methodref          #2.#173       // rpg/ooo/lambdas/LambdasSkillTrees.$anonfun$archeryTree$7:(Lrpg/PlayerTraits;)I
  #175 = NameAndType        #146:#120     // $anonfun$archeryTree$8:(Lrpg/PlayerTraits;)I
  #176 = Methodref          #2.#175       // rpg/ooo/lambdas/LambdasSkillTrees.$anonfun$archeryTree$8:(Lrpg/PlayerTraits;)I
  #177 = NameAndType        #148:#120     // $anonfun$archeryTree$9:(Lrpg/PlayerTraits;)I
  #178 = Methodref          #2.#177       // rpg/ooo/lambdas/LambdasSkillTrees.$anonfun$archeryTree$9:(Lrpg/PlayerTraits;)I
  #179 = NameAndType        #150:#120     // $anonfun$archeryTree$10:(Lrpg/PlayerTraits;)I
  #180 = Methodref          #2.#179       // rpg/ooo/lambdas/LambdasSkillTrees.$anonfun$archeryTree$10:(Lrpg/PlayerTraits;)I
  #181 = Utf8               $deserializeLambda$
  #182 = Utf8               (Ljava/lang/invoke/SerializedLambda;)Ljava/lang/Object;
  #183 = Utf8               scala/runtime/LambdaDeserialize
  #184 = Class              #183          // scala/runtime/LambdaDeserialize
  #185 = Utf8               bootstrap
  #186 = Utf8               (Ljava/lang/invoke/MethodHandles$Lookup;Ljava/lang/String;Ljava/lang/invoke/MethodType;[Ljava/lang/invoke/MethodHandle;)Ljava/lang/invoke/CallSite;
  #187 = NameAndType        #185:#186     // bootstrap:(Ljava/lang/invoke/MethodHandles$Lookup;Ljava/lang/String;Ljava/lang/invoke/MethodType;[Ljava/lang/invoke/MethodHandle;)Ljava/lang/invoke/CallSite;
  #188 = Methodref          #184.#187     // scala/runtime/LambdaDeserialize.bootstrap:(Ljava/lang/invoke/MethodHandles$Lookup;Ljava/lang/String;Ljava/lang/invoke/MethodType;[Ljava/lang/invoke/MethodHandle;)Ljava/lang/invoke/CallSite;
  #189 = MethodHandle       #6:#188       // invokestatic scala/runtime/LambdaDeserialize.bootstrap:(Ljava/lang/invoke/MethodHandles$Lookup;Ljava/lang/String;Ljava/lang/invoke/MethodType;[Ljava/lang/invoke/MethodHandle;)Ljava/lang/invoke/CallSite;
  #190 = Utf8               lambdaDeserialize
  #191 = NameAndType        #190:#182     // lambdaDeserialize:(Ljava/lang/invoke/SerializedLambda;)Ljava/lang/Object;
  #192 = InvokeDynamic      #10:#191      // #10:lambdaDeserialize:(Ljava/lang/invoke/SerializedLambda;)Ljava/lang/Object;
  #193 = Utf8               Code
  #194 = Utf8               LocalVariableTable
  #195 = Utf8               LineNumberTable
  #196 = Utf8               Signature
  #197 = Utf8               (Lrpg/PlayerTraits;)Lrpg/SkillTreeRepr<*>;
  #198 = Utf8               MethodParameters
  #199 = Utf8               BootstrapMethods
  #200 = Utf8               SourceFile
  #201 = Utf8               InnerClasses
  #202 = Utf8               RuntimeVisibleAnnotations
  #203 = Utf8               ScalaInlineInfo
  #204 = Utf8               ScalaSig
{
  public rpg.SkillTreeRepr<?> archeryTree(rpg.PlayerTraits);
    descriptor: (Lrpg/PlayerTraits;)Lrpg/SkillTreeRepr;
    flags: ACC_PUBLIC
    Code:
      stack=17, locals=3, args_size=2
         0: new           #20                 // class rpg/ooo/lambdas/Tree
         3: dup
         4: invokedynamic #43,  0             // InvokeDynamic #0:apply:()Lscala/Function1;
         9: new           #45                 // class rpg/ooo/lambdas/Step
        12: dup
        13: invokedynamic #50,  0             // InvokeDynamic #1:apply:()Lscala/Function1;
        18: new           #20                 // class rpg/ooo/lambdas/Tree
        21: dup
        22: invokedynamic #55,  0             // InvokeDynamic #2:apply:()Lscala/Function1;
        27: new           #57                 // class rpg/ooo/lambdas/Skill
        30: dup
        31: invokedynamic #62,  0             // InvokeDynamic #3:apply:()Lscala/Function1;
        36: ldc           #64                 // String aimed
        38: invokespecial #68                 // Method rpg/ooo/lambdas/Skill."<init>":(Lscala/Function1;Ljava/lang/String;)V
        41: new           #45                 // class rpg/ooo/lambdas/Step
        44: dup
        45: invokedynamic #73,  0             // InvokeDynamic #4:apply:()Lscala/Function1;
        50: new           #57                 // class rpg/ooo/lambdas/Skill
        53: dup
        54: invokedynamic #78,  0             // InvokeDynamic #5:apply:()Lscala/Function1;
        59: ldc           #80                 // String rapid
        61: invokespecial #68                 // Method rpg/ooo/lambdas/Skill."<init>":(Lscala/Function1;Ljava/lang/String;)V
        64: invokespecial #83                 // Method rpg/ooo/lambdas/Step."<init>":(Lscala/Function1;Lrpg/ooo/lambdas/Node;)V
        67: invokespecial #86                 // Method rpg/ooo/lambdas/Tree."<init>":(Lscala/Function1;Lrpg/ooo/lambdas/Node;Lrpg/ooo/lambdas/Node;)V
        70: invokespecial #83                 // Method rpg/ooo/lambdas/Step."<init>":(Lscala/Function1;Lrpg/ooo/lambdas/Node;)V
        73: new           #20                 // class rpg/ooo/lambdas/Tree
        76: dup
        77: invokedynamic #91,  0             // InvokeDynamic #6:apply:()Lscala/Function1;
        82: new           #57                 // class rpg/ooo/lambdas/Skill
        85: dup
        86: invokedynamic #96,  0             // InvokeDynamic #7:apply:()Lscala/Function1;
        91: ldc           #98                 // String power
        93: invokespecial #68                 // Method rpg/ooo/lambdas/Skill."<init>":(Lscala/Function1;Ljava/lang/String;)V
        96: new           #45                 // class rpg/ooo/lambdas/Step
        99: dup
       100: invokedynamic #103,  0            // InvokeDynamic #8:apply:()Lscala/Function1;
       105: new           #57                 // class rpg/ooo/lambdas/Skill
       108: dup
       109: invokedynamic #108,  0            // InvokeDynamic #9:apply:()Lscala/Function1;
       114: ldc           #110                // String double
       116: invokespecial #68                 // Method rpg/ooo/lambdas/Skill."<init>":(Lscala/Function1;Ljava/lang/String;)V
       119: invokespecial #83                 // Method rpg/ooo/lambdas/Step."<init>":(Lscala/Function1;Lrpg/ooo/lambdas/Node;)V
       122: invokespecial #86                 // Method rpg/ooo/lambdas/Tree."<init>":(Lscala/Function1;Lrpg/ooo/lambdas/Node;Lrpg/ooo/lambdas/Node;)V
       125: invokespecial #86                 // Method rpg/ooo/lambdas/Tree."<init>":(Lscala/Function1;Lrpg/ooo/lambdas/Node;Lrpg/ooo/lambdas/Node;)V
       128: astore_2
       129: new           #15                 // class rpg/ooo/lambdas/LambdasSkillTrees$$anon$1
       132: dup
       133: aconst_null
       134: aload_1
       135: aload_2
       136: invokespecial #113                // Method rpg/ooo/lambdas/LambdasSkillTrees$$anon$1."<init>":(Lrpg/ooo/lambdas/LambdasSkillTrees;Lrpg/PlayerTraits;Lrpg/ooo/lambdas/Tree;)V
       139: areturn
      LocalVariableTable:
        Start  Length  Slot  Name   Signature
          128      11     2  tree   Lrpg/ooo/lambdas/Tree;
            0     140     0  this   Lrpg/ooo/lambdas/LambdasSkillTrees;
            0     140     1 traits   Lrpg/PlayerTraits;
      LineNumberTable:
        line 32: 0
        line 33: 9
        line 34: 18
        line 35: 27
        line 36: 41
        line 38: 73
        line 39: 82
        line 40: 96
        line 43: 129
    Signature: #197                         // (Lrpg/PlayerTraits;)Lrpg/SkillTreeRepr<*>;
    MethodParameters:
      Name                           Flags
      traits                         final

  public static final int $anonfun$archeryTree$1(rpg.PlayerTraits);
    descriptor: (Lrpg/PlayerTraits;)I
    flags: ACC_PUBLIC, ACC_STATIC, ACC_FINAL, ACC_SYNTHETIC
    Code:
      stack=1, locals=1, args_size=1
         0: aload_0
         1: invokevirtual #127                // Method rpg/PlayerTraits.dexCost:()I
         4: ireturn
      LocalVariableTable:
        Start  Length  Slot  Name   Signature
            0       5     0   x$1   Lrpg/PlayerTraits;
      LineNumberTable:
        line 32: 0
    MethodParameters:
      Name                           Flags
      x$1                            final

  public static final int $anonfun$archeryTree$2(rpg.PlayerTraits);
    descriptor: (Lrpg/PlayerTraits;)I
    flags: ACC_PUBLIC, ACC_STATIC, ACC_FINAL, ACC_SYNTHETIC
    Code:
      stack=1, locals=1, args_size=1
         0: aload_0
         1: invokevirtual #127                // Method rpg/PlayerTraits.dexCost:()I
         4: ireturn
      LocalVariableTable:
        Start  Length  Slot  Name   Signature
            0       5     0   x$2   Lrpg/PlayerTraits;
      LineNumberTable:
        line 33: 0
    MethodParameters:
      Name                           Flags
      x$2                            final

  public static final int $anonfun$archeryTree$3(rpg.PlayerTraits);
    descriptor: (Lrpg/PlayerTraits;)I
    flags: ACC_PUBLIC, ACC_STATIC, ACC_FINAL, ACC_SYNTHETIC
    Code:
      stack=1, locals=1, args_size=1
         0: aload_0
         1: invokevirtual #134                // Method rpg/PlayerTraits.wisCost:()I
         4: ireturn
      LocalVariableTable:
        Start  Length  Slot  Name   Signature
            0       5     0   x$3   Lrpg/PlayerTraits;
      LineNumberTable:
        line 34: 0
    MethodParameters:
      Name                           Flags
      x$3                            final

  public static final int $anonfun$archeryTree$4(rpg.PlayerTraits);
    descriptor: (Lrpg/PlayerTraits;)I
    flags: ACC_PUBLIC, ACC_STATIC, ACC_FINAL, ACC_SYNTHETIC
    Code:
      stack=1, locals=1, args_size=1
         0: aload_0
         1: invokevirtual #134                // Method rpg/PlayerTraits.wisCost:()I
         4: ireturn
      LocalVariableTable:
        Start  Length  Slot  Name   Signature
            0       5     0   x$4   Lrpg/PlayerTraits;
      LineNumberTable:
        line 35: 0
    MethodParameters:
      Name                           Flags
      x$4                            final

  public static final int $anonfun$archeryTree$5(rpg.PlayerTraits);
    descriptor: (Lrpg/PlayerTraits;)I
    flags: ACC_PUBLIC, ACC_STATIC, ACC_FINAL, ACC_SYNTHETIC
    Code:
      stack=1, locals=1, args_size=1
         0: aload_0
         1: invokevirtual #134                // Method rpg/PlayerTraits.wisCost:()I
         4: ireturn
      LocalVariableTable:
        Start  Length  Slot  Name   Signature
            0       5     0   x$5   Lrpg/PlayerTraits;
      LineNumberTable:
        line 36: 0
    MethodParameters:
      Name                           Flags
      x$5                            final

  public static final int $anonfun$archeryTree$6(rpg.PlayerTraits);
    descriptor: (Lrpg/PlayerTraits;)I
    flags: ACC_PUBLIC, ACC_STATIC, ACC_FINAL, ACC_SYNTHETIC
    Code:
      stack=1, locals=1, args_size=1
         0: aload_0
         1: invokevirtual #127                // Method rpg/PlayerTraits.dexCost:()I
         4: ireturn
      LocalVariableTable:
        Start  Length  Slot  Name   Signature
            0       5     0   x$6   Lrpg/PlayerTraits;
      LineNumberTable:
        line 36: 0
    MethodParameters:
      Name                           Flags
      x$6                            final

  public static final int $anonfun$archeryTree$7(rpg.PlayerTraits);
    descriptor: (Lrpg/PlayerTraits;)I
    flags: ACC_PUBLIC, ACC_STATIC, ACC_FINAL, ACC_SYNTHETIC
    Code:
      stack=1, locals=1, args_size=1
         0: aload_0
         1: invokevirtual #145                // Method rpg/PlayerTraits.strCost:()I
         4: ireturn
      LocalVariableTable:
        Start  Length  Slot  Name   Signature
            0       5     0   x$7   Lrpg/PlayerTraits;
      LineNumberTable:
        line 38: 0
    MethodParameters:
      Name                           Flags
      x$7                            final

  public static final int $anonfun$archeryTree$8(rpg.PlayerTraits);
    descriptor: (Lrpg/PlayerTraits;)I
    flags: ACC_PUBLIC, ACC_STATIC, ACC_FINAL, ACC_SYNTHETIC
    Code:
      stack=1, locals=1, args_size=1
         0: aload_0
         1: invokevirtual #145                // Method rpg/PlayerTraits.strCost:()I
         4: ireturn
      LocalVariableTable:
        Start  Length  Slot  Name   Signature
            0       5     0   x$8   Lrpg/PlayerTraits;
      LineNumberTable:
        line 39: 0
    MethodParameters:
      Name                           Flags
      x$8                            final

  public static final int $anonfun$archeryTree$9(rpg.PlayerTraits);
    descriptor: (Lrpg/PlayerTraits;)I
    flags: ACC_PUBLIC, ACC_STATIC, ACC_FINAL, ACC_SYNTHETIC
    Code:
      stack=1, locals=1, args_size=1
         0: aload_0
         1: invokevirtual #145                // Method rpg/PlayerTraits.strCost:()I
         4: ireturn
      LocalVariableTable:
        Start  Length  Slot  Name   Signature
            0       5     0   x$9   Lrpg/PlayerTraits;
      LineNumberTable:
        line 40: 0
    MethodParameters:
      Name                           Flags
      x$9                            final

  public static final int $anonfun$archeryTree$10(rpg.PlayerTraits);
    descriptor: (Lrpg/PlayerTraits;)I
    flags: ACC_PUBLIC, ACC_STATIC, ACC_FINAL, ACC_SYNTHETIC
    Code:
      stack=1, locals=1, args_size=1
         0: aload_0
         1: invokevirtual #127                // Method rpg/PlayerTraits.dexCost:()I
         4: ireturn
      LocalVariableTable:
        Start  Length  Slot  Name   Signature
            0       5     0  x$10   Lrpg/PlayerTraits;
      LineNumberTable:
        line 40: 0
    MethodParameters:
      Name                           Flags
      x$10                           final

  public rpg.ooo.lambdas.LambdasSkillTrees();
    descriptor: ()V
    flags: ACC_PUBLIC
    Code:
      stack=1, locals=1, args_size=1
         0: aload_0
         1: invokespecial #154                // Method rpg/SkillTrees."<init>":()V
         4: return
      LocalVariableTable:
        Start  Length  Slot  Name   Signature
            0       5     0  this   Lrpg/ooo/lambdas/LambdasSkillTrees;
      LineNumberTable:
        line 24: 0

  public static final java.lang.Object $anonfun$archeryTree$1$adapted(rpg.PlayerTraits);
    descriptor: (Lrpg/PlayerTraits;)Ljava/lang/Object;
    flags: ACC_PUBLIC, ACC_STATIC, ACC_FINAL, ACC_SYNTHETIC
    Code:
      stack=1, locals=1, args_size=1
         0: aload_0
         1: invokestatic  #156                // Method $anonfun$archeryTree$1:(Lrpg/PlayerTraits;)I
         4: invokestatic  #162                // Method scala/runtime/BoxesRunTime.boxToInteger:(I)Ljava/lang/Integer;
         7: areturn
      LocalVariableTable:
        Start  Length  Slot  Name   Signature
            0       8     0   x$1   Lrpg/PlayerTraits;
      LineNumberTable:
        line 32: 0
    MethodParameters:
      Name                           Flags
      x$1                            final

  public static final java.lang.Object $anonfun$archeryTree$2$adapted(rpg.PlayerTraits);
    descriptor: (Lrpg/PlayerTraits;)Ljava/lang/Object;
    flags: ACC_PUBLIC, ACC_STATIC, ACC_FINAL, ACC_SYNTHETIC
    Code:
      stack=1, locals=1, args_size=1
         0: aload_0
         1: invokestatic  #164                // Method $anonfun$archeryTree$2:(Lrpg/PlayerTraits;)I
         4: invokestatic  #162                // Method scala/runtime/BoxesRunTime.boxToInteger:(I)Ljava/lang/Integer;
         7: areturn
      LocalVariableTable:
        Start  Length  Slot  Name   Signature
            0       8     0   x$2   Lrpg/PlayerTraits;
      LineNumberTable:
        line 33: 0
    MethodParameters:
      Name                           Flags
      x$2                            final

  public static final java.lang.Object $anonfun$archeryTree$3$adapted(rpg.PlayerTraits);
    descriptor: (Lrpg/PlayerTraits;)Ljava/lang/Object;
    flags: ACC_PUBLIC, ACC_STATIC, ACC_FINAL, ACC_SYNTHETIC
    Code:
      stack=1, locals=1, args_size=1
         0: aload_0
         1: invokestatic  #166                // Method $anonfun$archeryTree$3:(Lrpg/PlayerTraits;)I
         4: invokestatic  #162                // Method scala/runtime/BoxesRunTime.boxToInteger:(I)Ljava/lang/Integer;
         7: areturn
      LocalVariableTable:
        Start  Length  Slot  Name   Signature
            0       8     0   x$3   Lrpg/PlayerTraits;
      LineNumberTable:
        line 34: 0
    MethodParameters:
      Name                           Flags
      x$3                            final

  public static final java.lang.Object $anonfun$archeryTree$4$adapted(rpg.PlayerTraits);
    descriptor: (Lrpg/PlayerTraits;)Ljava/lang/Object;
    flags: ACC_PUBLIC, ACC_STATIC, ACC_FINAL, ACC_SYNTHETIC
    Code:
      stack=1, locals=1, args_size=1
         0: aload_0
         1: invokestatic  #168                // Method $anonfun$archeryTree$4:(Lrpg/PlayerTraits;)I
         4: invokestatic  #162                // Method scala/runtime/BoxesRunTime.boxToInteger:(I)Ljava/lang/Integer;
         7: areturn
      LocalVariableTable:
        Start  Length  Slot  Name   Signature
            0       8     0   x$4   Lrpg/PlayerTraits;
      LineNumberTable:
        line 35: 0
    MethodParameters:
      Name                           Flags
      x$4                            final

  public static final java.lang.Object $anonfun$archeryTree$5$adapted(rpg.PlayerTraits);
    descriptor: (Lrpg/PlayerTraits;)Ljava/lang/Object;
    flags: ACC_PUBLIC, ACC_STATIC, ACC_FINAL, ACC_SYNTHETIC
    Code:
      stack=1, locals=1, args_size=1
         0: aload_0
         1: invokestatic  #170                // Method $anonfun$archeryTree$5:(Lrpg/PlayerTraits;)I
         4: invokestatic  #162                // Method scala/runtime/BoxesRunTime.boxToInteger:(I)Ljava/lang/Integer;
         7: areturn
      LocalVariableTable:
        Start  Length  Slot  Name   Signature
            0       8     0   x$5   Lrpg/PlayerTraits;
      LineNumberTable:
        line 36: 0
    MethodParameters:
      Name                           Flags
      x$5                            final

  public static final java.lang.Object $anonfun$archeryTree$6$adapted(rpg.PlayerTraits);
    descriptor: (Lrpg/PlayerTraits;)Ljava/lang/Object;
    flags: ACC_PUBLIC, ACC_STATIC, ACC_FINAL, ACC_SYNTHETIC
    Code:
      stack=1, locals=1, args_size=1
         0: aload_0
         1: invokestatic  #172                // Method $anonfun$archeryTree$6:(Lrpg/PlayerTraits;)I
         4: invokestatic  #162                // Method scala/runtime/BoxesRunTime.boxToInteger:(I)Ljava/lang/Integer;
         7: areturn
      LocalVariableTable:
        Start  Length  Slot  Name   Signature
            0       8     0   x$6   Lrpg/PlayerTraits;
      LineNumberTable:
        line 36: 0
    MethodParameters:
      Name                           Flags
      x$6                            final

  public static final java.lang.Object $anonfun$archeryTree$7$adapted(rpg.PlayerTraits);
    descriptor: (Lrpg/PlayerTraits;)Ljava/lang/Object;
    flags: ACC_PUBLIC, ACC_STATIC, ACC_FINAL, ACC_SYNTHETIC
    Code:
      stack=1, locals=1, args_size=1
         0: aload_0
         1: invokestatic  #174                // Method $anonfun$archeryTree$7:(Lrpg/PlayerTraits;)I
         4: invokestatic  #162                // Method scala/runtime/BoxesRunTime.boxToInteger:(I)Ljava/lang/Integer;
         7: areturn
      LocalVariableTable:
        Start  Length  Slot  Name   Signature
            0       8     0   x$7   Lrpg/PlayerTraits;
      LineNumberTable:
        line 38: 0
    MethodParameters:
      Name                           Flags
      x$7                            final

  public static final java.lang.Object $anonfun$archeryTree$8$adapted(rpg.PlayerTraits);
    descriptor: (Lrpg/PlayerTraits;)Ljava/lang/Object;
    flags: ACC_PUBLIC, ACC_STATIC, ACC_FINAL, ACC_SYNTHETIC
    Code:
      stack=1, locals=1, args_size=1
         0: aload_0
         1: invokestatic  #176                // Method $anonfun$archeryTree$8:(Lrpg/PlayerTraits;)I
         4: invokestatic  #162                // Method scala/runtime/BoxesRunTime.boxToInteger:(I)Ljava/lang/Integer;
         7: areturn
      LocalVariableTable:
        Start  Length  Slot  Name   Signature
            0       8     0   x$8   Lrpg/PlayerTraits;
      LineNumberTable:
        line 39: 0
    MethodParameters:
      Name                           Flags
      x$8                            final

  public static final java.lang.Object $anonfun$archeryTree$9$adapted(rpg.PlayerTraits);
    descriptor: (Lrpg/PlayerTraits;)Ljava/lang/Object;
    flags: ACC_PUBLIC, ACC_STATIC, ACC_FINAL, ACC_SYNTHETIC
    Code:
      stack=1, locals=1, args_size=1
         0: aload_0
         1: invokestatic  #178                // Method $anonfun$archeryTree$9:(Lrpg/PlayerTraits;)I
         4: invokestatic  #162                // Method scala/runtime/BoxesRunTime.boxToInteger:(I)Ljava/lang/Integer;
         7: areturn
      LocalVariableTable:
        Start  Length  Slot  Name   Signature
            0       8     0   x$9   Lrpg/PlayerTraits;
      LineNumberTable:
        line 40: 0
    MethodParameters:
      Name                           Flags
      x$9                            final

  public static final java.lang.Object $anonfun$archeryTree$10$adapted(rpg.PlayerTraits);
    descriptor: (Lrpg/PlayerTraits;)Ljava/lang/Object;
    flags: ACC_PUBLIC, ACC_STATIC, ACC_FINAL, ACC_SYNTHETIC
    Code:
      stack=1, locals=1, args_size=1
         0: aload_0
         1: invokestatic  #180                // Method $anonfun$archeryTree$10:(Lrpg/PlayerTraits;)I
         4: invokestatic  #162                // Method scala/runtime/BoxesRunTime.boxToInteger:(I)Ljava/lang/Integer;
         7: areturn
      LocalVariableTable:
        Start  Length  Slot  Name   Signature
            0       8     0  x$10   Lrpg/PlayerTraits;
      LineNumberTable:
        line 40: 0
    MethodParameters:
      Name                           Flags
      x$10                           final

  private static java.lang.Object $deserializeLambda$(java.lang.invoke.SerializedLambda);
    descriptor: (Ljava/lang/invoke/SerializedLambda;)Ljava/lang/Object;
    flags: ACC_PRIVATE, ACC_STATIC, ACC_SYNTHETIC
    Code:
      stack=1, locals=1, args_size=1
         0: aload_0
         1: invokedynamic #192,  0            // InvokeDynamic #10:lambdaDeserialize:(Ljava/lang/invoke/SerializedLambda;)Ljava/lang/Object;
         6: areturn
}
BootstrapMethods:
  0: #27 invokestatic java/lang/invoke/LambdaMetafactory.altMetafactory:(Ljava/lang/invoke/MethodHandles$Lookup;Ljava/lang/String;Ljava/lang/invoke/MethodType;[Ljava/lang/Object;)Ljava/lang/invoke/CallSite;
    Method arguments:
      #29 (Ljava/lang/Object;)Ljava/lang/Object;
      #34 invokestatic rpg/ooo/lambdas/LambdasSkillTrees.$anonfun$archeryTree$1$adapted:(Lrpg/PlayerTraits;)Ljava/lang/Object;
      #35 (Lrpg/PlayerTraits;)Ljava/lang/Object;
      #36 7
      #37 1
      #39 scala/Serializable
      #37 1
      #35 (Lrpg/PlayerTraits;)Ljava/lang/Object;
  1: #27 invokestatic java/lang/invoke/LambdaMetafactory.altMetafactory:(Ljava/lang/invoke/MethodHandles$Lookup;Ljava/lang/String;Ljava/lang/invoke/MethodType;[Ljava/lang/Object;)Ljava/lang/invoke/CallSite;
    Method arguments:
      #29 (Ljava/lang/Object;)Ljava/lang/Object;
      #49 invokestatic rpg/ooo/lambdas/LambdasSkillTrees.$anonfun$archeryTree$2$adapted:(Lrpg/PlayerTraits;)Ljava/lang/Object;
      #35 (Lrpg/PlayerTraits;)Ljava/lang/Object;
      #36 7
      #37 1
      #39 scala/Serializable
      #37 1
      #35 (Lrpg/PlayerTraits;)Ljava/lang/Object;
  2: #27 invokestatic java/lang/invoke/LambdaMetafactory.altMetafactory:(Ljava/lang/invoke/MethodHandles$Lookup;Ljava/lang/String;Ljava/lang/invoke/MethodType;[Ljava/lang/Object;)Ljava/lang/invoke/CallSite;
    Method arguments:
      #29 (Ljava/lang/Object;)Ljava/lang/Object;
      #54 invokestatic rpg/ooo/lambdas/LambdasSkillTrees.$anonfun$archeryTree$3$adapted:(Lrpg/PlayerTraits;)Ljava/lang/Object;
      #35 (Lrpg/PlayerTraits;)Ljava/lang/Object;
      #36 7
      #37 1
      #39 scala/Serializable
      #37 1
      #35 (Lrpg/PlayerTraits;)Ljava/lang/Object;
  3: #27 invokestatic java/lang/invoke/LambdaMetafactory.altMetafactory:(Ljava/lang/invoke/MethodHandles$Lookup;Ljava/lang/String;Ljava/lang/invoke/MethodType;[Ljava/lang/Object;)Ljava/lang/invoke/CallSite;
    Method arguments:
      #29 (Ljava/lang/Object;)Ljava/lang/Object;
      #61 invokestatic rpg/ooo/lambdas/LambdasSkillTrees.$anonfun$archeryTree$4$adapted:(Lrpg/PlayerTraits;)Ljava/lang/Object;
      #35 (Lrpg/PlayerTraits;)Ljava/lang/Object;
      #36 7
      #37 1
      #39 scala/Serializable
      #37 1
      #35 (Lrpg/PlayerTraits;)Ljava/lang/Object;
  4: #27 invokestatic java/lang/invoke/LambdaMetafactory.altMetafactory:(Ljava/lang/invoke/MethodHandles$Lookup;Ljava/lang/String;Ljava/lang/invoke/MethodType;[Ljava/lang/Object;)Ljava/lang/invoke/CallSite;
    Method arguments:
      #29 (Ljava/lang/Object;)Ljava/lang/Object;
      #72 invokestatic rpg/ooo/lambdas/LambdasSkillTrees.$anonfun$archeryTree$5$adapted:(Lrpg/PlayerTraits;)Ljava/lang/Object;
      #35 (Lrpg/PlayerTraits;)Ljava/lang/Object;
      #36 7
      #37 1
      #39 scala/Serializable
      #37 1
      #35 (Lrpg/PlayerTraits;)Ljava/lang/Object;
  5: #27 invokestatic java/lang/invoke/LambdaMetafactory.altMetafactory:(Ljava/lang/invoke/MethodHandles$Lookup;Ljava/lang/String;Ljava/lang/invoke/MethodType;[Ljava/lang/Object;)Ljava/lang/invoke/CallSite;
    Method arguments:
      #29 (Ljava/lang/Object;)Ljava/lang/Object;
      #77 invokestatic rpg/ooo/lambdas/LambdasSkillTrees.$anonfun$archeryTree$6$adapted:(Lrpg/PlayerTraits;)Ljava/lang/Object;
      #35 (Lrpg/PlayerTraits;)Ljava/lang/Object;
      #36 7
      #37 1
      #39 scala/Serializable
      #37 1
      #35 (Lrpg/PlayerTraits;)Ljava/lang/Object;
  6: #27 invokestatic java/lang/invoke/LambdaMetafactory.altMetafactory:(Ljava/lang/invoke/MethodHandles$Lookup;Ljava/lang/String;Ljava/lang/invoke/MethodType;[Ljava/lang/Object;)Ljava/lang/invoke/CallSite;
    Method arguments:
      #29 (Ljava/lang/Object;)Ljava/lang/Object;
      #90 invokestatic rpg/ooo/lambdas/LambdasSkillTrees.$anonfun$archeryTree$7$adapted:(Lrpg/PlayerTraits;)Ljava/lang/Object;
      #35 (Lrpg/PlayerTraits;)Ljava/lang/Object;
      #36 7
      #37 1
      #39 scala/Serializable
      #37 1
      #35 (Lrpg/PlayerTraits;)Ljava/lang/Object;
  7: #27 invokestatic java/lang/invoke/LambdaMetafactory.altMetafactory:(Ljava/lang/invoke/MethodHandles$Lookup;Ljava/lang/String;Ljava/lang/invoke/MethodType;[Ljava/lang/Object;)Ljava/lang/invoke/CallSite;
    Method arguments:
      #29 (Ljava/lang/Object;)Ljava/lang/Object;
      #95 invokestatic rpg/ooo/lambdas/LambdasSkillTrees.$anonfun$archeryTree$8$adapted:(Lrpg/PlayerTraits;)Ljava/lang/Object;
      #35 (Lrpg/PlayerTraits;)Ljava/lang/Object;
      #36 7
      #37 1
      #39 scala/Serializable
      #37 1
      #35 (Lrpg/PlayerTraits;)Ljava/lang/Object;
  8: #27 invokestatic java/lang/invoke/LambdaMetafactory.altMetafactory:(Ljava/lang/invoke/MethodHandles$Lookup;Ljava/lang/String;Ljava/lang/invoke/MethodType;[Ljava/lang/Object;)Ljava/lang/invoke/CallSite;
    Method arguments:
      #29 (Ljava/lang/Object;)Ljava/lang/Object;
      #102 invokestatic rpg/ooo/lambdas/LambdasSkillTrees.$anonfun$archeryTree$9$adapted:(Lrpg/PlayerTraits;)Ljava/lang/Object;
      #35 (Lrpg/PlayerTraits;)Ljava/lang/Object;
      #36 7
      #37 1
      #39 scala/Serializable
      #37 1
      #35 (Lrpg/PlayerTraits;)Ljava/lang/Object;
  9: #27 invokestatic java/lang/invoke/LambdaMetafactory.altMetafactory:(Ljava/lang/invoke/MethodHandles$Lookup;Ljava/lang/String;Ljava/lang/invoke/MethodType;[Ljava/lang/Object;)Ljava/lang/invoke/CallSite;
    Method arguments:
      #29 (Ljava/lang/Object;)Ljava/lang/Object;
      #107 invokestatic rpg/ooo/lambdas/LambdasSkillTrees.$anonfun$archeryTree$10$adapted:(Lrpg/PlayerTraits;)Ljava/lang/Object;
      #35 (Lrpg/PlayerTraits;)Ljava/lang/Object;
      #36 7
      #37 1
      #39 scala/Serializable
      #37 1
      #35 (Lrpg/PlayerTraits;)Ljava/lang/Object;
  10: #189 invokestatic scala/runtime/LambdaDeserialize.bootstrap:(Ljava/lang/invoke/MethodHandles$Lookup;Ljava/lang/String;Ljava/lang/invoke/MethodType;[Ljava/lang/invoke/MethodHandle;)Ljava/lang/invoke/CallSite;
    Method arguments:
      #34 invokestatic rpg/ooo/lambdas/LambdasSkillTrees.$anonfun$archeryTree$1$adapted:(Lrpg/PlayerTraits;)Ljava/lang/Object;
      #49 invokestatic rpg/ooo/lambdas/LambdasSkillTrees.$anonfun$archeryTree$2$adapted:(Lrpg/PlayerTraits;)Ljava/lang/Object;
      #54 invokestatic rpg/ooo/lambdas/LambdasSkillTrees.$anonfun$archeryTree$3$adapted:(Lrpg/PlayerTraits;)Ljava/lang/Object;
      #61 invokestatic rpg/ooo/lambdas/LambdasSkillTrees.$anonfun$archeryTree$4$adapted:(Lrpg/PlayerTraits;)Ljava/lang/Object;
      #72 invokestatic rpg/ooo/lambdas/LambdasSkillTrees.$anonfun$archeryTree$5$adapted:(Lrpg/PlayerTraits;)Ljava/lang/Object;
      #77 invokestatic rpg/ooo/lambdas/LambdasSkillTrees.$anonfun$archeryTree$6$adapted:(Lrpg/PlayerTraits;)Ljava/lang/Object;
      #90 invokestatic rpg/ooo/lambdas/LambdasSkillTrees.$anonfun$archeryTree$7$adapted:(Lrpg/PlayerTraits;)Ljava/lang/Object;
      #95 invokestatic rpg/ooo/lambdas/LambdasSkillTrees.$anonfun$archeryTree$8$adapted:(Lrpg/PlayerTraits;)Ljava/lang/Object;
      #102 invokestatic rpg/ooo/lambdas/LambdasSkillTrees.$anonfun$archeryTree$9$adapted:(Lrpg/PlayerTraits;)Ljava/lang/Object;
      #107 invokestatic rpg/ooo/lambdas/LambdasSkillTrees.$anonfun$archeryTree$10$adapted:(Lrpg/PlayerTraits;)Ljava/lang/Object;
SourceFile: "LambdasSkillTrees.scala"
InnerClasses:
     public static final #13= #10 of #12; //Lookup=class java/lang/invoke/MethodHandles$Lookup of class java/lang/invoke/MethodHandles
     public final #15; //class rpg/ooo/lambdas/LambdasSkillTrees$$anon$1
RuntimeVisibleAnnotations:
  0: #6(#7=s#8)
Error: unknown attribute
  ScalaInlineInfo: length = 0x72
   01 00 00 16 00 1E 00 1F 01 00 77 00 78 01 00 68
   00 1F 01 00 96 00 78 01 00 2E 00 1F 01 00 80 00
   78 01 00 33 00 1F 01 00 82 00 78 01 00 3A 00 1F
   01 00 87 00 78 01 00 45 00 1F 01 00 89 00 78 01
   00 4A 00 1F 01 00 8B 00 78 01 00 57 00 1F 01 00
   8D 00 78 01 00 5C 00 1F 01 00 92 00 78 01 00 63
   00 1F 01 00 94 00 78 01 00 41 00 98 00 00 10 00
   11 00
Error: unknown attribute
  ScalaSig: length = 0x3
   05 00 00
