Compiled from "TypeclassSkillTrees.scala"
public final class rpg.typeclass.naive.WisStep$ implements scala.Serializable {
  public static rpg.typeclass.naive.WisStep$ MODULE$;

  public static {};
    Code:
       0: new           #2                  // class rpg/typeclass/naive/WisStep$
       3: invokespecial #14                 // Method "<init>":()V
       6: return

  public final java.lang.String toString();
    Code:
       0: ldc           #18                 // String WisStep
       2: areturn

  public <N> rpg.typeclass.naive.WisStep<N> apply(N);
    Code:
       0: new           #24                 // class rpg/typeclass/naive/WisStep
       3: dup
       4: aload_1
       5: invokespecial #27                 // Method rpg/typeclass/naive/WisStep."<init>":(Ljava/lang/Object;)V
       8: areturn

  public <N> scala.Option<N> unapply(rpg.typeclass.naive.WisStep<N>);
    Code:
       0: aload_1
       1: ifnonnull     10
       4: getstatic     #36                 // Field scala/None$.MODULE$:Lscala/None$;
       7: goto          21
      10: new           #38                 // class scala/Some
      13: dup
      14: aload_1
      15: invokevirtual #41                 // Method rpg/typeclass/naive/WisStep.to:()Ljava/lang/Object;
      18: invokespecial #42                 // Method scala/Some."<init>":(Ljava/lang/Object;)V
      21: areturn

  private java.lang.Object readResolve();
    Code:
       0: getstatic     #48                 // Field MODULE$:Lrpg/typeclass/naive/WisStep$;
       3: areturn

  private rpg.typeclass.naive.WisStep$();
    Code:
       0: aload_0
       1: invokespecial #49                 // Method java/lang/Object."<init>":()V
       4: aload_0
       5: putstatic     #48                 // Field MODULE$:Lrpg/typeclass/naive/WisStep$;
       8: return
}
