Classfile /home/krzysiek/workspace/scala-bcode-cutter/pref/target/scala-2.12/classes/rpg/typeclass/naive/DexSkill.class
  Last modified Apr 8, 2018; size 4459 bytes
  MD5 checksum e735a42abb81f8a54beb96a7c56637b4
  Compiled from "TypeclassSkillTrees.scala"
public class rpg.typeclass.naive.DexSkill implements rpg.typeclass.naive.Node,scala.Product,scala.Serializable
  minor version: 0
  major version: 52
  flags: ACC_PUBLIC, ACC_SUPER
Constant pool:
    #1 = Utf8               rpg/typeclass/naive/DexSkill
    #2 = Class              #1            // rpg/typeclass/naive/DexSkill
    #3 = Utf8               java/lang/Object
    #4 = Class              #3            // java/lang/Object
    #5 = Utf8               rpg/typeclass/naive/Node
    #6 = Class              #5            // rpg/typeclass/naive/Node
    #7 = Utf8               scala/Product
    #8 = Class              #7            // scala/Product
    #9 = Utf8               scala/Serializable
   #10 = Class              #9            // scala/Serializable
   #11 = Utf8               TypeclassSkillTrees.scala
   #12 = Utf8               Lscala/reflect/ScalaSignature;
   #13 = Utf8               bytes
   #14 = Utf8               bB&R3y'.LG\tQA\1jmT!!QL/Z2mCN(\"AIxmQF-qQ\"5\tQa]2bYL!a\rsPU3g!\t\t\"#D\t\"AO_,CA\t1BBAQe>$Wo;-ABA\r\r1VM]5bY&TM7f!YA!f\na8b[,!\t=r!aHbQ\"A\tBAs_>$h(%1K]3eKL!AJ\rM#(/8h\t!C*\tE\t!q-\3!Y\"-aN\5u}QQF\t#AQaAuAq\r'd_BLHCA3Yr%AAuAqQ'd_BLHZ3gCVdGJYR#!H,a\"! iR!aUt7\r[3dW$'BA\r)\tgN\8uCRLwN\i#8dQ7.3WCJLM\2f\t!!AB\tQ:pIVG:fM&DX#A\"KU\"A#;7b]TSU4-'\"91\nAA\na9s_,8\r^!sSRLX#A'-qBA(\r\rIe#\t\t\"S9(o3vGR,E.Z7f]R$\"a,-!BA+\r\r\te./B\t1N\rAH%\r3\t\t\"[=(o3vGRLE/:bi>X#A.q{6+D^\tqF\"d_2dWm;j_:L!Y/%#XM]1u_JDqA1-dC:,/^1m)\t!w\rK&a\r>|G.Z1o9-!AAMCq!#.iCND7i3f)ib7%\t%\\ti>FO]5oOR\t1\tCpI\t9\rX/7t)\t!CX]\tA*M!EiAA)=TW&dGk9AAA18cA;x/A!p_.I(B>\rXO;j[L!`=#7:bGR4UO\2uS>tC,kaFuaW/!AF5D\"av%\t)!\=5\n9\r!\n)!CA\tq!8baBdUBuI1!a\ry^5p]\"IqCA\r!Lq\"CAkIBA-X-3SKN|GN^3}c#\"%1E#\r='.Z2u
   #15 = Utf8               name
   #16 = Utf8               Ljava/lang/String;
   #17 = Utf8               unapply
   #18 = Utf8               (Lrpg/typeclass/naive/DexSkill;)Lscala/Option;
   #19 = Utf8               rpg/typeclass/naive/DexSkill$
   #20 = Class              #19           // rpg/typeclass/naive/DexSkill$
   #21 = Utf8               MODULE$
   #22 = Utf8               Lrpg/typeclass/naive/DexSkill$;
   #23 = NameAndType        #21:#22       // MODULE$:Lrpg/typeclass/naive/DexSkill$;
   #24 = Fieldref           #20.#23       // rpg/typeclass/naive/DexSkill$.MODULE$:Lrpg/typeclass/naive/DexSkill$;
   #25 = NameAndType        #17:#18       // unapply:(Lrpg/typeclass/naive/DexSkill;)Lscala/Option;
   #26 = Methodref          #20.#25       // rpg/typeclass/naive/DexSkill$.unapply:(Lrpg/typeclass/naive/DexSkill;)Lscala/Option;
   #27 = Utf8               apply
   #28 = Utf8               (Ljava/lang/String;)Lrpg/typeclass/naive/DexSkill;
   #29 = NameAndType        #27:#28       // apply:(Ljava/lang/String;)Lrpg/typeclass/naive/DexSkill;
   #30 = Methodref          #20.#29       // rpg/typeclass/naive/DexSkill$.apply:(Ljava/lang/String;)Lrpg/typeclass/naive/DexSkill;
   #31 = Utf8               andThen
   #32 = Utf8               (Lscala/Function1;)Lscala/Function1;
   #33 = NameAndType        #31:#32       // andThen:(Lscala/Function1;)Lscala/Function1;
   #34 = Methodref          #20.#33       // rpg/typeclass/naive/DexSkill$.andThen:(Lscala/Function1;)Lscala/Function1;
   #35 = Utf8               compose
   #36 = NameAndType        #35:#32       // compose:(Lscala/Function1;)Lscala/Function1;
   #37 = Methodref          #20.#36       // rpg/typeclass/naive/DexSkill$.compose:(Lscala/Function1;)Lscala/Function1;
   #38 = Utf8               ()Ljava/lang/String;
   #39 = NameAndType        #15:#16       // name:Ljava/lang/String;
   #40 = Fieldref           #2.#39        // rpg/typeclass/naive/DexSkill.name:Ljava/lang/String;
   #41 = Utf8               this
   #42 = Utf8               Lrpg/typeclass/naive/DexSkill;
   #43 = Utf8               copy
   #44 = Utf8               <init>
   #45 = Utf8               (Ljava/lang/String;)V
   #46 = NameAndType        #44:#45       // "<init>":(Ljava/lang/String;)V
   #47 = Methodref          #2.#46        // rpg/typeclass/naive/DexSkill."<init>":(Ljava/lang/String;)V
   #48 = Utf8               copy$default$1
   #49 = NameAndType        #15:#38       // name:()Ljava/lang/String;
   #50 = Methodref          #2.#49        // rpg/typeclass/naive/DexSkill.name:()Ljava/lang/String;
   #51 = Utf8               productPrefix
   #52 = Utf8               DexSkill
   #53 = String             #52           // DexSkill
   #54 = Utf8               productArity
   #55 = Utf8               ()I
   #56 = Utf8               productElement
   #57 = Utf8               (I)Ljava/lang/Object;
   #58 = Utf8               x$1
   #59 = Utf8               java/lang/IndexOutOfBoundsException
   #60 = Class              #59           // java/lang/IndexOutOfBoundsException
   #61 = Utf8               scala/runtime/BoxesRunTime
   #62 = Class              #61           // scala/runtime/BoxesRunTime
   #63 = Utf8               boxToInteger
   #64 = Utf8               (I)Ljava/lang/Integer;
   #65 = NameAndType        #63:#64       // boxToInteger:(I)Ljava/lang/Integer;
   #66 = Methodref          #62.#65       // scala/runtime/BoxesRunTime.boxToInteger:(I)Ljava/lang/Integer;
   #67 = Utf8               toString
   #68 = NameAndType        #67:#38       // toString:()Ljava/lang/String;
   #69 = Methodref          #4.#68        // java/lang/Object.toString:()Ljava/lang/String;
   #70 = Methodref          #60.#46       // java/lang/IndexOutOfBoundsException."<init>":(Ljava/lang/String;)V
   #71 = Utf8               I
   #72 = Utf8               java/lang/String
   #73 = Class              #72           // java/lang/String
   #74 = Utf8               productIterator
   #75 = Utf8               ()Lscala/collection/Iterator;
   #76 = Utf8               scala/runtime/ScalaRunTime$
   #77 = Class              #76           // scala/runtime/ScalaRunTime$
   #78 = Utf8               Lscala/runtime/ScalaRunTime$;
   #79 = NameAndType        #21:#78       // MODULE$:Lscala/runtime/ScalaRunTime$;
   #80 = Fieldref           #77.#79       // scala/runtime/ScalaRunTime$.MODULE$:Lscala/runtime/ScalaRunTime$;
   #81 = Utf8               typedProductIterator
   #82 = Utf8               (Lscala/Product;)Lscala/collection/Iterator;
   #83 = NameAndType        #81:#82       // typedProductIterator:(Lscala/Product;)Lscala/collection/Iterator;
   #84 = Methodref          #77.#83       // scala/runtime/ScalaRunTime$.typedProductIterator:(Lscala/Product;)Lscala/collection/Iterator;
   #85 = Utf8               canEqual
   #86 = Utf8               (Ljava/lang/Object;)Z
   #87 = Utf8               Ljava/lang/Object;
   #88 = Utf8               hashCode
   #89 = Utf8               _hashCode
   #90 = Utf8               (Lscala/Product;)I
   #91 = NameAndType        #89:#90       // _hashCode:(Lscala/Product;)I
   #92 = Methodref          #77.#91       // scala/runtime/ScalaRunTime$._hashCode:(Lscala/Product;)I
   #93 = Utf8               _toString
   #94 = Utf8               (Lscala/Product;)Ljava/lang/String;
   #95 = NameAndType        #93:#94       // _toString:(Lscala/Product;)Ljava/lang/String;
   #96 = Methodref          #77.#95       // scala/runtime/ScalaRunTime$._toString:(Lscala/Product;)Ljava/lang/String;
   #97 = Utf8               equals
   #98 = NameAndType        #97:#86       // equals:(Ljava/lang/Object;)Z
   #99 = Methodref          #4.#98        // java/lang/Object.equals:(Ljava/lang/Object;)Z
  #100 = NameAndType        #85:#86       // canEqual:(Ljava/lang/Object;)Z
  #101 = Methodref          #2.#100       // rpg/typeclass/naive/DexSkill.canEqual:(Ljava/lang/Object;)Z
  #102 = Utf8               ()V
  #103 = NameAndType        #44:#102      // "<init>":()V
  #104 = Methodref          #4.#103       // java/lang/Object."<init>":()V
  #105 = Utf8               $init$
  #106 = Utf8               (Lscala/Product;)V
  #107 = NameAndType        #105:#106     // $init$:(Lscala/Product;)V
  #108 = InterfaceMethodref #8.#107       // scala/Product.$init$:(Lscala/Product;)V
  #109 = Utf8               Code
  #110 = Utf8               Signature
  #111 = Utf8               (Lrpg/typeclass/naive/DexSkill;)Lscala/Option<Ljava/lang/String;>;
  #112 = Utf8               <A:Ljava/lang/Object;>(Lscala/Function1<Lrpg/typeclass/naive/DexSkill;TA;>;)Lscala/Function1<Ljava/lang/String;TA;>;
  #113 = Utf8               <A:Ljava/lang/Object;>(Lscala/Function1<TA;Ljava/lang/String;>;)Lscala/Function1<TA;Lrpg/typeclass/naive/DexSkill;>;
  #114 = Utf8               LocalVariableTable
  #115 = Utf8               LineNumberTable
  #116 = Utf8               MethodParameters
  #117 = Utf8               StackMapTable
  #118 = Utf8               ()Lscala/collection/Iterator<Ljava/lang/Object;>;
  #119 = Utf8               SourceFile
  #120 = Utf8               RuntimeVisibleAnnotations
  #121 = Utf8               ScalaInlineInfo
  #122 = Utf8               ScalaSig
{
  private final java.lang.String name;
    descriptor: Ljava/lang/String;
    flags: ACC_PRIVATE, ACC_FINAL

  public static scala.Option<java.lang.String> unapply(rpg.typeclass.naive.DexSkill);
    descriptor: (Lrpg/typeclass/naive/DexSkill;)Lscala/Option;
    flags: ACC_PUBLIC, ACC_STATIC
    Code:
      stack=2, locals=1, args_size=1
         0: getstatic     #24                 // Field rpg/typeclass/naive/DexSkill$.MODULE$:Lrpg/typeclass/naive/DexSkill$;
         3: aload_0
         4: invokevirtual #26                 // Method rpg/typeclass/naive/DexSkill$.unapply:(Lrpg/typeclass/naive/DexSkill;)Lscala/Option;
         7: areturn
    Signature: #111                         // (Lrpg/typeclass/naive/DexSkill;)Lscala/Option<Ljava/lang/String;>;

  public static rpg.typeclass.naive.DexSkill apply(java.lang.String);
    descriptor: (Ljava/lang/String;)Lrpg/typeclass/naive/DexSkill;
    flags: ACC_PUBLIC, ACC_STATIC
    Code:
      stack=2, locals=1, args_size=1
         0: getstatic     #24                 // Field rpg/typeclass/naive/DexSkill$.MODULE$:Lrpg/typeclass/naive/DexSkill$;
         3: aload_0
         4: invokevirtual #30                 // Method rpg/typeclass/naive/DexSkill$.apply:(Ljava/lang/String;)Lrpg/typeclass/naive/DexSkill;
         7: areturn

  public static <A extends java.lang.Object> scala.Function1<java.lang.String, A> andThen(scala.Function1<rpg.typeclass.naive.DexSkill, A>);
    descriptor: (Lscala/Function1;)Lscala/Function1;
    flags: ACC_PUBLIC, ACC_STATIC
    Code:
      stack=2, locals=1, args_size=1
         0: getstatic     #24                 // Field rpg/typeclass/naive/DexSkill$.MODULE$:Lrpg/typeclass/naive/DexSkill$;
         3: aload_0
         4: invokevirtual #34                 // Method rpg/typeclass/naive/DexSkill$.andThen:(Lscala/Function1;)Lscala/Function1;
         7: areturn
    Signature: #112                         // <A:Ljava/lang/Object;>(Lscala/Function1<Lrpg/typeclass/naive/DexSkill;TA;>;)Lscala/Function1<Ljava/lang/String;TA;>;

  public static <A extends java.lang.Object> scala.Function1<A, rpg.typeclass.naive.DexSkill> compose(scala.Function1<A, java.lang.String>);
    descriptor: (Lscala/Function1;)Lscala/Function1;
    flags: ACC_PUBLIC, ACC_STATIC
    Code:
      stack=2, locals=1, args_size=1
         0: getstatic     #24                 // Field rpg/typeclass/naive/DexSkill$.MODULE$:Lrpg/typeclass/naive/DexSkill$;
         3: aload_0
         4: invokevirtual #37                 // Method rpg/typeclass/naive/DexSkill$.compose:(Lscala/Function1;)Lscala/Function1;
         7: areturn
    Signature: #113                         // <A:Ljava/lang/Object;>(Lscala/Function1<TA;Ljava/lang/String;>;)Lscala/Function1<TA;Lrpg/typeclass/naive/DexSkill;>;

  public java.lang.String name();
    descriptor: ()Ljava/lang/String;
    flags: ACC_PUBLIC
    Code:
      stack=1, locals=1, args_size=1
         0: aload_0
         1: getfield      #40                 // Field name:Ljava/lang/String;
         4: areturn
      LocalVariableTable:
        Start  Length  Slot  Name   Signature
            0       5     0  this   Lrpg/typeclass/naive/DexSkill;
      LineNumberTable:
        line 21: 0

  public rpg.typeclass.naive.DexSkill copy(java.lang.String);
    descriptor: (Ljava/lang/String;)Lrpg/typeclass/naive/DexSkill;
    flags: ACC_PUBLIC
    Code:
      stack=3, locals=2, args_size=2
         0: new           #2                  // class rpg/typeclass/naive/DexSkill
         3: dup
         4: aload_1
         5: invokespecial #47                 // Method "<init>":(Ljava/lang/String;)V
         8: areturn
      LocalVariableTable:
        Start  Length  Slot  Name   Signature
            0       9     0  this   Lrpg/typeclass/naive/DexSkill;
            0       9     1  name   Ljava/lang/String;
      LineNumberTable:
        line 21: 0
    MethodParameters:
      Name                           Flags
      name                           final

  public java.lang.String copy$default$1();
    descriptor: ()Ljava/lang/String;
    flags: ACC_PUBLIC
    Code:
      stack=1, locals=1, args_size=1
         0: aload_0
         1: invokevirtual #50                 // Method name:()Ljava/lang/String;
         4: areturn
      LocalVariableTable:
        Start  Length  Slot  Name   Signature
            0       5     0  this   Lrpg/typeclass/naive/DexSkill;
      LineNumberTable:
        line 21: 0

  public java.lang.String productPrefix();
    descriptor: ()Ljava/lang/String;
    flags: ACC_PUBLIC
    Code:
      stack=1, locals=1, args_size=1
         0: ldc           #53                 // String DexSkill
         2: areturn
      LocalVariableTable:
        Start  Length  Slot  Name   Signature
            0       3     0  this   Lrpg/typeclass/naive/DexSkill;
      LineNumberTable:
        line 21: 0

  public int productArity();
    descriptor: ()I
    flags: ACC_PUBLIC
    Code:
      stack=1, locals=1, args_size=1
         0: iconst_1
         1: ireturn
      LocalVariableTable:
        Start  Length  Slot  Name   Signature
            0       2     0  this   Lrpg/typeclass/naive/DexSkill;
      LineNumberTable:
        line 21: 0

  public java.lang.Object productElement(int);
    descriptor: (I)Ljava/lang/Object;
    flags: ACC_PUBLIC
    Code:
      stack=3, locals=3, args_size=2
         0: iload_1
         1: istore_2
         2: iload_2
         3: tableswitch   { // 0 to 0
                       0: 20
                 default: 27
            }
        20: aload_0
        21: invokevirtual #50                 // Method name:()Ljava/lang/String;
        24: goto          42
        27: new           #60                 // class java/lang/IndexOutOfBoundsException
        30: dup
        31: iload_1
        32: invokestatic  #66                 // Method scala/runtime/BoxesRunTime.boxToInteger:(I)Ljava/lang/Integer;
        35: invokevirtual #69                 // Method java/lang/Object.toString:()Ljava/lang/String;
        38: invokespecial #70                 // Method java/lang/IndexOutOfBoundsException."<init>":(Ljava/lang/String;)V
        41: athrow
        42: areturn
      LocalVariableTable:
        Start  Length  Slot  Name   Signature
            0      43     0  this   Lrpg/typeclass/naive/DexSkill;
            0      43     1   x$1   I
      LineNumberTable:
        line 21: 0
      StackMapTable: number_of_entries = 3
        frame_type = 252 /* append */
          offset_delta = 20
          locals = [ int ]
        frame_type = 6 /* same */
        frame_type = 78 /* same_locals_1_stack_item */
          stack = [ class java/lang/String ]
    MethodParameters:
      Name                           Flags
      x$1                            final

  public scala.collection.Iterator<java.lang.Object> productIterator();
    descriptor: ()Lscala/collection/Iterator;
    flags: ACC_PUBLIC
    Code:
      stack=2, locals=1, args_size=1
         0: getstatic     #80                 // Field scala/runtime/ScalaRunTime$.MODULE$:Lscala/runtime/ScalaRunTime$;
         3: aload_0
         4: invokevirtual #84                 // Method scala/runtime/ScalaRunTime$.typedProductIterator:(Lscala/Product;)Lscala/collection/Iterator;
         7: areturn
      LocalVariableTable:
        Start  Length  Slot  Name   Signature
            0       8     0  this   Lrpg/typeclass/naive/DexSkill;
      LineNumberTable:
        line 21: 0
    Signature: #118                         // ()Lscala/collection/Iterator<Ljava/lang/Object;>;

  public boolean canEqual(java.lang.Object);
    descriptor: (Ljava/lang/Object;)Z
    flags: ACC_PUBLIC
    Code:
      stack=1, locals=2, args_size=2
         0: aload_1
         1: instanceof    #2                  // class rpg/typeclass/naive/DexSkill
         4: ireturn
      LocalVariableTable:
        Start  Length  Slot  Name   Signature
            0       5     0  this   Lrpg/typeclass/naive/DexSkill;
            0       5     1   x$1   Ljava/lang/Object;
      LineNumberTable:
        line 21: 0
    MethodParameters:
      Name                           Flags
      x$1                            final

  public int hashCode();
    descriptor: ()I
    flags: ACC_PUBLIC
    Code:
      stack=2, locals=1, args_size=1
         0: getstatic     #80                 // Field scala/runtime/ScalaRunTime$.MODULE$:Lscala/runtime/ScalaRunTime$;
         3: aload_0
         4: invokevirtual #92                 // Method scala/runtime/ScalaRunTime$._hashCode:(Lscala/Product;)I
         7: ireturn
      LocalVariableTable:
        Start  Length  Slot  Name   Signature
            0       8     0  this   Lrpg/typeclass/naive/DexSkill;
      LineNumberTable:
        line 21: 0

  public java.lang.String toString();
    descriptor: ()Ljava/lang/String;
    flags: ACC_PUBLIC
    Code:
      stack=2, locals=1, args_size=1
         0: getstatic     #80                 // Field scala/runtime/ScalaRunTime$.MODULE$:Lscala/runtime/ScalaRunTime$;
         3: aload_0
         4: invokevirtual #96                 // Method scala/runtime/ScalaRunTime$._toString:(Lscala/Product;)Ljava/lang/String;
         7: areturn
      LocalVariableTable:
        Start  Length  Slot  Name   Signature
            0       8     0  this   Lrpg/typeclass/naive/DexSkill;
      LineNumberTable:
        line 21: 0

  public boolean equals(java.lang.Object);
    descriptor: (Ljava/lang/Object;)Z
    flags: ACC_PUBLIC
    Code:
      stack=2, locals=6, args_size=2
         0: aload_0
         1: aload_1
         2: if_acmpeq     86
         5: aload_1
         6: astore_3
         7: aload_3
         8: instanceof    #2                  // class rpg/typeclass/naive/DexSkill
        11: ifeq          19
        14: iconst_1
        15: istore_2
        16: goto          27
        19: goto          22
        22: iconst_0
        23: istore_2
        24: goto          27
        27: iload_2
        28: ifeq          90
        31: aload_1
        32: checkcast     #2                  // class rpg/typeclass/naive/DexSkill
        35: astore        4
        37: aload_0
        38: invokevirtual #50                 // Method name:()Ljava/lang/String;
        41: aload         4
        43: invokevirtual #50                 // Method name:()Ljava/lang/String;
        46: astore        5
        48: dup
        49: ifnonnull     61
        52: pop
        53: aload         5
        55: ifnull        69
        58: goto          82
        61: aload         5
        63: invokevirtual #99                 // Method java/lang/Object.equals:(Ljava/lang/Object;)Z
        66: ifeq          82
        69: aload         4
        71: aload_0
        72: invokevirtual #101                // Method canEqual:(Ljava/lang/Object;)Z
        75: ifeq          82
        78: iconst_1
        79: goto          83
        82: iconst_0
        83: ifeq          90
        86: iconst_1
        87: goto          91
        90: iconst_0
        91: ireturn
      LocalVariableTable:
        Start  Length  Slot  Name   Signature
            0      92     0  this   Lrpg/typeclass/naive/DexSkill;
            0      92     1   x$1   Ljava/lang/Object;
      LineNumberTable:
        line 21: 0
      StackMapTable: number_of_entries = 10
        frame_type = 253 /* append */
          offset_delta = 19
          locals = [ top, class java/lang/Object ]
        frame_type = 2 /* same */
        frame_type = 255 /* full_frame */
          offset_delta = 4
          locals = [ class rpg/typeclass/naive/DexSkill, class java/lang/Object, int, class java/lang/Object ]
          stack = []
        frame_type = 255 /* full_frame */
          offset_delta = 33
          locals = [ class rpg/typeclass/naive/DexSkill, class java/lang/Object, int, class java/lang/Object, class rpg/typeclass/naive/DexSkill, class java/lang/String ]
          stack = [ class java/lang/String ]
        frame_type = 7 /* same */
        frame_type = 12 /* same */
        frame_type = 64 /* same_locals_1_stack_item */
          stack = [ int ]
        frame_type = 255 /* full_frame */
          offset_delta = 2
          locals = [ class rpg/typeclass/naive/DexSkill, class java/lang/Object ]
          stack = []
        frame_type = 253 /* append */
          offset_delta = 3
          locals = [ int, class java/lang/Object ]
        frame_type = 255 /* full_frame */
          offset_delta = 0
          locals = [ class rpg/typeclass/naive/DexSkill, class java/lang/Object ]
          stack = [ int ]
    MethodParameters:
      Name                           Flags
      x$1                            final

  public rpg.typeclass.naive.DexSkill(java.lang.String);
    descriptor: (Ljava/lang/String;)V
    flags: ACC_PUBLIC
    Code:
      stack=2, locals=2, args_size=2
         0: aload_0
         1: aload_1
         2: putfield      #40                 // Field name:Ljava/lang/String;
         5: aload_0
         6: invokespecial #104                // Method java/lang/Object."<init>":()V
         9: aload_0
        10: invokestatic  #108                // InterfaceMethod scala/Product.$init$:(Lscala/Product;)V
        13: return
      LocalVariableTable:
        Start  Length  Slot  Name   Signature
            0      14     0  this   Lrpg/typeclass/naive/DexSkill;
            0      14     1  name   Ljava/lang/String;
      LineNumberTable:
        line 21: 0
    MethodParameters:
      Name                           Flags
      name                           final
}
SourceFile: "TypeclassSkillTrees.scala"
RuntimeVisibleAnnotations:
  0: #12(#13=s#14)
Error: unknown attribute
  ScalaInlineInfo: length = 0x40
   01 00 00 0C 00 2C 00 2D 00 00 55 00 56 00 00 30
   00 26 00 00 2B 00 1C 00 00 61 00 56 00 00 58 00
   37 00 00 0F 00 26 00 00 36 00 37 00 00 38 00 39
   00 00 4A 00 4B 00 00 33 00 26 00 00 43 00 26 00

Error: unknown attribute
  ScalaSig: length = 0x3
   05 00 00
