Compiled from "OOOSubcallsSkillTrees.scala"
public class rpg.ooo.subcalls.DexSkill implements rpg.ooo.subcalls.Skill,rpg.ooo.subcalls.DexBased,scala.Product,scala.Serializable {
  private final java.lang.String name;

  public static scala.Option<java.lang.String> unapply(rpg.ooo.subcalls.DexSkill);
    Code:
       0: getstatic     #26                 // Field rpg/ooo/subcalls/DexSkill$.MODULE$:Lrpg/ooo/subcalls/DexSkill$;
       3: aload_0
       4: invokevirtual #28                 // Method rpg/ooo/subcalls/DexSkill$.unapply:(Lrpg/ooo/subcalls/DexSkill;)Lscala/Option;
       7: areturn

  public static rpg.ooo.subcalls.DexSkill apply(java.lang.String);
    Code:
       0: getstatic     #26                 // Field rpg/ooo/subcalls/DexSkill$.MODULE$:Lrpg/ooo/subcalls/DexSkill$;
       3: aload_0
       4: invokevirtual #32                 // Method rpg/ooo/subcalls/DexSkill$.apply:(Ljava/lang/String;)Lrpg/ooo/subcalls/DexSkill;
       7: areturn

  public static <A> scala.Function1<java.lang.String, A> andThen(scala.Function1<rpg.ooo.subcalls.DexSkill, A>);
    Code:
       0: getstatic     #26                 // Field rpg/ooo/subcalls/DexSkill$.MODULE$:Lrpg/ooo/subcalls/DexSkill$;
       3: aload_0
       4: invokevirtual #36                 // Method rpg/ooo/subcalls/DexSkill$.andThen:(Lscala/Function1;)Lscala/Function1;
       7: areturn

  public static <A> scala.Function1<A, rpg.ooo.subcalls.DexSkill> compose(scala.Function1<A, java.lang.String>);
    Code:
       0: getstatic     #26                 // Field rpg/ooo/subcalls/DexSkill$.MODULE$:Lrpg/ooo/subcalls/DexSkill$;
       3: aload_0
       4: invokevirtual #39                 // Method rpg/ooo/subcalls/DexSkill$.compose:(Lscala/Function1;)Lscala/Function1;
       7: areturn

  public int thisCost(rpg.PlayerTraits);
    Code:
       0: aload_0
       1: aload_1
       2: invokestatic  #46                 // InterfaceMethod rpg/ooo/subcalls/DexBased.thisCost$:(Lrpg/ooo/subcalls/DexBased;Lrpg/PlayerTraits;)I
       5: ireturn

  public int cost(rpg.PlayerTraits);
    Code:
       0: aload_0
       1: aload_1
       2: invokestatic  #54                 // InterfaceMethod rpg/ooo/subcalls/Skill.cost$:(Lrpg/ooo/subcalls/Skill;Lrpg/PlayerTraits;)I
       5: ireturn

  public java.lang.String name();
    Code:
       0: aload_0
       1: getfield      #57                 // Field name:Ljava/lang/String;
       4: areturn

  public rpg.ooo.subcalls.DexSkill copy(java.lang.String);
    Code:
       0: new           #2                  // class rpg/ooo/subcalls/DexSkill
       3: dup
       4: aload_1
       5: invokespecial #62                 // Method "<init>":(Ljava/lang/String;)V
       8: areturn

  public java.lang.String copy$default$1();
    Code:
       0: aload_0
       1: invokevirtual #65                 // Method name:()Ljava/lang/String;
       4: areturn

  public java.lang.String productPrefix();
    Code:
       0: ldc           #68                 // String DexSkill
       2: areturn

  public int productArity();
    Code:
       0: iconst_1
       1: ireturn

  public java.lang.Object productElement(int);
    Code:
       0: iload_1
       1: istore_2
       2: iload_2
       3: tableswitch   { // 0 to 0
                     0: 20
               default: 27
          }
      20: aload_0
      21: invokevirtual #65                 // Method name:()Ljava/lang/String;
      24: goto          42
      27: new           #75                 // class java/lang/IndexOutOfBoundsException
      30: dup
      31: iload_1
      32: invokestatic  #81                 // Method scala/runtime/BoxesRunTime.boxToInteger:(I)Ljava/lang/Integer;
      35: invokevirtual #84                 // Method java/lang/Object.toString:()Ljava/lang/String;
      38: invokespecial #85                 // Method java/lang/IndexOutOfBoundsException."<init>":(Ljava/lang/String;)V
      41: athrow
      42: areturn

  public scala.collection.Iterator<java.lang.Object> productIterator();
    Code:
       0: getstatic     #95                 // Field scala/runtime/ScalaRunTime$.MODULE$:Lscala/runtime/ScalaRunTime$;
       3: aload_0
       4: invokevirtual #99                 // Method scala/runtime/ScalaRunTime$.typedProductIterator:(Lscala/Product;)Lscala/collection/Iterator;
       7: areturn

  public boolean canEqual(java.lang.Object);
    Code:
       0: aload_1
       1: instanceof    #2                  // class rpg/ooo/subcalls/DexSkill
       4: ireturn

  public int hashCode();
    Code:
       0: getstatic     #95                 // Field scala/runtime/ScalaRunTime$.MODULE$:Lscala/runtime/ScalaRunTime$;
       3: aload_0
       4: invokevirtual #107                // Method scala/runtime/ScalaRunTime$._hashCode:(Lscala/Product;)I
       7: ireturn

  public java.lang.String toString();
    Code:
       0: getstatic     #95                 // Field scala/runtime/ScalaRunTime$.MODULE$:Lscala/runtime/ScalaRunTime$;
       3: aload_0
       4: invokevirtual #111                // Method scala/runtime/ScalaRunTime$._toString:(Lscala/Product;)Ljava/lang/String;
       7: areturn

  public boolean equals(java.lang.Object);
    Code:
       0: aload_0
       1: aload_1
       2: if_acmpeq     86
       5: aload_1
       6: astore_3
       7: aload_3
       8: instanceof    #2                  // class rpg/ooo/subcalls/DexSkill
      11: ifeq          19
      14: iconst_1
      15: istore_2
      16: goto          27
      19: goto          22
      22: iconst_0
      23: istore_2
      24: goto          27
      27: iload_2
      28: ifeq          90
      31: aload_1
      32: checkcast     #2                  // class rpg/ooo/subcalls/DexSkill
      35: astore        4
      37: aload_0
      38: invokevirtual #65                 // Method name:()Ljava/lang/String;
      41: aload         4
      43: invokevirtual #65                 // Method name:()Ljava/lang/String;
      46: astore        5
      48: dup
      49: ifnonnull     61
      52: pop
      53: aload         5
      55: ifnull        69
      58: goto          82
      61: aload         5
      63: invokevirtual #114                // Method java/lang/Object.equals:(Ljava/lang/Object;)Z
      66: ifeq          82
      69: aload         4
      71: aload_0
      72: invokevirtual #116                // Method canEqual:(Ljava/lang/Object;)Z
      75: ifeq          82
      78: iconst_1
      79: goto          83
      82: iconst_0
      83: ifeq          90
      86: iconst_1
      87: goto          91
      90: iconst_0
      91: ireturn

  public rpg.ooo.subcalls.DexSkill(java.lang.String);
    Code:
       0: aload_0
       1: aload_1
       2: putfield      #57                 // Field name:Ljava/lang/String;
       5: aload_0
       6: invokespecial #119                // Method java/lang/Object."<init>":()V
       9: aload_0
      10: invokestatic  #123                // InterfaceMethod rpg/ooo/subcalls/Skill.$init$:(Lrpg/ooo/subcalls/Skill;)V
      13: aload_0
      14: invokestatic  #126                // InterfaceMethod rpg/ooo/subcalls/DexBased.$init$:(Lrpg/ooo/subcalls/DexBased;)V
      17: aload_0
      18: invokestatic  #129                // InterfaceMethod scala/Product.$init$:(Lscala/Product;)V
      21: return
}
