Compiled from "PatMatSkillTrees.scala"
public final class rpg.patmat.steppedClass.WisTree$ extends scala.runtime.AbstractFunction2<rpg.patmat.steppedClass.Node, rpg.patmat.steppedClass.Node, rpg.patmat.steppedClass.WisTree> implements scala.Serializable {
  public static rpg.patmat.steppedClass.WisTree$ MODULE$;

  public static {};
    Code:
       0: new           #2                  // class rpg/patmat/steppedClass/WisTree$
       3: invokespecial #15                 // Method "<init>":()V
       6: return

  public final java.lang.String toString();
    Code:
       0: ldc           #19                 // String WisTree
       2: areturn

  public rpg.patmat.steppedClass.WisTree apply(rpg.patmat.steppedClass.Node, rpg.patmat.steppedClass.Node);
    Code:
       0: new           #26                 // class rpg/patmat/steppedClass/WisTree
       3: dup
       4: aload_1
       5: aload_2
       6: invokespecial #29                 // Method rpg/patmat/steppedClass/WisTree."<init>":(Lrpg/patmat/steppedClass/Node;Lrpg/patmat/steppedClass/Node;)V
       9: areturn

  public scala.Option<scala.Tuple2<rpg.patmat.steppedClass.Node, rpg.patmat.steppedClass.Node>> unapply(rpg.patmat.steppedClass.WisTree);
    Code:
       0: aload_1
       1: ifnonnull     10
       4: getstatic     #38                 // Field scala/None$.MODULE$:Lscala/None$;
       7: goto          32
      10: new           #40                 // class scala/Some
      13: dup
      14: new           #42                 // class scala/Tuple2
      17: dup
      18: aload_1
      19: invokevirtual #45                 // Method rpg/patmat/steppedClass/WisTree.left:()Lrpg/patmat/steppedClass/Node;
      22: aload_1
      23: invokevirtual #47                 // Method rpg/patmat/steppedClass/WisTree.right:()Lrpg/patmat/steppedClass/Node;
      26: invokespecial #50                 // Method scala/Tuple2."<init>":(Ljava/lang/Object;Ljava/lang/Object;)V
      29: invokespecial #53                 // Method scala/Some."<init>":(Ljava/lang/Object;)V
      32: areturn

  private java.lang.Object readResolve();
    Code:
       0: getstatic     #60                 // Field MODULE$:Lrpg/patmat/steppedClass/WisTree$;
       3: areturn

  public java.lang.Object apply(java.lang.Object, java.lang.Object);
    Code:
       0: aload_0
       1: aload_1
       2: checkcast     #65                 // class rpg/patmat/steppedClass/Node
       5: aload_2
       6: checkcast     #65                 // class rpg/patmat/steppedClass/Node
       9: invokevirtual #67                 // Method apply:(Lrpg/patmat/steppedClass/Node;Lrpg/patmat/steppedClass/Node;)Lrpg/patmat/steppedClass/WisTree;
      12: areturn

  private rpg.patmat.steppedClass.WisTree$();
    Code:
       0: aload_0
       1: invokespecial #69                 // Method scala/runtime/AbstractFunction2."<init>":()V
       4: aload_0
       5: putstatic     #60                 // Field MODULE$:Lrpg/patmat/steppedClass/WisTree$;
       8: return
}
