Classfile /home/krzysiek/workspace/scala-bcode-cutter/pref/target/scala-2.12/classes/rpg/ooo/nested/OOOSkillTrees.class
  Last modified Apr 8, 2018; size 1959 bytes
  MD5 checksum 61e03b2e15bb5531315836f0662711bb
  Compiled from "OOOSubcallsSkillTrees.scala"
public class rpg.ooo.nested.OOOSkillTrees extends rpg.SkillTrees
  minor version: 0
  major version: 52
  flags: ACC_PUBLIC, ACC_SUPER
Constant pool:
   #1 = Utf8               rpg/ooo/nested/OOOSkillTrees
   #2 = Class              #1             // rpg/ooo/nested/OOOSkillTrees
   #3 = Utf8               rpg/SkillTrees
   #4 = Class              #3             // rpg/SkillTrees
   #5 = Utf8               OOOSubcallsSkillTrees.scala
   #6 = Utf8               Lscala/reflect/ScalaSignature;
   #7 = Utf8               bytes
   #8 = Utf8               52A!\tiqjT(TW&dG:fKNT!a\r9,7^3e\t)a!Ap_>TaBeB<7A\n)\"aI!!M[7Ue,7C#=S:LGO#A!A!)AC!+YM]2iKJLHK]3f)\t1\r9A1\ne1!!D*lS2dGK]3f%(91A!C\tQ!\ryF%M\t?\"IRAIgG.YIqAT8uQ&tw\r!M%q%\t:L\"BQA;sC&$8W%AF\r!20:UeLGo
   #9 = Utf8               rpg/ooo/nested/FeatTree$Skill
  #10 = Class              #9             // rpg/ooo/nested/FeatTree$Skill
  #11 = Utf8               rpg/ooo/nested/FeatTree
  #12 = Class              #11            // rpg/ooo/nested/FeatTree
  #13 = Utf8               Skill
  #14 = Utf8               rpg/ooo/nested/FeatTree$Step
  #15 = Class              #14            // rpg/ooo/nested/FeatTree$Step
  #16 = Utf8               Step
  #17 = Utf8               rpg/ooo/nested/FeatTree$Tree
  #18 = Class              #17            // rpg/ooo/nested/FeatTree$Tree
  #19 = Utf8               Tree
  #20 = Utf8               rpg/ooo/nested/OOOSkillTrees$$anon$1
  #21 = Class              #20            // rpg/ooo/nested/OOOSkillTrees$$anon$1
  #22 = Utf8               archeryTree
  #23 = Utf8               (Lrpg/PlayerTraits;)Lrpg/SkillTreeRepr;
  #24 = Utf8               traits
  #25 = Utf8               rpg/ooo/nested/Dex$
  #26 = Class              #25            // rpg/ooo/nested/Dex$
  #27 = Utf8               MODULE$
  #28 = Utf8               Lrpg/ooo/nested/Dex$;
  #29 = NameAndType        #27:#28        // MODULE$:Lrpg/ooo/nested/Dex$;
  #30 = Fieldref           #26.#29        // rpg/ooo/nested/Dex$.MODULE$:Lrpg/ooo/nested/Dex$;
  #31 = Utf8               rpg/ooo/nested/Wis$
  #32 = Class              #31            // rpg/ooo/nested/Wis$
  #33 = Utf8               Lrpg/ooo/nested/Wis$;
  #34 = NameAndType        #27:#33        // MODULE$:Lrpg/ooo/nested/Wis$;
  #35 = Fieldref           #32.#34        // rpg/ooo/nested/Wis$.MODULE$:Lrpg/ooo/nested/Wis$;
  #36 = Utf8               aimed
  #37 = String             #36            // aimed
  #38 = Utf8               <init>
  #39 = Utf8               (Lrpg/ooo/nested/FeatTree;Ljava/lang/String;)V
  #40 = NameAndType        #38:#39        // "<init>":(Lrpg/ooo/nested/FeatTree;Ljava/lang/String;)V
  #41 = Methodref          #10.#40        // rpg/ooo/nested/FeatTree$Skill."<init>":(Lrpg/ooo/nested/FeatTree;Ljava/lang/String;)V
  #42 = Utf8               rapid
  #43 = String             #42            // rapid
  #44 = Utf8               (Lrpg/ooo/nested/FeatTree;Lrpg/ooo/nested/Node;)V
  #45 = NameAndType        #38:#44        // "<init>":(Lrpg/ooo/nested/FeatTree;Lrpg/ooo/nested/Node;)V
  #46 = Methodref          #15.#45        // rpg/ooo/nested/FeatTree$Step."<init>":(Lrpg/ooo/nested/FeatTree;Lrpg/ooo/nested/Node;)V
  #47 = Utf8               (Lrpg/ooo/nested/FeatTree;Lrpg/ooo/nested/Node;Lrpg/ooo/nested/Node;)V
  #48 = NameAndType        #38:#47        // "<init>":(Lrpg/ooo/nested/FeatTree;Lrpg/ooo/nested/Node;Lrpg/ooo/nested/Node;)V
  #49 = Methodref          #18.#48        // rpg/ooo/nested/FeatTree$Tree."<init>":(Lrpg/ooo/nested/FeatTree;Lrpg/ooo/nested/Node;Lrpg/ooo/nested/Node;)V
  #50 = Utf8               rpg/ooo/nested/Str$
  #51 = Class              #50            // rpg/ooo/nested/Str$
  #52 = Utf8               Lrpg/ooo/nested/Str$;
  #53 = NameAndType        #27:#52        // MODULE$:Lrpg/ooo/nested/Str$;
  #54 = Fieldref           #51.#53        // rpg/ooo/nested/Str$.MODULE$:Lrpg/ooo/nested/Str$;
  #55 = Utf8               power
  #56 = String             #55            // power
  #57 = Utf8               double
  #58 = String             #57            // double
  #59 = Utf8               (Lrpg/ooo/nested/OOOSkillTrees;Lrpg/PlayerTraits;Lrpg/ooo/nested/Node;)V
  #60 = NameAndType        #38:#59        // "<init>":(Lrpg/ooo/nested/OOOSkillTrees;Lrpg/PlayerTraits;Lrpg/ooo/nested/Node;)V
  #61 = Methodref          #21.#60        // rpg/ooo/nested/OOOSkillTrees$$anon$1."<init>":(Lrpg/ooo/nested/OOOSkillTrees;Lrpg/PlayerTraits;Lrpg/ooo/nested/Node;)V
  #62 = Utf8               tree
  #63 = Utf8               Lrpg/ooo/nested/Node;
  #64 = Utf8               this
  #65 = Utf8               Lrpg/ooo/nested/OOOSkillTrees;
  #66 = Utf8               Lrpg/PlayerTraits;
  #67 = Utf8               ()V
  #68 = NameAndType        #38:#67        // "<init>":()V
  #69 = Methodref          #4.#68         // rpg/SkillTrees."<init>":()V
  #70 = Utf8               Code
  #71 = Utf8               LocalVariableTable
  #72 = Utf8               LineNumberTable
  #73 = Utf8               Signature
  #74 = Utf8               (Lrpg/PlayerTraits;)Lrpg/SkillTreeRepr<*>;
  #75 = Utf8               MethodParameters
  #76 = Utf8               SourceFile
  #77 = Utf8               InnerClasses
  #78 = Utf8               RuntimeVisibleAnnotations
  #79 = Utf8               ScalaInlineInfo
  #80 = Utf8               ScalaSig
{
  public rpg.SkillTreeRepr<?> archeryTree(rpg.PlayerTraits);
    descriptor: (Lrpg/PlayerTraits;)Lrpg/SkillTreeRepr;
    flags: ACC_PUBLIC
    Code:
      stack=17, locals=3, args_size=2
         0: new           #18                 // class rpg/ooo/nested/FeatTree$Tree
         3: dup
         4: getstatic     #30                 // Field rpg/ooo/nested/Dex$.MODULE$:Lrpg/ooo/nested/Dex$;
         7: new           #15                 // class rpg/ooo/nested/FeatTree$Step
        10: dup
        11: getstatic     #30                 // Field rpg/ooo/nested/Dex$.MODULE$:Lrpg/ooo/nested/Dex$;
        14: new           #18                 // class rpg/ooo/nested/FeatTree$Tree
        17: dup
        18: getstatic     #35                 // Field rpg/ooo/nested/Wis$.MODULE$:Lrpg/ooo/nested/Wis$;
        21: new           #10                 // class rpg/ooo/nested/FeatTree$Skill
        24: dup
        25: getstatic     #35                 // Field rpg/ooo/nested/Wis$.MODULE$:Lrpg/ooo/nested/Wis$;
        28: ldc           #37                 // String aimed
        30: invokespecial #41                 // Method rpg/ooo/nested/FeatTree$Skill."<init>":(Lrpg/ooo/nested/FeatTree;Ljava/lang/String;)V
        33: new           #15                 // class rpg/ooo/nested/FeatTree$Step
        36: dup
        37: getstatic     #35                 // Field rpg/ooo/nested/Wis$.MODULE$:Lrpg/ooo/nested/Wis$;
        40: new           #10                 // class rpg/ooo/nested/FeatTree$Skill
        43: dup
        44: getstatic     #30                 // Field rpg/ooo/nested/Dex$.MODULE$:Lrpg/ooo/nested/Dex$;
        47: ldc           #43                 // String rapid
        49: invokespecial #41                 // Method rpg/ooo/nested/FeatTree$Skill."<init>":(Lrpg/ooo/nested/FeatTree;Ljava/lang/String;)V
        52: invokespecial #46                 // Method rpg/ooo/nested/FeatTree$Step."<init>":(Lrpg/ooo/nested/FeatTree;Lrpg/ooo/nested/Node;)V
        55: invokespecial #49                 // Method rpg/ooo/nested/FeatTree$Tree."<init>":(Lrpg/ooo/nested/FeatTree;Lrpg/ooo/nested/Node;Lrpg/ooo/nested/Node;)V
        58: invokespecial #46                 // Method rpg/ooo/nested/FeatTree$Step."<init>":(Lrpg/ooo/nested/FeatTree;Lrpg/ooo/nested/Node;)V
        61: new           #18                 // class rpg/ooo/nested/FeatTree$Tree
        64: dup
        65: getstatic     #54                 // Field rpg/ooo/nested/Str$.MODULE$:Lrpg/ooo/nested/Str$;
        68: new           #10                 // class rpg/ooo/nested/FeatTree$Skill
        71: dup
        72: getstatic     #54                 // Field rpg/ooo/nested/Str$.MODULE$:Lrpg/ooo/nested/Str$;
        75: ldc           #56                 // String power
        77: invokespecial #41                 // Method rpg/ooo/nested/FeatTree$Skill."<init>":(Lrpg/ooo/nested/FeatTree;Ljava/lang/String;)V
        80: new           #15                 // class rpg/ooo/nested/FeatTree$Step
        83: dup
        84: getstatic     #54                 // Field rpg/ooo/nested/Str$.MODULE$:Lrpg/ooo/nested/Str$;
        87: new           #10                 // class rpg/ooo/nested/FeatTree$Skill
        90: dup
        91: getstatic     #30                 // Field rpg/ooo/nested/Dex$.MODULE$:Lrpg/ooo/nested/Dex$;
        94: ldc           #58                 // String double
        96: invokespecial #41                 // Method rpg/ooo/nested/FeatTree$Skill."<init>":(Lrpg/ooo/nested/FeatTree;Ljava/lang/String;)V
        99: invokespecial #46                 // Method rpg/ooo/nested/FeatTree$Step."<init>":(Lrpg/ooo/nested/FeatTree;Lrpg/ooo/nested/Node;)V
       102: invokespecial #49                 // Method rpg/ooo/nested/FeatTree$Tree."<init>":(Lrpg/ooo/nested/FeatTree;Lrpg/ooo/nested/Node;Lrpg/ooo/nested/Node;)V
       105: invokespecial #49                 // Method rpg/ooo/nested/FeatTree$Tree."<init>":(Lrpg/ooo/nested/FeatTree;Lrpg/ooo/nested/Node;Lrpg/ooo/nested/Node;)V
       108: astore_2
       109: new           #21                 // class rpg/ooo/nested/OOOSkillTrees$$anon$1
       112: dup
       113: aconst_null
       114: aload_1
       115: aload_2
       116: invokespecial #61                 // Method rpg/ooo/nested/OOOSkillTrees$$anon$1."<init>":(Lrpg/ooo/nested/OOOSkillTrees;Lrpg/PlayerTraits;Lrpg/ooo/nested/Node;)V
       119: areturn
      LocalVariableTable:
        Start  Length  Slot  Name   Signature
          108      11     2  tree   Lrpg/ooo/nested/Node;
            0     120     0  this   Lrpg/ooo/nested/OOOSkillTrees;
            0     120     1 traits   Lrpg/PlayerTraits;
      LineNumberTable:
        line 50: 0
        line 51: 7
        line 52: 21
        line 53: 33
        line 55: 61
        line 56: 68
        line 57: 80
        line 60: 109
    Signature: #74                          // (Lrpg/PlayerTraits;)Lrpg/SkillTreeRepr<*>;
    MethodParameters:
      Name                           Flags
      traits                         final

  public rpg.ooo.nested.OOOSkillTrees();
    descriptor: ()V
    flags: ACC_PUBLIC
    Code:
      stack=1, locals=1, args_size=1
         0: aload_0
         1: invokespecial #69                 // Method rpg/SkillTrees."<init>":()V
         4: return
      LocalVariableTable:
        Start  Length  Slot  Name   Signature
            0       5     0  this   Lrpg/ooo/nested/OOOSkillTrees;
      LineNumberTable:
        line 42: 0
}
SourceFile: "OOOSubcallsSkillTrees.scala"
InnerClasses:
     public #13= #10 of #12; //Skill=class rpg/ooo/nested/FeatTree$Skill of class rpg/ooo/nested/FeatTree
     public #16= #15 of #12; //Step=class rpg/ooo/nested/FeatTree$Step of class rpg/ooo/nested/FeatTree
     public #19= #18 of #12; //Tree=class rpg/ooo/nested/FeatTree$Tree of class rpg/ooo/nested/FeatTree
     public final #21; //class rpg/ooo/nested/OOOSkillTrees$$anon$1
RuntimeVisibleAnnotations:
  0: #6(#7=s#8)
Error: unknown attribute
  ScalaInlineInfo: length = 0xE
   01 00 00 02 00 26 00 43 00 00 16 00 17 00
Error: unknown attribute
  ScalaSig: length = 0x3
   05 00 00
