Compiled from "PatMatSkillTrees.scala"
public class rpg.patmat.steppedClass.DexTree extends rpg.patmat.steppedClass.Tree implements scala.Product,scala.Serializable {
  private final rpg.patmat.steppedClass.Node left;

  private final rpg.patmat.steppedClass.Node right;

  public static scala.Option<scala.Tuple2<rpg.patmat.steppedClass.Node, rpg.patmat.steppedClass.Node>> unapply(rpg.patmat.steppedClass.DexTree);
    Code:
       0: getstatic     #23                 // Field rpg/patmat/steppedClass/DexTree$.MODULE$:Lrpg/patmat/steppedClass/DexTree$;
       3: aload_0
       4: invokevirtual #25                 // Method rpg/patmat/steppedClass/DexTree$.unapply:(Lrpg/patmat/steppedClass/DexTree;)Lscala/Option;
       7: areturn

  public static rpg.patmat.steppedClass.DexTree apply(rpg.patmat.steppedClass.Node, rpg.patmat.steppedClass.Node);
    Code:
       0: getstatic     #23                 // Field rpg/patmat/steppedClass/DexTree$.MODULE$:Lrpg/patmat/steppedClass/DexTree$;
       3: aload_0
       4: aload_1
       5: invokevirtual #29                 // Method rpg/patmat/steppedClass/DexTree$.apply:(Lrpg/patmat/steppedClass/Node;Lrpg/patmat/steppedClass/Node;)Lrpg/patmat/steppedClass/DexTree;
       8: areturn

  public static scala.Function1<scala.Tuple2<rpg.patmat.steppedClass.Node, rpg.patmat.steppedClass.Node>, rpg.patmat.steppedClass.DexTree> tupled();
    Code:
       0: getstatic     #23                 // Field rpg/patmat/steppedClass/DexTree$.MODULE$:Lrpg/patmat/steppedClass/DexTree$;
       3: invokevirtual #33                 // Method rpg/patmat/steppedClass/DexTree$.tupled:()Lscala/Function1;
       6: areturn

  public static scala.Function1<rpg.patmat.steppedClass.Node, scala.Function1<rpg.patmat.steppedClass.Node, rpg.patmat.steppedClass.DexTree>> curried();
    Code:
       0: getstatic     #23                 // Field rpg/patmat/steppedClass/DexTree$.MODULE$:Lrpg/patmat/steppedClass/DexTree$;
       3: invokevirtual #36                 // Method rpg/patmat/steppedClass/DexTree$.curried:()Lscala/Function1;
       6: areturn

  public rpg.patmat.steppedClass.Node left();
    Code:
       0: aload_0
       1: getfield      #39                 // Field left:Lrpg/patmat/steppedClass/Node;
       4: areturn

  public rpg.patmat.steppedClass.Node right();
    Code:
       0: aload_0
       1: getfield      #43                 // Field right:Lrpg/patmat/steppedClass/Node;
       4: areturn

  public rpg.patmat.steppedClass.DexTree copy(rpg.patmat.steppedClass.Node, rpg.patmat.steppedClass.Node);
    Code:
       0: new           #2                  // class rpg/patmat/steppedClass/DexTree
       3: dup
       4: aload_1
       5: aload_2
       6: invokespecial #48                 // Method "<init>":(Lrpg/patmat/steppedClass/Node;Lrpg/patmat/steppedClass/Node;)V
       9: areturn

  public rpg.patmat.steppedClass.Node copy$default$1();
    Code:
       0: aload_0
       1: invokevirtual #51                 // Method left:()Lrpg/patmat/steppedClass/Node;
       4: areturn

  public rpg.patmat.steppedClass.Node copy$default$2();
    Code:
       0: aload_0
       1: invokevirtual #54                 // Method right:()Lrpg/patmat/steppedClass/Node;
       4: areturn

  public java.lang.String productPrefix();
    Code:
       0: ldc           #58                 // String DexTree
       2: areturn

  public int productArity();
    Code:
       0: iconst_2
       1: ireturn

  public java.lang.Object productElement(int);
    Code:
       0: iload_1
       1: istore_2
       2: iload_2
       3: tableswitch   { // 0 to 1
                     0: 24
                     1: 31
               default: 38
          }
      24: aload_0
      25: invokevirtual #51                 // Method left:()Lrpg/patmat/steppedClass/Node;
      28: goto          53
      31: aload_0
      32: invokevirtual #54                 // Method right:()Lrpg/patmat/steppedClass/Node;
      35: goto          53
      38: new           #65                 // class java/lang/IndexOutOfBoundsException
      41: dup
      42: iload_1
      43: invokestatic  #71                 // Method scala/runtime/BoxesRunTime.boxToInteger:(I)Ljava/lang/Integer;
      46: invokevirtual #76                 // Method java/lang/Object.toString:()Ljava/lang/String;
      49: invokespecial #79                 // Method java/lang/IndexOutOfBoundsException."<init>":(Ljava/lang/String;)V
      52: athrow
      53: areturn

  public scala.collection.Iterator<java.lang.Object> productIterator();
    Code:
       0: getstatic     #89                 // Field scala/runtime/ScalaRunTime$.MODULE$:Lscala/runtime/ScalaRunTime$;
       3: aload_0
       4: invokevirtual #93                 // Method scala/runtime/ScalaRunTime$.typedProductIterator:(Lscala/Product;)Lscala/collection/Iterator;
       7: areturn

  public boolean canEqual(java.lang.Object);
    Code:
       0: aload_1
       1: instanceof    #2                  // class rpg/patmat/steppedClass/DexTree
       4: ireturn

  public int hashCode();
    Code:
       0: getstatic     #89                 // Field scala/runtime/ScalaRunTime$.MODULE$:Lscala/runtime/ScalaRunTime$;
       3: aload_0
       4: invokevirtual #101                // Method scala/runtime/ScalaRunTime$._hashCode:(Lscala/Product;)I
       7: ireturn

  public java.lang.String toString();
    Code:
       0: getstatic     #89                 // Field scala/runtime/ScalaRunTime$.MODULE$:Lscala/runtime/ScalaRunTime$;
       3: aload_0
       4: invokevirtual #105                // Method scala/runtime/ScalaRunTime$._toString:(Lscala/Product;)Ljava/lang/String;
       7: areturn

  public boolean equals(java.lang.Object);
    Code:
       0: aload_0
       1: aload_1
       2: if_acmpeq     118
       5: aload_1
       6: astore_3
       7: aload_3
       8: instanceof    #2                  // class rpg/patmat/steppedClass/DexTree
      11: ifeq          19
      14: iconst_1
      15: istore_2
      16: goto          27
      19: goto          22
      22: iconst_0
      23: istore_2
      24: goto          27
      27: iload_2
      28: ifeq          122
      31: aload_1
      32: checkcast     #2                  // class rpg/patmat/steppedClass/DexTree
      35: astore        4
      37: aload_0
      38: invokevirtual #51                 // Method left:()Lrpg/patmat/steppedClass/Node;
      41: aload         4
      43: invokevirtual #51                 // Method left:()Lrpg/patmat/steppedClass/Node;
      46: astore        5
      48: dup
      49: ifnonnull     61
      52: pop
      53: aload         5
      55: ifnull        69
      58: goto          114
      61: aload         5
      63: invokevirtual #108                // Method java/lang/Object.equals:(Ljava/lang/Object;)Z
      66: ifeq          114
      69: aload_0
      70: invokevirtual #54                 // Method right:()Lrpg/patmat/steppedClass/Node;
      73: aload         4
      75: invokevirtual #54                 // Method right:()Lrpg/patmat/steppedClass/Node;
      78: astore        6
      80: dup
      81: ifnonnull     93
      84: pop
      85: aload         6
      87: ifnull        101
      90: goto          114
      93: aload         6
      95: invokevirtual #108                // Method java/lang/Object.equals:(Ljava/lang/Object;)Z
      98: ifeq          114
     101: aload         4
     103: aload_0
     104: invokevirtual #110                // Method canEqual:(Ljava/lang/Object;)Z
     107: ifeq          114
     110: iconst_1
     111: goto          115
     114: iconst_0
     115: ifeq          122
     118: iconst_1
     119: goto          123
     122: iconst_0
     123: ireturn

  public rpg.patmat.steppedClass.DexTree(rpg.patmat.steppedClass.Node, rpg.patmat.steppedClass.Node);
    Code:
       0: aload_0
       1: aload_1
       2: putfield      #39                 // Field left:Lrpg/patmat/steppedClass/Node;
       5: aload_0
       6: aload_2
       7: putfield      #43                 // Field right:Lrpg/patmat/steppedClass/Node;
      10: aload_0
      11: invokespecial #113                // Method rpg/patmat/steppedClass/Tree."<init>":()V
      14: aload_0
      15: invokestatic  #117                // InterfaceMethod scala/Product.$init$:(Lscala/Product;)V
      18: return
}
