Classfile /home/krzysiek/workspace/scala-bcode-cutter/talk_n_blog/clazz/target/scala-2.12/classes/Application.class
  Last modified Nov 23, 2017; size 791 bytes
  MD5 checksum 54e4270ae428cbb818d9b3ebc35a5f9d
  Compiled from "Clazz.scala"
public final class Application
  minor version: 0
  major version: 52
  flags: ACC_PUBLIC, ACC_FINAL, ACC_SUPER
Constant pool:
   #1 = Utf8               Application
   #2 = Class              #1             // Application
   #3 = Utf8               java/lang/Object
   #4 = Class              #3             // java/lang/Object
   #5 = Utf8               Clazz.scala
   #6 = Utf8               Lscala/reflect/ScalaSignature;
   #7 = Utf8               bytes
   #8 = Utf8               Y9Q!\t\t1\"9qY&\r^5p]*\t1!A=K6H/ AaaB)BE\tY\t9mSG/[8o'\r9!\t9i)1oY1mC&q:L(+4-\tB\n\r\r\t)!\t!Fy%t 
   #9 = Utf8               main
  #10 = Utf8               ([Ljava/lang/String;)V
  #11 = Utf8               Application$
  #12 = Class              #11            // Application$
  #13 = Utf8               MODULE$
  #14 = Utf8               LApplication$;
  #15 = NameAndType        #13:#14        // MODULE$:LApplication$;
  #16 = Fieldref           #12.#15        // Application$.MODULE$:LApplication$;
  #17 = NameAndType        #9:#10         // main:([Ljava/lang/String;)V
  #18 = Methodref          #12.#17        // Application$.main:([Ljava/lang/String;)V
  #19 = Utf8               delayedInit
  #20 = Utf8               (Lscala/Function0;)V
  #21 = NameAndType        #19:#20        // delayedInit:(Lscala/Function0;)V
  #22 = Methodref          #12.#21        // Application$.delayedInit:(Lscala/Function0;)V
  #23 = Utf8               delayedEndpoint$Application$1
  #24 = Utf8               ()V
  #25 = NameAndType        #23:#24        // delayedEndpoint$Application$1:()V
  #26 = Methodref          #12.#25        // Application$.delayedEndpoint$Application$1:()V
  #27 = Utf8               executionStart
  #28 = Utf8               ()J
  #29 = NameAndType        #27:#28        // executionStart:()J
  #30 = Methodref          #12.#29        // Application$.executionStart:()J
  #31 = Utf8               Code
  #32 = Utf8               Signature
  #33 = Utf8               (Lscala/Function0<Lscala/runtime/BoxedUnit;>;)V
  #34 = Utf8               SourceFile
  #35 = Utf8               RuntimeVisibleAnnotations
  #36 = Utf8               ScalaSig
{
  public static void main(java.lang.String[]);
    descriptor: ([Ljava/lang/String;)V
    flags: ACC_PUBLIC, ACC_STATIC
    Code:
      stack=2, locals=1, args_size=1
         0: getstatic     #16                 // Field Application$.MODULE$:LApplication$;
         3: aload_0
         4: invokevirtual #18                 // Method Application$.main:([Ljava/lang/String;)V
         7: return

  public static void delayedInit(scala.Function0<scala.runtime.BoxedUnit>);
    descriptor: (Lscala/Function0;)V
    flags: ACC_PUBLIC, ACC_STATIC
    Code:
      stack=2, locals=1, args_size=1
         0: getstatic     #16                 // Field Application$.MODULE$:LApplication$;
         3: aload_0
         4: invokevirtual #22                 // Method Application$.delayedInit:(Lscala/Function0;)V
         7: return
    Signature: #33                          // (Lscala/Function0<Lscala/runtime/BoxedUnit;>;)V

  public static void delayedEndpoint$Application$1();
    descriptor: ()V
    flags: ACC_PUBLIC, ACC_STATIC
    Code:
      stack=1, locals=0, args_size=0
         0: getstatic     #16                 // Field Application$.MODULE$:LApplication$;
         3: invokevirtual #26                 // Method Application$.delayedEndpoint$Application$1:()V
         6: return

  public static long executionStart();
    descriptor: ()J
    flags: ACC_PUBLIC, ACC_STATIC
    Code:
      stack=2, locals=0, args_size=0
         0: getstatic     #16                 // Field Application$.MODULE$:LApplication$;
         3: invokevirtual #30                 // Method Application$.executionStart:()J
         6: lreturn
}
SourceFile: "Clazz.scala"
RuntimeVisibleAnnotations:
  0: #6(#7=s#8)
Error: unknown attribute
  ScalaSig: length = 0x3
   05 00 00
