Classfile /home/krzysiek/workspace/scala-bcode-cutter/talk_n_blog/clazz/target/scala-2.12/classes/Constructor.class
  Last modified Nov 23, 2017; size 632 bytes
  MD5 checksum 21ace945ef5a5ab6cc652a6dd1f4df5f
  Compiled from "Clazz.scala"
public class Constructor
  minor version: 0
  major version: 52
  flags: ACC_PUBLIC, ACC_SUPER
Constant pool:
   #1 = Utf8               Constructor
   #2 = Class              #1             // Constructor
   #3 = Utf8               java/lang/Object
   #4 = Class              #3             // java/lang/Object
   #5 = Utf8               Clazz.scala
   #6 = Utf8               Lscala/reflect/ScalaSignature;
   #7 = Utf8               bytes
   #8 = Utf8               E1A!\tY1i8tiJ,8\r^8saf[B$PP'\ta5\tBC\n8-7b\tYBB]fVM!\tADy%t =\"\t
   #9 = Utf8               <init>
  #10 = Utf8               ()V
  #11 = NameAndType        #9:#10         // "<init>":()V
  #12 = Methodref          #4.#11         // java/lang/Object."<init>":()V
  #13 = Utf8               scala/Predef$
  #14 = Class              #13            // scala/Predef$
  #15 = Utf8               MODULE$
  #16 = Utf8               Lscala/Predef$;
  #17 = NameAndType        #15:#16        // MODULE$:Lscala/Predef$;
  #18 = Fieldref           #14.#17        // scala/Predef$.MODULE$:Lscala/Predef$;
  #19 = Utf8               Hello!
  #20 = String             #19            // Hello!
  #21 = Utf8               println
  #22 = Utf8               (Ljava/lang/Object;)V
  #23 = NameAndType        #21:#22        // println:(Ljava/lang/Object;)V
  #24 = Methodref          #14.#23        // scala/Predef$.println:(Ljava/lang/Object;)V
  #25 = Utf8               this
  #26 = Utf8               LConstructor;
  #27 = Utf8               Code
  #28 = Utf8               LocalVariableTable
  #29 = Utf8               LineNumberTable
  #30 = Utf8               SourceFile
  #31 = Utf8               RuntimeVisibleAnnotations
  #32 = Utf8               ScalaInlineInfo
  #33 = Utf8               ScalaSig
{
  public Constructor();
    descriptor: ()V
    flags: ACC_PUBLIC
    Code:
      stack=2, locals=1, args_size=1
         0: aload_0
         1: invokespecial #12                 // Method java/lang/Object."<init>":()V
         4: getstatic     #18                 // Field scala/Predef$.MODULE$:Lscala/Predef$;
         7: ldc           #20                 // String Hello!
         9: invokevirtual #24                 // Method scala/Predef$.println:(Ljava/lang/Object;)V
        12: return
      LocalVariableTable:
        Start  Length  Slot  Name   Signature
            0      13     0  this   LConstructor;
      LineNumberTable:
        line 5: 0
        line 2: 4
        line 1: 12
}
SourceFile: "Clazz.scala"
RuntimeVisibleAnnotations:
  0: #6(#7=s#8)
Error: unknown attribute
  ScalaInlineInfo: length = 0x9
   01 00 00 01 00 09 00 0A 00
Error: unknown attribute
  ScalaSig: length = 0x3
   05 00 00
